Workbook
Name BE_shifting: Ranges!$D$4:$D$6
Name DR_shifting: Ranges!$E$4:$E$6
Name none: Ranges!$C$4:$C$6
Name ST_storage: Ranges!$F$5:$F$7

Sheet IESA-Opt database
C3: IESA - NL' energy system database TRANSFORM
D5: By:
E6: TNO Energy and Material Transition
E7: Universiteit Utrecht (UU)
E8: Planbureau voor de Leefomgeving (PBL)
E9: Rijksuniveriteit Groningen (RUG)
D11: Contact persons:
E12: Kira West
E13: Amir Fattahi
D16: Generalities:
E17: All the costs are expressed in 2019 euros [€_2019]. Please take this into consideration when updating data. For this pupose a conversion table is provided in data sources sheet. The red tabs contain data related to the definition of the activities, and their projected volumes within the scenario. The blue tabs contain the technologies, and their descriptions in terms of the required modelling parameters. The yellow tabs contain other parameters relevant for the functioning of the model and this excel file. The data contained in this excel file represents one scenario only. This means that each scenario explored must have its own excel data file.
D19: Name of the scenario:
E20: IESA TRANSFORM Scenario
D22: Storyline of the scenario:

Sheet Data Sources
A1: List of data sources used to build and update the database | H1: Currency conversion
H2: Auxiliar for € adjustment | J2: Data source
A3: No. | B3: Source name | C3: Description | D3: Year | E3: Link to public source [if available] | F3: Link to publication [if available] | H3: Year of € | I3: Equivalent in €_2019 | J3: [ref No.]
A4: 1 | B4: PBL's ENSYSI model database | C4: Data collected from different sources by PBL to build ENSYSI. | D4: 2015 | E4: NA | F4: EFFECTEN VAN DE ENERGIETRANSITIE OP DE REGIONALE ARBEIDSMARKT – EEN QUICKSCAN | H4: 2010 | I4: 0.88715401 | J4: [8]
A5: 2 | B5: COMPETES model database | C5: Data collected from different sources by PBL/ECN based on TYNDP (MAF 2016 & Sustainable Transition) | D5: 2020 | E5: NA | F5: Capacity vs energy subsidies for promoting renewable investment: Benefits and costs for the EU power market | H5: 2011 | I5: 0.90684883 | J5: [8]
A6: 3 | B6: TNO factsheets | C6: Large scale alkalyne electrolyzer factsheet | D6: 2019 | E6: Electrolyzer factsheet | F6: NA | H6: 2012 | I6: 0.93186657 | J6: [8]
A7: 4 | B7: TNO factsheets | C7: Data collected by Remko Detz into the set of factsheets | D7: 2019 | E7: DAC factsheet | F7: NA | H7: 2013 | I7: 0.95253726 | J7: [8]
A8: 5 | B8: TNO factsheets | C8: Data collected by Remko Detz into the set of factsheets | D8: 2019 | E8: FT facsheet (not yet online) | F8: NA | H8: 2014 | I8: 0.96061036 | J8: [8]
A9: 6 | B9: TNO factsheets | C9: Data collected by Remko Detz into the set of factsheets | D9: 2019 | E9: Methanol path factsheet (not yet online) | F9: NA | H9: 2015 | I9: 0.95892477 | J9: [8]
A10: 7 | B10: Cost of storage technologies | C10: Publication (Zakeri and Syri, 2015) | D10: 2015 | E10: NA | F10: Electrical energy storage systems: A comparative life cycle cost analysis | H10: 2016 | I10: 0.96132009 | J10: [8]
A11: 8 | B11: Euro inflation tool | C11: Source from where the euro adjustment parameters where obtained for different years | D11: 2020 | E11: inflationtool | F11: NA | H11: 2017 | I11: 0.97187722 | J11: [8]
A12: 9 | B12: OPERA model database | C12: Data collected from different sources by ECN | D12: 2015 | E12: NA | F12: FLEXNET Report OPERA section | H12: 2018 | I12: 0.9850071 | J12: [8]
A13: 10 | B13: METIS T4 | C13: Maximum clearing price in the APX day ahead electricity market accordingly with European Comission regulations | D13: 2016 | E13: NA | F13: METIS T4 | H13: 2019 | I13: 1 | J13: [8]
A14: 11 | B14: POTENCIA Central Scenario NL | C14: Assumptions used for the services activity volumes in the POTENCIA scenarios by JRC. This data was used to define the heat intensity of the service sectors as well as the drivers. The drivers were directly extracted from the CENTRAL SCENARIO NL database. And the intensities were combined with ENSYSI data to provide the water heating plus HDD function for the heat intensity. The reference HDD used for the reference parameters was of 2900 HDD. | D14: 2019 | E14: Database access | F14: POTENCIA Scenario Report
A15: 12 | B15: POTENCIA Central Scenario | C15: Assumptions and data used for the Transport sectors in the POTENCIA scenario by JRC. We grouped some of the activities and proportionally adjusted the parameters from the POTENCIA database. Most of the data was extracted from the Annual Reports>Transport folder. Given the lack of data on capital costs, data was extracted from different sources and compared/callibrated to provide grouped annual costs similar to the reported by POTENCIA. | D15: 2019 | E15: Database access | F15: POTENCIA Scenario Report
A16: 13 | B16: Methodology to quantify transport emissions | C16: Source to justify accounting only for LTO in aviation within national emissions. | D16: 2019 | F16: Methods for calculating the emissions of transport in the Netherlands
A17: 14 | B17: LTO vs CCD emissions | C17: Source to justify the proxies used for LTO and CCD emissions in aviation for Intra and Extra EU flights. It is not the perfect source, but it works for now. We are using it for the parameters regarding the share of international emmisions in aviation. | D17: 2019 | F17: Paper showing EEA data
A18: 15 | B18: POTENCIA Central Scenario NL | C18: Data extracted to define residential, industry and agriculture activity volumes in the reference scenario | D18: 2019 | E18: Database access | F18: POTENCIA Scenario Report
A19: 16 | B19: Change in HDD in EU countries | C19: Publication (Spinioni et al, 2018) | D19: 2018 | E19: NA | F19: Changes of heating and cooling degree-days in Europe from 1981 to 2100
A20: 17 | B20: ENSPRESO Biomass | C20: Projection on potentials for biomass availability and expected energy prices. Reference scenario. | D20: 2019 | E20: Database access | F20: Bioenergy potentials for EU and neighbouring countries
A21: 18 | B21: Climate and Energy Outlook 2019 | C21: Use of the expected ETS prices developments (2020-2030). | D21: 2019 | E21: KEV table attachment | F21: Climate and Energy Outlook 2019
A22: 19 | B22: CBP ETS valuation projections | C22: Long term projection scenarios on ETS price according with CBP. Mixed with KEV 19 available data on 2020-2030, to complement the long term 2050 picture. | D22: 2016 | F22: Valuation of CO2 emissions in CBA: implications of the scenario study Welfare, Prosperity and the Human Environment
A23: 20 | B23: ENTSOG network | C23: Information about interconnection nodes to the national gas network | D23: 2019 | E23: ENTSOG network map
A24: 21 | B24: NLOG Gas production data | C24: Data about the production of dutch gas fields. Complemented with the policy of closure of the Groningen field by 2022. | D24: 2015 | E24: NLOG data | F24: SP Global Analysis on groningen field closure
A25: 22 | B25: LNG Price estimation | C25: Collection of sources for the estimation of the LNG gas price in Europe | D25: 2019 | F25: CSIS article gathering data from EUROSTAT and US Department of Energy
A26: 23 | B26: TAQA Bergermeer Gas Storage | C26: Operational and project costs data of the operational TAQA gas storage plant | D26: 2015/2020 | E26: TAQA Operational figures | F26: TAQA Project
A27: 24 | B27: Zuidwending Gas Buffer | C27: Operational and project costs data of the operational Zuidwending gas storage plant | D27: 2006/2020 | E27: Public data | F27: Project description
A28: 25 | B28: NL GHG Inventory Report | C28: GHG Emissions in the Netherlands from 1990 to 2017 extracted from the national inventory 2019 | D28: 2019 | F28: Publication with data in tables
A29: 26 | B29: nonCO2 GHG emissions MACCs | C29: Publication with the MACC curves evolution until 2100 for most important nonCO2 GHG emissions in the World. | D29: 2019 | E29: Public data | F29: Publication
A30: 27 | B30: HFC emissions projections | C30: Publication with the expected development of HFC emissions in the world | D30: 2009 | F30: Publication
A31: 28 | B31: Trends in cattle numbers | C31: Historcal trends of cattle evolution in the Netherlands used as criteria to define the evolution of cattle related emissions. This database proposes that cattle numbers will decrease in the future. | D31: 2019 | E31: CBS data
A32: 29 | B32: Trends in agricultural land use in the Netherlands | C32: Thesis from VU exploring land use change in the Netherlands. This study is used to define the driver in N2O agricultural emmisions which assumes a 10% decrease in 2050. | D32: 2012 | F32: Thesis
A33: 30 | B33: Low carbon electricity generation costs | C33: Database from JRC on cost prametes of green electricity sources in Europe | D33: 2017 | E33: Database | F33: Publication
A34: 31 | B34: Compressor costs | C34: Paper with pipeline compressor costs in the USA | D34: 2018 | F34: Publication
A35: 32 | B35: CE Delft Scenarios | C35: Grid for the future scenario report | D35: 2017 | F35: Publication
A36: 33 | B36: TNO Scenarios | C36: Scenarios for a climate neutral energy system (adapt and transform data) | D36: 2020 | E36: Data | F36: Publication
A37: 34 | B37: Nuclear generation data | C37: Corrigendum from nuclear industry (Kan et al. paper) | D37: 2020 | F37: Publication
A38: 35 | B38: Petrochemical sector | C38: Petroleum products balance sheet; supply, consumption and stock | D38: 2017 | E38: Data
A39: 36 | B39: CBS Energy Balance | C39: Energy balance sheet; supply, transformation and consumption | D39: 2019 | E39: Data
A40: 37 | B40: Steel production ECN-MIDDEN | C40: 2050 Decarbonisation of the Dutch Steelmaking Industry (Note: Coke oven gas generation is added to the gas network in the balance used in IESA-Opt) | D40: 2019 | F40: Master Thesis
A41: 38 | B41: Costs of steel productiom | C41: Decarbonization options for the Dutch steel industry | D41: 2019 | F41: Publication
A42: 39 | B42: Ammonia production MIDDEN | C42: Decarbonization options for the Dutch fertilizer industry | D42: 2019 | F42: Publication
A43: 40 | B43: Drivetrain cost share | C43: Share in costs of transport drivetrain | D43: 2014 | F43: Publication
A44: 41 | B44: TNO factsheets | C44: Nuclear Gen III | D44: 2018 | E44: Data
A45: 42 | B45: TNO factsheets | C45: Nuclear SMR | D45: 2018 | E45: Data
A46: 43 | B46: Manufacturing cost analysis of fuel cells | C46: Hydrogen Fuel Cells technologies | D46: 2017 | F46: Publication
A47: 44 | B47: TYNDP ENTSOE | C47: ENSTSOE Scenarios for the TYNDP | D47: 2020 | E47: Data | F47: Publication
A48: 45 | B48: ENTSOE Hydropower | C48: Data on capacities, profiles and operation on different hydropower technologies all over Europe | D48: 2020 | E48: Data
A49: 46 | B49: TNO factsheets | C49: Air-Source Heat Pump | D49: 2019 | E49: Data
A50: 47 | B50: TNO factsheets | C50: Ground-Source Heat Pump | D50: 2019 | E50: Data
A51: 48 | B51: TNO factsheets | C51: Nuclear Gen IV Hydrogen production | D51: 2018 | E51: Data
A52: 49 | B52: IEA Net-Zeroby 2050 | C52: Capacity factors, Financing rates, CAPEX (Nuclear Gen III, Wind offshore) | D52: 2021 | E52: Data
A53: 50 | B53: KEV 2020 | C53: Demand volumes, prices and other GHG | D53: 2020 | F53: Publication
A54: 51 | B54: MIDDEN Steel | C54: Industrial decarbonization report for steel | D54: 2019 | E54: Data | F54: Publication
A55: 52 | B55: MIDDEN Aluminum | C55: Industrial decarbonization report for aluminum | D55: 2019 | E55: Data | F55: Publication
A56: 53 | B56: MIDDEN Zinc | C56: Industrial decarbonization report for zinc | D56: 2019 | E56: Data | F56: Publication
A57: 54 | B57: MIDDEN Fertilizers | C57: Industrial decarbonization report for fertilizers | D57: 2019 | E57: Data | F57: Publication
A58: 55 | B58: MIDDEN HVC | C58: Industrial decarbonization report for HVCs | D58: 2020 | E58: Data | F58: Publication
A59: 56 | B59: MIDDEN Chlor-alkali | C59: Industrial decarbonization report for chlor-alkali | D59: 2021 | E59: Data | F59: Publication
A60: 57 | B60: MIDDEN Ceramics | C60: Industrial decarbonization report for ceramics | D60: 2020 | E60: Data | F60: Publication
A61: 58 | B61: MIDDEN Glass | C61: Industrial decarbonization report for glass | D61: 2019 | E61: Data | F61: Publication
A62: 59 | B62: MIDDEN Paper cardboard | C62: Industrial decarbonization report for paper and cardboard | D62: 2019 | E62: Data | F62: Publication
A63: 60 | B63: TNO factsheets | C63: Syngas from RWGS | D63: 2019 | E63: Data
A64: 61 | B64: TNO factsheets | C64: Fischer Tropsch process | D64: 2019 | E64: Data
A65: 62 | B65: TNO factsheets | C65: Direct production of methanol from H2 and CO2 | D65: 2019 | E65: Data
A66: 63 | B66: Costs of syngas SOEC | C66: Article on valuation of electrolytic syngas | D66: 2013 | F66: Publication
A67: 64 | B67: TNO factsheets | C67: Methanol to olefins | D67: 2021 | E67: Data
A68: 65 | B68: TNO factsheets | C68: Pyrolysis oil from biomass | D68: 2019 | E68: Data
A69: 66 | B69: Biomass gasification | C69: Syngas production from biomass | D69: 2020
A70: 67 | B70: Ethanol dehydration | C70: New feedstock for plastic industry article (Biomass magazine) | D70: 2020 | F70: Publication
A71: 68 | B71: Biomass polymerization | C71: HWWI Research paper on biomass polymerization (PLA) | D71: 2021 | F71: Publication
A72: 69 | B72: TNO factsheets | C72: Alkaline electrolyzer | D72: 2018 | E72: Data
A73: 70 | B73: TNO factsheets | C73: PEM electrolyzer | D73: 2019 | E73: Data
A74: 71 | B74: TNO factsheets | C74: SOE electrolizer | D74: 2020 | E74: Data
A75: 72 | B75: TNO factsheets | C75: Plastic waste pyrolysis | D75: 2020 | E75: Data
A76: 73 | B76: Biomass data EU | C76: JRC bioenergy potentials for EU and neighboring countries | D76: 2015 | E76: Data | F76: Publication
A77: 74 | B77: Plastic Waste NL CE Delft | C77: CE Delft report: Plastic use and processing of plastic waste in the Netherlands. | D77: 2019 | F77: Publication
A78: 75 | B78: TNO factsheets | C78: ANAEROBIC DIGESTION OF WET BIOMASS FOR HEAT GENERATION | D78: 2018 | E78: Data
A79: 76 | B79: TNO factsheets | C79: INDUSTRIAL NATURAL GAS CHP - GAS TURBINES WITH HEAT RECOVERY STEAM GENERATORS | D79: 2020 | E79: Data
A80: 77 | B80: TNO factsheets | C80: HYBRID HEAT PUMP HOUSEHOLDS | D80: 2019 | E80: Data
A81: 78 | B81: TNO factsheets | C81: AIR SOURCE HEAT PUMP | D81: 2019 | E81: Data
A82: 79 | B82: TNO factsheets | C82: Hydrogen (H2) boiler services sector | D82: 2021 | E82: Data
A83: 80 | B83: TNO factsheets | C83: ELECTRIC INDUSTRIAL BOILER | D83: 2018 | E83: Data
A84: 81 | B84: TNO factsheets | C84: HEAT PUMP - AIR TO WATER | D84: 2020 | E84: Data
A85: 82 | B85: TNO factsheets | C85: HEAT PUMP ‐ GROUNDWATER TO WATER | D85: 2020 | E85: Data
A86: 83 | B86: MIDDEN database | C86: Heat generation technologies | D86: 2021 | E86: Data
A87: 84 | B87: MIDDEN database | C87: Basic organic chemicals | D87: 2020
A88: 85 | B88: MIDDEN Polyolefins | C88: Industrial decarbonization report for polyolefins | D88: 2021 | F88: Publication
A89: 86 | B89: MIDDEN PET | C89: Industrial decarbonization report for PTA & PET | D89: 2021 | F89: Publication
A90: 87 | B90: MIDDEN waste incineration | C90: Industrial decarbonization report for waste incineration | D90: 2022 | F90: Publication
A91: 88 | B91: Jeswani et al. 2021 | C91: Life cycle environmental impacts of chemical recycling via pyrolysis of mixed plastic waste in comparison with mechanical recycling and energy recovery, Science of the Total Environment, Vol. 769. | D91: 2021 | F91: Publication
A92: 89 | B92: SDE++ Eindadvies 2022 | C92: Eindadvies basisbedragen SDE++ 2022, PBL | D92: 2022 | F92: Publication
A93: 90 | B93: Volk et al. 2021 | C93: Techno-economic assessment and comparison of different plastic recycling pathways: A German case study, Journal of Industrial Ecology, 25(1): 1-20. | D93: 2021 | F93: Publication
A94: 91 | B94: CE Delft Verkenning Chemische Recycling - Update 2019 | C94: Report about chemical recycling techniques | D94: 2018 | F94: Publication
A95: 92 | B95: Naviroj et al. 2019 | C95: Chemical Recycling of Plastics by Dissolution, University of Pennsylvania | D95: 2019 | F95: Publication
A96: 93 | B96: IERO report | C96: Iron production by electrochemical reduction of its oxide for high CO2 mitigation (IERO), 2016, JRC | D96: 2016 | F96: Publication
A97: 94 | B97: Levi & Cullen 2018 | C97: Mapping Global Flows of Chemicals: From Fossil Fuel Feedstocks to Chemical Productions, Environmental Science & Technology, 52, 4, 1724-1734 | D97: 2018 | F97: Publication
A98: 95 | B98: corRES profiles | C98: Profiles were takne from JoostvStralen | D98: 2024
A99: 96 | B99: Cost of FT and MtJ | C99: Scientific paper | D99: 2024 | F99: Publication
A100: 97 | B100: Cost of biokerosene from HEFA | C100: Scientific paper | D100: 2018 | F100: Publication
...

Sheet Activities
A1: These markets are the activity levels that must be met by the model in each year. The activity balance of the technologies must be equal to these.
C2: Evolution of driver in time | J2: Data source
A3: External drivers (not in AIMMS) | B3: UoA | C3: =Parameters!$B$13 -> 2022 | D3: 2025 | E3: 2030 | F3: 2035 | G3: 2040 | H3: 2045 | I3: 2050 | J3: [ref No.]
A4: Population | B4: [Mpp] | C4: 17.59 | D4: 18.347 | E4: 18.757 | F4: 18.977 | G4: 19.063 | H4: 19.042 | I4: 18.958 | J4: CBS statline (bevolking; kerncijfers), UN Population Division, World Population Prospects 2024
A5: Gross Domestic Product | B5: [M€_2022] | C5: 1146886 | D5: 1167902 | E5: 1274004 | F5: 1366385 | G5: 1477170 | H5: 1608711 | I5: 1747307 | J5: OECD Real GDP long-term forecast
A6: Heat degree days | B6: [HDD] | C6: 2900 | D6: 2850 | E6: 2800 | F6: 2710 | G6: 2620 | H6: 2530 | I6: 2440 | J6: [16]
C7: Evolution of volumes in time | J7: Maximum transformation | K7: Dispatch resolution | L7: Activity Type | M7: Node | N7: Target | O7: Energy Label | P7: Emission Factors | Q7: Share of neutrality | R7: Data source
A8: Activities | B8: UoA | C8: =Parameters!$B$13 -> 2022 | D8: 2025 | E8: 2030 | F8: 2035 | G8: 2040 | H8: 2045 | I8: 2050 | J8: [%/5years] | K8: [type] | L8: [type] | M8: [type] | N8: [y/n] | O8: [type] | P8: [Mton_CO2/PJ] | Q8: [%] | R8: [ref No.]
A9: Electricity demand - Residential | B9: [PJ] | C9: 80.1 | D9: =(D$4/C$4)*C9 -> 83.547169 | E9: =(E$4/D$4)*D9 -> 85.414196 | F9: =(F$4/E$4)*E9 -> 86.416015 | G9: =(G$4/F$4)*F9 -> 86.807635 | H9: =(H$4/G$4)*G9 -> 86.712007 | I9: =(I$4/H$4)*H9 -> 86.329494 | K9: yearly | L9: Driver | M9: NL | N9: 0 | O9: NA | P9: NA | Q9: NA
A10: Houses - Residential Flats | B10: [khouses] | C10: 2916 | D10: =(D4/C4)*C10 -> 3041.4924 | E10: =(E4/D4)*D10 -> 3109.4606 | F10: =(F4/E4)*E10 -> 3145.9313 | G10: =(G4/F4)*F10 -> 3160.1881 | H10: =(H4/G4)*G10 -> 3156.7068 | I10: =(I4/H4)*H10 -> 3142.7816 | K10: yearly | L10: Driver | M10: NL | N10: 0 | O10: NA | P10: NA | Q10: NA
A11: Houses - Residential Terrace | B11: [khouses] | C11: =1019+2361 -> 3380 | D11: =(D4/C4)*C11 -> 3525.4611 | E11: =(E4/D4)*D11 -> 3604.2445 | F11: =(F4/E4)*E11 -> 3646.5185 | G11: =(G4/F4)*F11 -> 3663.0438 | H11: =(H4/G4)*G11 -> 3659.0085 | I11: =(I4/H4)*H11 -> 3642.8675 | K11: yearly | L11: Driver | M11: NL | N11: 0 | O11: NA | P11: NA | Q11: NA
A12: Houses - Residential Dwellings | B12: [khouses] | C12: =1043+704 -> 1747 | D12: =(D4/C4)*C12 -> 1822.1836 | E12: =(E4/D4)*D12 -> 1862.9039 | F12: =(F4/E4)*E12 -> 1884.7538 | G12: =(G4/F4)*F12 -> 1893.2951 | H12: =(H4/G4)*G12 -> 1891.2094 | I12: =(I4/H4)*H12 -> 1882.8667 | K12: yearly | L12: Driver | M12: NL | N12: 0 | O12: NA | P12: NA | Q12: NA
A13: Electricity demand - Services | B13: [PJ] | C13: 124.9 | D13: =D$5/C$5*C13 -> 127.18872 | E13: =E$5/D$5*D13 -> 138.74361 | F13: =F$5/E$5*E13 -> 148.80423 | G13: =G$5/F$5*F13 -> 160.86911 | H13: =H$5/G$5*G13 -> 175.1944 | I13: =I$5/H$5*H13 -> 190.288 | K13: yearly | L13: Driver | M13: NL | N13: 0 | O13: NA | P13: NA | Q13: NA
A14: Space - Services | B14: [Mm2] | C14: =430*1.0203 -> 438.729 | D14: =D$5/C$5*C14 -> 446.76845 | E14: =E$5/D$5*D14 -> 487.35663 | F14: =F$5/E$5*E14 -> 522.696 | G14: =G$5/F$5*F14 -> 565.07562 | H14: =H$5/G$5*G14 -> 615.39523 | I14: =I$5/H$5*H14 -> 668.41365 | K14: yearly | L14: Driver | M14: NL | N14: 0 | O14: NA | P14: NA | Q14: NA
A15: Electricity demand - Agricuture | B15: [PJ] | C15: 25.2 | D15: =D$5/C$5*C15 -> 25.661775 | E15: =E$5/D$5*D15 -> 27.993106 | F15: =F$5/E$5*E15 -> 30.022951 | G15: =G$5/F$5*F15 -> 32.457179 | H15: =H$5/G$5*G15 -> 35.347469 | I15: =I$5/H$5*H15 -> 38.392775 | K15: yearly | L15: Driver | M15: NL | N15: 0 | O15: NA | P15: NA | Q15: NA
A16: Heat demand - Agriculture | B16: [PJ] | C16: =39.7+14.2+20.7*0.9 -> 72.53 | D16: =C16 -> 72.53 | E16: =D16 -> 72.53 | F16: =E16 -> 72.53 | G16: =F16 -> 72.53 | H16: =G16 -> 72.53 | I16: =H16 -> 72.53 | K16: yearly | L16: Driver | M16: NL | N16: 0 | O16: NA | P16: NA | Q16: NA
A17: Machinery - Agriculture | B17: [PJ] | C17: 25.2 | D17: =C17 -> 25.2 | E17: =D17 -> 25.2 | F17: =E17 -> 25.2 | G17: =F17 -> 25.2 | H17: =G17 -> 25.2 | I17: =H17 -> 25.2 | K17: yearly | L17: Driver | M17: NL | N17: 0 | O17: NA | P17: NA | Q17: NA
A18: Steel production - Basic Metals Industry | B18: [Mton_Steel] | C18: 6.143 | D18: =(C18)*(1+$T$2)^(D$8-C$8) -> 6.143 | E18: =(D18)*(1+$T$2)^(E$8-D$8) -> 6.143 | F18: =(E18)*(1+$T$2)^(F$8-E$8) -> 6.143 | G18: =(F18)*(1+$T$2)^(G$8-F$8) -> 6.143 | H18: =(G18)*(1+$T$2)^(H$8-G$8) -> 6.143 | I18: =(H18)*(1+$T$2)^(I$8-H$8) -> 6.143 | K18: yearly | L18: Driver | M18: NL | N18: 0 | O18: NA | P18: NA | Q18: NA
A19: Nitric Acid production - Fertilizers Industry | B19: [Mton_AN] | C19: 2.4 | D19: =(C19)*(1+$T$2)^(D$8-C$8) -> 2.4 | E19: =(D19)*(1+$T$2)^(E$8-D$8) -> 2.4 | F19: =(E19)*(1+$T$2)^(F$8-E$8) -> 2.4 | G19: =(F19)*(1+$T$2)^(G$8-F$8) -> 2.4 | H19: =(G19)*(1+$T$2)^(H$8-G$8) -> 2.4 | I19: =(H19)*(1+$T$2)^(I$8-H$8) -> 2.4 | K19: yearly | L19: Driver | M19: NL | N19: 0 | O19: NA | P19: NA | Q19: NA
A20: Urea production - Fertilizers Industry | B20: [Mton_Urea] | C20: 1.8 | D20: =(C20)*(1+$T$2)^(D$8-C$8) -> 1.8 | E20: =(D20)*(1+$T$2)^(E$8-D$8) -> 1.8 | F20: =(E20)*(1+$T$2)^(F$8-E$8) -> 1.8 | G20: =(F20)*(1+$T$2)^(G$8-F$8) -> 1.8 | H20: =(G20)*(1+$T$2)^(H$8-G$8) -> 1.8 | I20: =(H20)*(1+$T$2)^(I$8-H$8) -> 1.8 | K20: yearly | L20: Driver | M20: NL | N20: 0 | O20: NA | P20: NA | Q20: NA
A21: Other Ammonia based fertilizers - Fertilizers Industry | B21: [Mton_NH3] | C21: 1.2 | D21: =(C21)*(1+$T$2)^(D$8-C$8) -> 1.2 | E21: =(D21)*(1+$T$2)^(E$8-D$8) -> 1.2 | F21: =(E21)*(1+$T$2)^(F$8-E$8) -> 1.2 | G21: =(F21)*(1+$T$2)^(G$8-F$8) -> 1.2 | H21: =(G21)*(1+$T$2)^(H$8-G$8) -> 1.2 | I21: =(H21)*(1+$T$2)^(I$8-H$8) -> 1.2 | K21: yearly | L21: Driver | M21: NL | N21: 0 | O21: NA | P21: NA | Q21: NA
A22: Ethylene production - Chemical Industry | B22: [Mton_Ey] | C22: =2.4+EnergyBalance!$CS$71*Activities!$C$26+EnergyBalance!$CS$72*Activities!$C$27+EnergyBalance!$CS$73*Activities!$C$28+EnergyBalance!$CS$80*Activities!$C$31+EnergyBalance!$CS$87*Activities!$C$33+EnergyBalance!$CS$87*EnergyBalance!$CZ$88*EnergyBalance!$DA$79*Activities!$C$32 -> 0.4003093 | D22: =(C22)*(1+$T$2)^(D$8-C$8) -> 0.4003093 | E22: =(D22)*(1+$T$2)^(E$8-D$8) -> 0.4003093 | F22: =(E22)*(1+$T$2)^(F$8-E$8) -> 0.4003093 | G22: =(F22)*(1+$T$2)^(G$8-F$8) -> 0.4003093 | H22: =(G22)*(1+$T$2)^(H$8-G$8) -> 0.4003093 | I22: =(H22)*(1+$T$2)^(I$8-H$8) -> 0.4003093 | K22: yearly | L22: Driver | M22: NL | N22: 0 | O22: NA | P22: NA | Q22: NA
A23: Propylene production - Chemical Industry | B23: [Mton_Py] | C23: =2.4*(0.136/0.303)-C29*1.02+0.5 -> 0.96522772 | D23: =(C23)*(1+$T$2)^(D$8-C$8) -> 0.96522772 | E23: =(D23)*(1+$T$2)^(E$8-D$8) -> 0.96522772 | F23: =(E23)*(1+$T$2)^(F$8-E$8) -> 0.96522772 | G23: =(F23)*(1+$T$2)^(G$8-F$8) -> 0.96522772 | H23: =(G23)*(1+$T$2)^(H$8-G$8) -> 0.96522772 | I23: =(H23)*(1+$T$2)^(I$8-H$8) -> 0.96522772 | K23: yearly | L23: Driver | M23: NL | N23: 0 | O23: NA | P23: NA | Q23: NA
A24: Butadiene production - Chemical Industry | B24: [Mton_Butadiene] | C24: =0.43/3*2.4 -> 0.344 | D24: =(C24)*(1+$T$2)^(D$8-C$8) -> 0.344 | E24: =(D24)*(1+$T$2)^(E$8-D$8) -> 0.344 | F24: =(E24)*(1+$T$2)^(F$8-E$8) -> 0.344 | G24: =(F24)*(1+$T$2)^(G$8-F$8) -> 0.344 | H24: =(G24)*(1+$T$2)^(H$8-G$8) -> 0.344 | I24: =(H24)*(1+$T$2)^(I$8-H$8) -> 0.344 | K24: yearly | L24: Driver | M24: NL | N24: 0 | O24: NA | P24: NA | Q24: NA
A25: BTX aromatics production - Chemical Industry | B25: [Mton_BTX] | C25: 3 | D25: =(C25)*(1+$T$2)^(D$8-C$8) -> 3 | E25: =(D25)*(1+$T$2)^(E$8-D$8) -> 3 | F25: =(E25)*(1+$T$2)^(F$8-E$8) -> 3 | G25: =(F25)*(1+$T$2)^(G$8-F$8) -> 3 | H25: =(G25)*(1+$T$2)^(H$8-G$8) -> 3 | I25: =(H25)*(1+$T$2)^(I$8-H$8) -> 3 | K25: yearly | L25: Driver | M25: NL | N25: 0 | O25: NA | P25: NA | Q25: NA
A26: LDPE production - Chemical Industry | B26: [Mton_LDPE] | C26: =0.73/3*2.4 -> 0.584 | D26: =(C26)*(1+$T$2)^(D$8-C$8) -> 0.584 | E26: =(D26)*(1+$T$2)^(E$8-D$8) -> 0.584 | F26: =(E26)*(1+$T$2)^(F$8-E$8) -> 0.584 | G26: =(F26)*(1+$T$2)^(G$8-F$8) -> 0.584 | H26: =(G26)*(1+$T$2)^(H$8-G$8) -> 0.584 | I26: =(H26)*(1+$T$2)^(I$8-H$8) -> 0.584 | K26: yearly | L26: Driver | M26: NL | N26: 0 | O26: NA | P26: NA | Q26: NA
A27: LLDPE production - Chemical Industry | B27: [Mton_LLDPE] | C27: =0.8/3*2.4 -> 0.64 | D27: =(C27)*(1+$T$2)^(D$8-C$8) -> 0.64 | E27: =(D27)*(1+$T$2)^(E$8-D$8) -> 0.64 | F27: =(E27)*(1+$T$2)^(F$8-E$8) -> 0.64 | G27: =(F27)*(1+$T$2)^(G$8-F$8) -> 0.64 | H27: =(G27)*(1+$T$2)^(H$8-G$8) -> 0.64 | I27: =(H27)*(1+$T$2)^(I$8-H$8) -> 0.64 | K27: yearly | L27: Driver | M27: NL | N27: 0 | O27: NA | P27: NA | Q27: NA
A28: HDPE production - Chemical Industry | B28: [Mton_HDPE] | C28: =0.31/3*2.4 -> 0.248 | D28: =(C28)*(1+$T$2)^(D$8-C$8) -> 0.248 | E28: =(D28)*(1+$T$2)^(E$8-D$8) -> 0.248 | F28: =(E28)*(1+$T$2)^(F$8-E$8) -> 0.248 | G28: =(F28)*(1+$T$2)^(G$8-F$8) -> 0.248 | H28: =(G28)*(1+$T$2)^(H$8-G$8) -> 0.248 | I28: =(H28)*(1+$T$2)^(I$8-H$8) -> 0.248 | K28: yearly | L28: Driver | M28: NL | N28: 0 | O28: NA | P28: NA | Q28: NA
A29: Polypropylene production - Chemical Industry | B29: [Mton_PP] | C29: =0.75/3*2.4 -> 0.6 | D29: =(C29)*(1+$T$2)^(D$8-C$8) -> 0.6 | E29: =(D29)*(1+$T$2)^(E$8-D$8) -> 0.6 | F29: =(E29)*(1+$T$2)^(F$8-E$8) -> 0.6 | G29: =(F29)*(1+$T$2)^(G$8-F$8) -> 0.6 | H29: =(G29)*(1+$T$2)^(H$8-G$8) -> 0.6 | I29: =(H29)*(1+$T$2)^(I$8-H$8) -> 0.6 | K29: yearly | L29: Driver | M29: NL | N29: 0 | O29: NA | P29: NA | Q29: NA
A30: PTA production - Chemical Industry | B30: [Mton_PTA] | C30: =0.342/3*2.4 -> 0.2736 | D30: =(C30)*(1+$T$2)^(D$8-C$8) -> 0.2736 | E30: =(D30)*(1+$T$2)^(E$8-D$8) -> 0.2736 | F30: =(E30)*(1+$T$2)^(F$8-E$8) -> 0.2736 | G30: =(F30)*(1+$T$2)^(G$8-F$8) -> 0.2736 | H30: =(G30)*(1+$T$2)^(H$8-G$8) -> 0.2736 | I30: =(H30)*(1+$T$2)^(I$8-H$8) -> 0.2736 | K30: yearly | L30: Driver | M30: NL | N30: 0 | O30: NA | P30: NA | Q30: NA
A31: PVC production - Chemical Industry | B31: [Mton_PVC] | C31: =0.75/3*2.4 -> 0.6 | D31: =(C31)*(1+$T$2)^(D$8-C$8) -> 0.6 | E31: =(D31)*(1+$T$2)^(E$8-D$8) -> 0.6 | F31: =(E31)*(1+$T$2)^(F$8-E$8) -> 0.6 | G31: =(F31)*(1+$T$2)^(G$8-F$8) -> 0.6 | H31: =(G31)*(1+$T$2)^(H$8-G$8) -> 0.6 | I31: =(H31)*(1+$T$2)^(I$8-H$8) -> 0.6 | K31: yearly | L31: Driver | M31: NL | N31: 0 | O31: NA | P31: NA | Q31: NA
A32: Polyester production - Chemical Industry | B32: [Mton_material] | C32: =0.426/3*2.4 -> 0.3408 | D32: =(C32)*(1+$T$2)^(D$8-C$8) -> 0.3408 | E32: =(D32)*(1+$T$2)^(E$8-D$8) -> 0.3408 | F32: =(E32)*(1+$T$2)^(F$8-E$8) -> 0.3408 | G32: =(F32)*(1+$T$2)^(G$8-F$8) -> 0.3408 | H32: =(G32)*(1+$T$2)^(H$8-G$8) -> 0.3408 | I32: =(H32)*(1+$T$2)^(I$8-H$8) -> 0.3408 | K32: yearly | L32: Driver | M32: NL | N32: 0 | O32: NA | P32: NA | Q32: NA
A33: Ethylene oxide production - Chemical Industry | B33: [Mton_EO] | C33: =0.183/3*2.4 -> 0.1464 | D33: =(C33)*(1+$T$2)^(D$8-C$8) -> 0.1464 | E33: =(D33)*(1+$T$2)^(E$8-D$8) -> 0.1464 | F33: =(E33)*(1+$T$2)^(F$8-E$8) -> 0.1464 | G33: =(F33)*(1+$T$2)^(G$8-F$8) -> 0.1464 | H33: =(G33)*(1+$T$2)^(H$8-G$8) -> 0.1464 | I33: =(H33)*(1+$T$2)^(I$8-H$8) -> 0.1464 | K33: yearly | L33: Driver | M33: NL | N33: 0 | O33: NA | P33: NA | Q33: NA
A34: Chlorine production - Chemical Industry | B34: [Mton_CL2] | C34: 1 | D34: =(C34)*(1+$T$2)^(D$8-C$8) -> 1 | E34: =(D34)*(1+$T$2)^(E$8-D$8) -> 1 | F34: =(E34)*(1+$T$2)^(F$8-E$8) -> 1 | G34: =(F34)*(1+$T$2)^(G$8-F$8) -> 1 | H34: =(G34)*(1+$T$2)^(H$8-G$8) -> 1 | I34: =(H34)*(1+$T$2)^(I$8-H$8) -> 1 | K34: yearly | L34: Driver | M34: NL | N34: 0 | O34: NA | P34: NA | Q34: NA
A35: Other ETS chemicals - Chemical Industry | B35: [Idx_2020] | C35: 1 | D35: =(C35)*(1+$T$2)^(D$8-C$8) -> 1 | E35: =(D35)*(1+$T$2)^(E$8-D$8) -> 1 | F35: =(E35)*(1+$T$2)^(F$8-E$8) -> 1 | G35: =(F35)*(1+$T$2)^(G$8-F$8) -> 1 | H35: =(G35)*(1+$T$2)^(H$8-G$8) -> 1 | I35: =(H35)*(1+$T$2)^(I$8-H$8) -> 1 | K35: yearly | L35: Driver | M35: NL | N35: 0 | O35: NA | P35: NA | Q35: NA
A36: Glass production - ETS Industry | B36: [Mton_Glass] | C36: 0.92 | D36: =(C36)*(1+$T$2)^(D$8-C$8) -> 0.92 | E36: =(D36)*(1+$T$2)^(E$8-D$8) -> 0.92 | F36: =(E36)*(1+$T$2)^(F$8-E$8) -> 0.92 | G36: =(F36)*(1+$T$2)^(G$8-F$8) -> 0.92 | H36: =(G36)*(1+$T$2)^(H$8-G$8) -> 0.92 | I36: =(H36)*(1+$T$2)^(I$8-H$8) -> 0.92 | K36: yearly | L36: Driver | M36: NL | N36: 0 | O36: NA | P36: NA | Q36: NA
A37: Ceramics production -ETS Industry | B37: [Mton_Ceramics] | C37: =(2.39+2.94)/2 -> 2.665 | D37: =(C37)*(1+$T$2)^(D$8-C$8) -> 2.665 | E37: =(D37)*(1+$T$2)^(E$8-D$8) -> 2.665 | F37: =(E37)*(1+$T$2)^(F$8-E$8) -> 2.665 | G37: =(F37)*(1+$T$2)^(G$8-F$8) -> 2.665 | H37: =(G37)*(1+$T$2)^(H$8-G$8) -> 2.665 | I37: =(H37)*(1+$T$2)^(I$8-H$8) -> 2.665 | K37: yearly | L37: Driver | M37: NL | N37: 0 | O37: NA | P37: NA | Q37: NA
A38: Paper production - ETS Industry | B38: [Mton_Paper] | C38: 1.015 | D38: =(C38)*(1+$T$2)^(D$8-C$8) -> 1.015 | E38: =(D38)*(1+$T$2)^(E$8-D$8) -> 1.015 | F38: =(E38)*(1+$T$2)^(F$8-E$8) -> 1.015 | G38: =(F38)*(1+$T$2)^(G$8-F$8) -> 1.015 | H38: =(G38)*(1+$T$2)^(H$8-G$8) -> 1.015 | I38: =(H38)*(1+$T$2)^(I$8-H$8) -> 1.015 | K38: yearly | L38: Driver | M38: NL | N38: 0 | O38: NA | P38: NA | Q38: NA
A39: Board production - ETS Industry | B39: [Mton_board] | C39: 1.855 | D39: =(C39)*(1+$T$2)^(D$8-C$8) -> 1.855 | E39: =(D39)*(1+$T$2)^(E$8-D$8) -> 1.855 | F39: =(E39)*(1+$T$2)^(F$8-E$8) -> 1.855 | G39: =(F39)*(1+$T$2)^(G$8-F$8) -> 1.855 | H39: =(G39)*(1+$T$2)^(H$8-G$8) -> 1.855 | I39: =(H39)*(1+$T$2)^(I$8-H$8) -> 1.855 | K39: yearly | L39: Driver | M39: NL | N39: 0 | O39: NA | P39: NA | Q39: NA
A40: Food production - non-ETS Industry | B40: [Idx_2020] | C40: 1 | D40: =(C40)*(1+$T$2)^(D$8-C$8) -> 1 | E40: =(D40)*(1+$T$2)^(E$8-D$8) -> 1 | F40: =(E40)*(1+$T$2)^(F$8-E$8) -> 1 | G40: =(F40)*(1+$T$2)^(G$8-F$8) -> 1 | H40: =(G40)*(1+$T$2)^(H$8-G$8) -> 1 | I40: =(H40)*(1+$T$2)^(I$8-H$8) -> 1 | K40: yearly | L40: Driver | M40: NL | N40: 0 | O40: NA | P40: NA | Q40: NA
A41: Other ETS - Industry | B41: [Idx_2020] | C41: 1 | D41: =(C41)*(1+$T$2)^(D$8-C$8) -> 1 | E41: =(D41)*(1+$T$2)^(E$8-D$8) -> 1 | F41: =(E41)*(1+$T$2)^(F$8-E$8) -> 1 | G41: =(F41)*(1+$T$2)^(G$8-F$8) -> 1 | H41: =(G41)*(1+$T$2)^(H$8-G$8) -> 1 | I41: =(H41)*(1+$T$2)^(I$8-H$8) -> 1 | K41: yearly | L41: Driver | M41: NL | N41: 0 | O41: NA | P41: NA | Q41: NA
A42: Other non-ETS - Industry | B42: [Idx_2020] | C42: 1 | D42: =(C42)*(1+$T$2)^(D$8-C$8) -> 1 | E42: =(D42)*(1+$T$2)^(E$8-D$8) -> 1 | F42: =(E42)*(1+$T$2)^(F$8-E$8) -> 1 | G42: =(F42)*(1+$T$2)^(G$8-F$8) -> 1 | H42: =(G42)*(1+$T$2)^(H$8-G$8) -> 1 | I42: =(H42)*(1+$T$2)^(I$8-H$8) -> 1 | K42: yearly | L42: Driver | M42: NL | N42: 0 | O42: NA | P42: NA | Q42: NA
A43: Machinery - Industry | B43: [PJ] | C43: 25.4 | D43: =(C43)*(1+$T$2)^(D$8-C$8) -> 25.4 | E43: =(D43)*(1+$T$2)^(E$8-D$8) -> 25.4 | F43: =(E43)*(1+$T$2)^(F$8-E$8) -> 25.4 | G43: =(F43)*(1+$T$2)^(G$8-F$8) -> 25.4 | H43: =(G43)*(1+$T$2)^(H$8-G$8) -> 25.4 | I43: =(H43)*(1+$T$2)^(I$8-H$8) -> 25.4 | K43: yearly | L43: Driver | M43: NL | N43: 0 | O43: NA | P43: NA | Q43: NA
A44: Waste Management | B44: [Mton_Waste] | C44: 8.34 | D44: =C44 -> 8.34 | E44: =D44 -> 8.34 | F44: =E44 -> 8.34 | G44: =F44 -> 8.34 | H44: =G44 -> 8.34 | I44: =H44 -> 8.34 | K44: yearly | L44: Driver | M44: NL | N44: 0 | O44: NA | P44: NA | Q44: NA
A45: Motorcycles | B45: [Gvkm] | C45: =5.1*1.035 -> 5.2785 | D45: =(D$4/C$4)*C45 -> 5.5056646 | E45: =(E$4/D$4)*D45 -> 5.6286995 | F45: =(F$4/E$4)*E45 -> 5.6947183 | G45: =(G$4/F$4)*F45 -> 5.7205256 | H45: =(H$4/G$4)*G45 -> 5.7142238 | I45: =(I$4/H$4)*H45 -> 5.6890167 | K45: yearly | L45: Driver | M45: NL | N45: 0 | O45: NA | P45: NA | Q45: NA | T45: =SUM(C45:C48,SUM(C49:C51)/10^3) -> 135.2625 | U45: =SUM(D45:D48,SUM(D49:D51)/10^3) -> 141.08363 | V45: =SUM(E45:E48,SUM(E49:E51)/10^3) -> 144.23642 | W45: =SUM(F45:F48,SUM(F49:F51)/10^3) -> 145.92817 | X45: =SUM(G45:G48,SUM(G49:G51)/10^3) -> 146.58948 | Y45: =SUM(H45:H48,SUM(H49:H51)/10^3) -> 146.428 | Z45: =SUM(I45:I48,SUM(I49:I51)/10^3) -> 145.78206
A46: Passenger Cars | B46: [Gvkm] | C46: 102.7 | D46: =(D$4/C$4)*C46 -> 107.11978 | E46: =(E$4/D$4)*D46 -> 109.51358 | F46: =(F$4/E$4)*E46 -> 110.79806 | G46: =(G$4/F$4)*F46 -> 111.30018 | H46: =(H$4/G$4)*G46 -> 111.17757 | I46: =(I$4/H$4)*H46 -> 110.68713 | K46: yearly | L46: Driver | M46: NL | N46: 0 | O46: NA | P46: NA | Q46: NA
A47: Light-Duty Vehicles | B47: [Gvkm] | C47: 18.94 | D47: =(D$4/C$4)*C47 -> 19.755098 | E47: =(E$4/D$4)*D47 -> 20.196565 | F47: =(F$4/E$4)*E47 -> 20.43345 | G47: =(G$4/F$4)*F47 -> 20.52605 | H47: =(H$4/G$4)*G47 -> 20.503438 | I47: =(I$4/H$4)*H47 -> 20.412991 | K47: yearly | L47: Driver | M47: NL | N47: 0 | O47: NA | P47: NA | Q47: NA
A48: Heavy-Duty Vehicles | B48: [Gvkm] | C48: =2.034+5.595 -> 7.629 | D48: =(D$4/C$4)*C48 -> 7.9573202 | E48: =(E$4/D$4)*D48 -> 8.1351423 | F48: =(F$4/E$4)*E48 -> 8.230559 | G48: =(G$4/F$4)*F48 -> 8.2678583 | H48: =(H$4/G$4)*G48 -> 8.2587503 | I48: =(I$4/H$4)*H48 -> 8.2223185 | K48: yearly | L48: Driver | M48: NL | N48: 0 | O48: NA | P48: NA | Q48: NA
A49: Buses | B49: [Mvkm] | C49: 490 | D49: =(D$4/C$4)*C49 -> 511.08755 | E49: =(E$4/D$4)*D49 -> 522.50881 | F49: =(F$4/E$4)*E49 -> 528.63729 | G49: =(G$4/F$4)*F49 -> 531.03297 | H49: =(H$4/G$4)*G49 -> 530.44798 | I49: =(I$4/H$4)*H49 -> 528.10802 | K49: yearly | L49: Driver | M49: NL | N49: 0 | O49: NA | P49: NA | Q49: NA
A50: Rail | B50: [Mvkm] | C50: 170 | D50: =(D$4/C$4)*C50 -> 177.31609 | E50: =(E$4/D$4)*D50 -> 181.27857 | F50: =(F$4/E$4)*E50 -> 183.40478 | G50: =(G$4/F$4)*F50 -> 184.23593 | H50: =(H$4/G$4)*G50 -> 184.03297 | I50: =(I$4/H$4)*H50 -> 183.22115 | K50: yearly | L50: Driver | M50: NL | N50: 0 | O50: NA | P50: NA | Q50: NA
A51: Domestic Navigation | B51: [Mvkm] | C51: 55 | D51: =(D$4/C$4)*C51 -> 57.36697 | E51: =(E$4/D$4)*D51 -> 58.648948 | F51: =(F$4/E$4)*E51 -> 59.336839 | G51: =(G$4/F$4)*F51 -> 59.605742 | H51: =(H$4/G$4)*G51 -> 59.54008 | I51: =(I$4/H$4)*H51 -> 59.27743 | K51: yearly | L51: Driver | M51: NL | N51: 0 | O51: NA | P51: NA | Q51: NA
A52: Other Transport | B52: [PJ] | C52: 0.4 | D52: =(D$4/C$4)*C52 -> 0.41721433 | E52: =(E$4/D$4)*D52 -> 0.42653781 | F52: =(F$4/E$4)*E52 -> 0.43154065 | G52: =(G$4/F$4)*F52 -> 0.4334963 | H52: =(H$4/G$4)*G52 -> 0.43301876 | I52: =(I$4/H$4)*H52 -> 0.43110858 | K52: yearly | L52: Driver | M52: NL | N52: 0 | O52: NA | P52: NA | Q52: NA
A53: Bunker Aviation | B53: [Mvkm] | C53: 580 | D53: =ROUND((C53+E53)/2,2) -> 580 | E53: =C53 -> 580 | F53: =ROUND((E53+G53)/2,2) -> 580 | G53: =ROUND((E53+I53)/2,2) -> 580 | H53: =ROUND((G53+I53)/2,2) -> 580 | I53: =E53 -> 580 | K53: yearly | L53: Driver | M53: NL | N53: 0 | O53: NA | P53: NA | Q53: NA
A54: Bunker Navigation | B54: [Mvkm] | C54: 110 | D54: =ROUND((C54+E54)/2,2) -> 110 | E54: =C54 -> 110 | F54: =ROUND((E54+G54)/2,2) -> 110 | G54: =ROUND((E54+I54)/2,2) -> 110 | H54: =ROUND((G54+I54)/2,2) -> 110 | I54: =E54 -> 110 | K54: yearly | L54: Driver | M54: NL | N54: 0 | O54: NA | P54: NA | Q54: NA
A55: neGHG - Residential - CO2 | B55: [Mton_CO2e] | C55: 0.4 | D55: =ROUND((C55+E55)/2,2) -> 0.35 | E55: 0.299 | F55: =ROUND((E55+G55)/2,2) -> 0.3 | G55: =ROUND((E55+I55)/2,2) -> 0.3 | H55: =ROUND((G55+I55)/2,2) -> 0.3 | I55: 0.303 | K55: yearly | L55: Driver | M55: NL | N55: 0 | O55: NA | P55: NA | Q55: NA
A56: neGHG - Services - CH4 | B56: [Mton_CO2e] | C56: 0.3 | D56: =ROUND((C56+E56)/2,2) -> 0.34 | E56: 0.388 | F56: =ROUND((E56+G56)/2,2) -> 0.37 | G56: =ROUND((E56+I56)/2,2) -> 0.35 | H56: =ROUND((G56+I56)/2,2) -> 0.34 | I56: 0.321 | K56: yearly | L56: Driver | M56: NL | N56: 0 | O56: NA | P56: NA | Q56: NA
A57: neGHG - Agriculture - CO2 | B57: [Mton_CO2e] | C57: 0.3 | D57: =ROUND((C57+E57)/2,2) -> 0.26 | E57: 0.213 | F57: =ROUND((E57+G57)/2,2) -> 0.2 | G57: =ROUND((E57+I57)/2,2) -> 0.19 | H57: =ROUND((G57+I57)/2,2) -> 0.18 | I57: 0.166 | K57: yearly | L57: Driver | M57: NL | N57: 0 | O57: NA | P57: NA | Q57: NA
A58: neGHG - Agriculture - CH4 | B58: [Mton_CO2e] | C58: 12.6 | D58: =ROUND((C58+E58)/2,2) -> 10.24 | E58: 7.87 | F58: =ROUND((E58+G58)/2,2) -> 7.43 | G58: =ROUND((E58+I58)/2,2) -> 6.99 | H58: =ROUND((G58+I58)/2,2) -> 6.55 | I58: 6.11 | K58: yearly | L58: Driver | M58: NL | N58: 0 | O58: NA | P58: NA | Q58: NA
A59: neGHG - Agriculture - N2O | B59: [Mton_CO2e] | C59: 4.5 | D59: =ROUND((C59+E59)/2,2) -> 4.03 | E59: 3.56 | F59: =ROUND((E59+G59)/2,2) -> 3.32 | G59: =ROUND((E59+I59)/2,2) -> 3.07 | H59: =ROUND((G59+I59)/2,2) -> 2.83 | I59: 2.58 | K59: yearly | L59: Driver | M59: NL | N59: 0 | O59: NA | P59: NA | Q59: NA
A60: neGHG - Industry - Chemical - CO2 | B60: [Mton_CO2e] | C60: 0.9 | D60: =ROUND((C60+E60)/2,2) -> 0.85 | E60: 0.802 | F60: =ROUND((E60+G60)/2,2) -> 0.75 | G60: =ROUND((E60+I60)/2,2) -> 0.7 | H60: =ROUND((G60+I60)/2,2) -> 0.65 | I60: 0.602 | K60: yearly | L60: Driver | M60: NL | N60: 0 | O60: NA | P60: NA | Q60: NA
A61: neGHG - Industry - Other - CO2 | B61: [Mton_CO2e] | C61: 0.9 | D61: =ROUND((C61+E61)/2,2) -> 0.78 | E61: 0.669 | F61: =ROUND((E61+G61)/2,2) -> 0.67 | G61: =ROUND((E61+I61)/2,2) -> 0.68 | H61: =ROUND((G61+I61)/2,2) -> 0.69 | I61: 0.696 | K61: yearly | L61: Driver | M61: NL | N61: 0 | O61: NA | P61: NA | Q61: NA
A62: neGHG - Industry - CH4 | B62: [Mton_CO2e] | C62: 2.6 | D62: =ROUND((C62+E62)/2,2) -> 2.62 | E62: 2.64 | F62: =ROUND((E62+G62)/2,2) -> 2.32 | G62: =ROUND((E62+I62)/2,2) -> 2 | H62: =ROUND((G62+I62)/2,2) -> 1.68 | I62: 1.35 | K62: yearly | L62: Driver | M62: NL | N62: 0 | O62: NA | P62: NA | Q62: NA
A63: neGHG - Industry - N2O | B63: [Mton_CO2e] | C63: 1 | D63: =ROUND((C63+E63)/2,2) -> 0.69 | E63: 0.381 | F63: =ROUND((E63+G63)/2,2) -> 0.38 | G63: =ROUND((E63+I63)/2,2) -> 0.37 | H63: =ROUND((G63+I63)/2,2) -> 0.36 | I63: 0.359 | K63: yearly | L63: Driver | M63: NL | N63: 0 | O63: NA | P63: NA | Q63: NA
A64: neGHG - Industry - F-gas | B64: [Mton_CO2e] | C64: 1.5 | D64: =ROUND((C64+E64)/2,2) -> 1.13 | E64: 0.767 | F64: =ROUND((E64+G64)/2,2) -> 0.71 | G64: =ROUND((E64+I64)/2,2) -> 0.65 | H64: =ROUND((G64+I64)/2,2) -> 0.6 | I64: 0.541 | K64: yearly | L64: Driver | M64: NL | N64: 0 | O64: NA | P64: NA | Q64: NA
A65: neGHG - Transport - CH4 | B65: [Mton_CO2e] | C65: 0.08 | D65: =ROUND((C65+E65)/2,2) -> 0.07 | E65: 0.06 | F65: =ROUND((E65+G65)/2,2) -> 0.05 | G65: =ROUND((E65+I65)/2,2) -> 0.04 | H65: =ROUND((G65+I65)/2,2) -> 0.03 | I65: 0.011 | K65: yearly | L65: Driver | M65: NL | N65: 0 | O65: NA | P65: NA | Q65: NA
A66: neGHG - Transport - N2O | B66: [Mton_CO2e] | C66: 1.1 | D66: =ROUND((C66+E66)/2,2) -> 0.64 | E66: 0.175 | F66: =ROUND((E66+G66)/2,2) -> 0.15 | G66: =ROUND((E66+I66)/2,2) -> 0.13 | H66: =ROUND((G66+I66)/2,2) -> 0.11 | I66: 0.084 | K66: yearly | L66: Driver | M66: NL | N66: 0 | O66: NA | P66: NA | Q66: NA
... A68: neGHG - LULUCF | B68: [Mton_CO2e] | C68: 2.5 | D68: =ROUND((C68+E68)/2,2) -> 3.08 | E68: 3.66 | F68: =ROUND((E68+G68)/2,2) -> 3.41 | G68: =ROUND((E68+I68)/2,2) -> 3.16 | H68: =ROUND((G68+I68)/2,2) -> 2.91 | I68: 2.66 | K68: yearly | L68: Driver | M68: NL | N68: 0 | O68: NA | P68: NA | Q68: NA
A69: Natural Gas Exports | B69: [PJ] | C69: 1198 | D69: =ROUND((C69+E69)/2,2) -> 1198 | E69: =C69 -> 1198 | F69: =ROUND((E69+G69)/2,2) -> 898.5 | G69: =ROUND((E69+I69)/2,2) -> 599 | H69: =ROUND((G69+I69)/2,2) -> 299.5 | I69: 0 | K69: yearly | L69: Driver | M69: EU | N69: 0 | O69: NA | P69: 0.0566 | Q69: 0
A70: Naphtha Exports | B70: [PJ] | C70: 556 | D70: =ROUND((C70+E70)/2,2) -> 556 | E70: =C70 -> 556 | F70: =ROUND((E70+G70)/2,2) -> 451.75 | G70: =ROUND((E70+I70)/2,2) -> 347.5 | H70: =ROUND((G70+I70)/2,2) -> 243.25 | I70: =E70*0.25 -> 139 | K70: yearly | L70: Driver | M70: EU | N70: 0 | O70: NA | P70: 0.071 | Q70: 0 | R70: [36]
A71: Road Fuel Exports | B71: [PJ] | C71: 846 | D71: =ROUND((C71+E71)/2,2) -> 846 | E71: =C71 -> 846 | F71: =ROUND((E71+G71)/2,2) -> 687.38 | G71: =ROUND((E71+I71)/2,2) -> 528.75 | H71: =ROUND((G71+I71)/2,2) -> 370.13 | I71: =E71*0.25 -> 211.5 | K71: yearly | L71: Driver | M71: EU | N71: 0 | O71: NA | P71: 0.073 | Q71: 0 | R71: [36]
A72: Kerosene Exports | B72: [PJ] | C72: 353 | D72: =ROUND((C72+E72)/2,2) -> 353 | E72: =C72 -> 353 | F72: =ROUND((E72+G72)/2,2) -> 286.82 | G72: =ROUND((E72+I72)/2,2) -> 220.63 | H72: =ROUND((G72+I72)/2,2) -> 154.44 | I72: =E72*0.25 -> 88.25 | K72: yearly | L72: Driver | M72: EU | N72: 0 | O72: NA | P72: 0.072 | Q72: 0 | R72: [36]
A73: Electricity demand - EU | B73: [PJ] | C73: 4260 | D73: =ROUND((C73+E73)/2,2) -> 4560 | E73: 4860 | F73: =ROUND((E73+G73)/2,2) -> 5163.75 | G73: =ROUND((E73+I73)/2,2) -> 5467.5 | H73: =ROUND((G73+I73)/2,2) -> 5771.25 | I73: 6075 | K73: yearly | L73: Driver | M73: EU | N73: 0 | O73: NA | P73: NA | Q73: NA | R73: [2]
A74: Concrete demand | B74: [Mton_concrete] | C74: 31.2 | D74: 33.8 | E74: =D74 -> 33.8 | F74: =E74 -> 33.8 | G74: =F74 -> 33.8 | H74: =G74 -> 33.8 | I74: =H74 -> 33.8 | K74: yearly | L74: Driver | M74: NL | N74: 0 | O74: NA | P74: NA | Q74: NA | R74: [108],[C]
A75: Salt production | B75: [Mton_salt] | C75: 0 | D75: =C75 -> 0 | E75: =D75 -> 0 | F75: =E75 -> 0 | G75: =F75 -> 0 | H75: =G75 -> 0 | I75: =H75 -> 0 | K75: yearly | L75: Driver | M75: NL | N75: 0 | O75: NA | P75: NA | Q75: NA
A76: End-of-life concrete | B76: [Mton_EOL_concrete] | C76: 0 | D76: 0 | E76: 0 | F76: 0 | G76: 0 | H76: 0 | I76: 0 | K76: yearly | L76: Material conversion | M76: NL | N76: 0 | O76: EOL | P76: NA | Q76: NA | S76: 1
A77: Sand | B77: [Mton_sand] | C77: 0 | D77: 0 | E77: 0 | F77: 0 | G77: 0 | H77: 0 | I77: 0 | K77: yearly | L77: Material conversion | M77: NL | N77: 0 | O77: Material | P77: NA | Q77: NA | S77: 1
A78: Gravel/aggregate | B78: [Mton_aggregate] | C78: 0 | D78: 0 | E78: 0 | F78: 0 | G78: 0 | H78: 0 | I78: 0 | K78: yearly | L78: Material conversion | M78: NL | N78: 0 | O78: Material | P78: NA | Q78: NA | S78: 1
A79: Cement | B79: [Mton_cement] | C79: 0 | D79: 0 | E79: 0 | F79: 0 | G79: 0 | H79: 0 | I79: 0 | K79: yearly | L79: Material conversion | M79: NL | N79: 0 | O79: Material | P79: NA | Q79: NA | S79: 1
A80: End-of-life ceramic | B80: [Mton_EOL_CTW] | C80: 0 | D80: 0 | E80: 0 | F80: 0 | G80: 0 | H80: 0 | I80: 0 | K80: yearly | L80: Material conversion | M80: NL | N80: 0 | O80: EOL | P80: NA | Q80: NA | S80: 1
A81: Supplementary cementitious material (SCM) | B81: [Mton_SCM] | C81: 0 | D81: 0 | E81: 0 | F81: 0 | G81: 0 | H81: 0 | I81: 0 | K81: yearly | L81: Material conversion | M81: NL | N81: 0 | O81: Material | P81: NA | Q81: NA | S81: 1
A82: Iron ore | B82: [Mton_iron_ore] | C82: 0 | D82: 0 | E82: 0 | F82: 0 | G82: 0 | H82: 0 | I82: 0 | K82: yearly | L82: Material conversion | M82: NL | N82: 0 | O82: Material | P82: NA | Q82: NA | S82: 1
A83: Limestone | B83: [Mton_limestone] | C83: 0 | D83: 0 | E83: 0 | F83: 0 | G83: 0 | H83: 0 | I83: 0 | K83: yearly | L83: Material conversion | M83: NL | N83: 0 | O83: Material | P83: NA | Q83: NA | S83: 1
A84: Extracted salt | B84: [Mton_salt] | C84: 0 | D84: 0 | E84: 0 | F84: 0 | G84: 0 | H84: 0 | I84: 0 | K84: yearly | L84: Material conversion | M84: NL | N84: 0 | O84: Material | P84: NA | Q84: NA | S84: 1
A85: Clay | B85: [Mton_clay] | C85: 0 | D85: 0 | E85: 0 | F85: 0 | G85: 0 | H85: 0 | I85: 0 | K85: yearly | L85: Material conversion | M85: NL | N85: 0 | O85: Material | P85: NA | Q85: NA | S85: 1
A86: Recycled glass | B86: [Mton_Glass] | C86: 0 | D86: 0 | E86: 0 | F86: 0 | G86: 0 | H86: 0 | I86: 0 | K86: yearly | L86: Material conversion | M86: NL | N86: 0 | O86: EOL | P86: NA | Q86: NA | S86: 1
A87: DRI | B87: [Mton_DRI/y] | C87: 0 | D87: 0 | E87: 0 | F87: 0 | G87: 0 | H87: 0 | I87: 0 | K87: yearly | L87: Material conversion | M87: NL | N87: 0 | O87: Material | P87: NA | Q87: NA | S87: 1
... A96: Ethylene oxide intermediate | B96: [Mton_EO] | C96: 0 | D96: 0 | E96: 0 | F96: 0 | G96: 0 | H96: 0 | I96: 0 | K96: yearly | L96: Material conversion | M96: NL | N96: 0 | O96: Material | P96: NA | Q96: NA | S96: 1
A97: Ethylene glycol | B97: [Mton_EG] | C97: 0 | D97: =C97 -> 0 | E97: =D97 -> 0 | F97: =E97 -> 0 | G97: =F97 -> 0 | H97: =G97 -> 0 | I97: =H97 -> 0 | K97: yearly | L97: Material conversion | M97: NL | N97: 0 | O97: Material | P97: NA | Q97: NA | S97: 1
A98: Sorted polyethylene | B98: [Mton_sortedPE] | C98: 0 | D98: 0 | E98: 0 | F98: 0 | G98: 0 | H98: 0 | I98: 0 | K98: yearly | L98: Material conversion | M98: NL | N98: 0 | O98: Waste | P98: NA | Q98: NA | S98: 1
A99: Sorted polypropylene | B99: [Mton_sortedPP] | C99: 0 | D99: 0 | E99: 0 | F99: 0 | G99: 0 | H99: 0 | I99: 0 | K99: yearly | L99: Material conversion | M99: NL | N99: 0 | O99: Waste | P99: NA | Q99: NA | S99: 1
A100: Sorted PET | B100: [Mton_sortedPET] | C100: 0 | D100: 0 | E100: 0 | F100: 0 | G100: 0 | H100: 0 | I100: 0 | K100: yearly | L100: Material conversion | M100: NL | N100: 0 | O100: Waste | P100: NA | Q100: NA | S100: 1
A101: Sorted PVC | B101: [Mton_sortedPVC] | C101: 0 | D101: 0 | E101: 0 | F101: 0 | G101: 0 | H101: 0 | I101: 0 | K101: yearly | L101: Material conversion | M101: NL | N101: 0 | O101: Waste | P101: NA | Q101: NA | S101: 1
A102: Electricity EU | B102: [PJ] | C102: 0 | D102: 0 | E102: 0 | F102: 0 | G102: 0 | H102: 0 | I102: 0 | K102: hourly-interconnected | L102: Energy | M102: EU | N102: 0 | O102: Electricity | P102: NA | Q102: NA | R102: [1]
A103: Electricity NL - HVNS | B103: [PJ] | C103: 0 | D103: 0 | E103: 0 | F103: 0 | G103: 0 | H103: 0 | I103: 0 | K103: hourly | L103: Energy | M103: NL | N103: 0 | O103: Electricity | P103: NA | Q103: NA | R103: [1]
A104: Electricity NL - HV | B104: [PJ] | C104: 0 | D104: 0 | E104: 0 | F104: 0 | G104: 0 | H104: 0 | I104: 0 | K104: hourly | L104: Energy | M104: NL | N104: 0 | O104: Electricity | P104: NA | Q104: NA | R104: [1]
A105: Electricity NL - LV | B105: [PJ] | C105: 0 | D105: 0 | E105: 0 | F105: 0 | G105: 0 | H105: 0 | I105: 0 | K105: hourly | L105: Energy | M105: NL | N105: 0 | O105: Electricity | P105: NA | Q105: NA | R105: [1]
A106: Heat LT Houses C-G | B106: [PJ] | C106: 0 | D106: 0 | E106: 0 | F106: 0 | G106: 0 | H106: 0 | I106: 0 | K106: hourly-indirect | L106: Energy | M106: NL | N106: 0 | O106: Heat | P106: NA | Q106: NA | R106: [1]
A107: Heat LT Houses A+,A,B | B107: [PJ] | C107: 0 | D107: 0 | E107: 0 | F107: 0 | G107: 0 | H107: 0 | I107: 0 | K107: hourly-indirect | L107: Energy | M107: NL | N107: 0 | O107: Heat | P107: NA | Q107: NA | R107: [1]
A108: Heat LT Services | B108: [PJ] | C108: 0 | D108: 0 | E108: 0 | F108: 0 | G108: 0 | H108: 0 | I108: 0 | K108: hourly-indirect | L108: Energy | M108: NL | N108: 0 | O108: Heat | P108: NA | Q108: NA | R108: [1]
A109: Heat LT Network | B109: [PJ] | C109: 0 | D109: 0 | E109: 0 | F109: 0 | G109: 0 | H109: 0 | I109: 0 | K109: hourly | L109: Energy | M109: NL | N109: 0 | O109: Heat | P109: NA | Q109: NA | R109: [1]
...

Sheet Technologies
A2: Tech. Specifics | I2: Cost data | AI2: Operation data | AM2: CHP flexibility data | AS2: Asymetric flexibility | AV2: Hydro Reservoirs | AY2: Flexibility data | BH2: Network buffers | BO2: Planned decommissioning | BU2: Minimum stock in a year | CB2: Maximum stock in a year | CI2: Minimum use in a year | CP2: Maximum use in a year | CW2: No new investments | DD2: No economic/early decommissioning | DK2: Data source | DL2: Reference Volume of the main activity
A3: Tech_ID | B3: Policy Sectors | C3: Category | D3: Sector | E3: Sub-sector | F3: Main Activity | G3: Name | H3: UoC | I3: Investment | J3: Investment | K3: Investment | L3: Investment | M3: Investment | N3: Investment | O3: Investment | P3: Salvage value | Q3: Fixed O&M | R3: Fixed O&M | S3: Fixed O&M | T3: Fixed O&M | U3: Fixed O&M | V3: Fixed O&M | W3: Fixed O&M | X3: Variable O&M | Y3: Variable O&M | Z3: Variable O&M | AA3: Variable O&M | AB3: Variable O&M | AC3: Variable O&M | AD3: Variable O&M | AE3: WACC | AF3: Const. Time | AG3: Ec. Lifetime | AH3: Tech. Lifetime | AI3: Cap2Act | AJ3: Type of process | AK3: Type of profile | AL3: Ramping constraint | AM3: CHP product | AN3: CHP fuel | AO3: CHP η | AP3: CHP heat balance range | AQ3: CHP deviation in USE tolerance | AR3: CHP deviation in P/H RATIO tolerance | AS3: Shedding capacity | AT3: Shedding volume | AU3: Range for demand curtailing | AV3: Pump to head ratio | AW3: Reservoir capacity | AX3: Pumping losses | AY3: Form of Flexibility | AZ3: Benefited activity | BA3: Flexible capacity | BB3: Storage capacity | BC3: Shifting range | BD3: Losses | BE3: Non-negotiable load | BF3: Average journey duration | BG3: Average speed | BH3: Benefited activity | BI3: Upward capacity | BJ3: Downward capacity | BK3: Buffer capacity | BL3: Current installed capacity needed | BM3: Maximum technology deployment | BN3: Current Installed Capacity | CB3: 0 | CC3: 0 | CD3: 0.1 | CE3: 0.2 | CF3: 0.5 | CG3: 1 | CH3: 1 | CW3: 1 = no new investments allowed in this year | DD3: 1 = no early decommissioning allowed in this year | DL3: (also works as an auxiliary)
I4: =Parameters!$B$13 -> 2022 | J4: 2025 | K4: 2030 | L4: 2035 | M4: 2040 | N4: 2045 | O4: 2050 | P4: % of CAPEX | Q4: =Parameters!$B$13 -> 2022 | R4: 2025 | S4: 2030 | T4: 2035 | U4: 2040 | V4: 2045 | W4: 2050 | X4: =Parameters!$B$13 -> 2022 | Y4: 2025 | Z4: 2030 | AA4: 2035 | AB4: 2040 | AC4: 2045 | AD4: 2050 | AP4: (h,d,w) | AQ4: (only for CHP) | AR4: (only for CHP) | AT4: (if range is more than 1 hour) | AV4: (zero if not PS) | AW4: (hours of discharge) | BB4: (hours of charge) | BK4: (in relation to discharge) | BL4: (not in the model) | BO4: 1 | BP4: 2 | BQ4: 3 | BR4: 4 | BS4: 5 | BT4: 6 | CB4: 0 | CC4: 0.5 | CD4: 1 | CE4: 1 | CF4: 1 | CG4: 1 | CH4: 1 | CZ4: [y/n] | DG4: [y/n] | DO4: (no AIMMS)
AJ5: (mandatory) | AK5: (mandatory) | AL5: (only for Hourly dispatch) | BB5: (only if storage is present) | BF5: (only for flexible electric transport) | BG5: (only for flexible electric transport) | BN5: =Parameters!$B$13 -> 2022 | BO5: 2025 | BP5: 2030 | BQ5: 2035 | BR5: 2040 | BS5: 2045 | BT5: 2050 | BU5: =Parameters!$B$13 -> 2022 | BV5: 2025 | BW5: 2030 | BX5: 2035 | BY5: 2040 | BZ5: 2045 | CA5: 2050 | CB5: =Parameters!$B$13 -> 2022 | CC5: 2025 | CD5: 2030 | CE5: 2035 | CF5: 2040 | CG5: 2045 | CH5: 2050 | CI5: =Parameters!$B$13 -> 2022 | CJ5: 2025 | CK5: 2030 | CL5: 2035 | CM5: 2040 | CN5: 2045 | CO5: 2050 | CP5: =Parameters!$B$13 -> 2022 | CQ5: 2025 | CR5: 2030 | CS5: 2035 | CT5: 2040 | CU5: 2045 | CV5: 2050 | CW5: =Parameters!$B$13 -> 2022 | CX5: 2025 | CY5: 2030 | CZ5: 2035 | DA5: 2040 | DB5: 2045 | DC5: 2050 | DD5: =Parameters!$B$13 -> 2022 | DE5: 2025 | DF5: 2030 | DG5: 2035 | DH5: 2040 | DI5: 2045 | DJ5: 2050
I6: [M€/UoC] | J6: [M€/UoC] | K6: [M€/UoC] | L6: [M€/UoC] | M6: [M€/UoC] | N6: [M€/UoC] | O6: [M€/UoC] | P6: [%] | Q6: [M€/UoC-y] | R6: [M€/UoC-y] | S6: [M€/UoC-y] | T6: [M€/UoC-y] | U6: [M€/UoC-y] | V6: [M€/UoC-y] | W6: [M€/UoC-y] | X6: [M€/UoA] | Y6: [M€/UoA] | Z6: [M€/UoA] | AA6: [M€/UoA] | AB6: [M€/UoA] | AC6: [M€/UoA] | AD6: [M€/UoA] | AE6: [1/y] | AF6: [y] | AG6: [y] | AH6: [y] | AI6: [UoA/UoC-y] | AJ6: [type] | AK6: [type] | AL6: [%] | AM6: [activity] | AN6: [activity] | AO6: [%] | AP6: [UoR] | AQ6: [%] | AR6: [%] | AS6: [%] | AT6: [%] | AU6: [UoR] | AV6: [%] | AW6: [h] | AX6: [%] | AY6: [type] | AZ6: [activity] | BA6: [%] | BB6: [h] | BC6: [UoR] | BD6: [%] | BE6: [%] | BF6: [h] | BG6: [UoA/UoC-h] | BH6: [activity] | BI6: [PJ/UoC-d] | BJ6: [PJ/UoC-d] | BK6: [d] | BL6: [y/n] | BM6: [UoC/5y] | BN6: [UoC] | BO6: [UoC] | BP6: [UoC] | BQ6: [UoC] | BR6: [UoC] | BS6: [UoC] | BT6: [UoC] | BU6: [UoC] | BV6: [UoC] | BW6: [UoC] | BX6: [UoC] | BY6: [UoC] | BZ6: [UoC] | CA6: [UoC] | CB6: [UoC] | CC6: [UoC] | CD6: [UoC] | CE6: [UoC] | CF6: [UoC] | CG6: [UoC] | CH6: [UoC] | CI6: [UoA] | CJ6: [UoA] | CK6: [UoA] | CL6: [UoA] | CM6: [UoA] | CN6: [UoA] | CO6: [UoA] | CP6: [UoA] | CQ6: [UoA] | CR6: [UoA] | CS6: [UoA] | CT6: [UoA] | CU6: [UoA] | CV6: [UoA] | CW6: [y/n] | CX6: [y/n] | CY6: [y/n] | CZ6: [y/n] | DA6: [y/n] | DB6: [y/n] | DC6: [y/n] | DD6: [y/n] | DE6: [y/n] | DF6: [y/n] | DG6: [y/n] | DH6: [y/n] | DI6: [y/n] | DJ6: [y/n] | DK6: [ref No.] | DL6: =Parameters!$B$13 -> 2022 | DM6: 2025 | DN6: 2030 | DO6: 2035 | DP6: 2040 | DQ6: 2045 | DR6: 2050
A7: Res01_01 | B7: Gebouwde omgeving | C7: Final | D7: Residential | E7: Appliances | F7: Electricity demand - Residential | G7: Dummy standard electricity consumption - Residential | H7: [PJ/y] | I7: 0 | J7: 0 | K7: 0 | L7: 0 | M7: 0 | N7: 0 | O7: 0 | P7: 0 | Q7: 0 | R7: 0 | S7: 0 | T7: 0 | U7: 0 | V7: 0 | W7: 0 | X7: 0 | Y7: 0 | Z7: 0 | AA7: 0 | AB7: 0 | AC7: 0 | AD7: 0 | AE7: 0.08 | AF7: 0 | AG7: 1 | AH7: 1 | AI7: 1 | AJ7: Operation | AK7: Standard Load | AY7: none | BN7: =DL7 -> 80.1 | BO7: 0 | BP7: 0 | BQ7: 0 | BR7: 0 | BS7: 0 | BT7: 0 | BU7: =IF(BL7=1,BN7,0) -> 0 | CB7: =DL7 -> 80.1 | CC7: =DM7 -> 83.547169 | CD7: =DN7 -> 85.414196 | CE7: =DO7 -> 86.416015 | CF7: =DP7 -> 86.807635 | CG7: =DQ7 -> 86.712007 | CH7: =DR7 -> 86.329494 | DK7: [1],[12] | DL7: =VLOOKUP($F7,Activities!$A$9:$I$180,3,FALSE)/$AI7 -> 80.1 | DM7: =VLOOKUP($F7,Activities!$A$9:$I$180,4,FALSE)/$AI7 -> 83.547169 | DN7: =VLOOKUP($F7,Activities!$A$9:$I$180,5,FALSE)/$AI7 -> 85.414196 | DO7: =VLOOKUP($F7,Activities!$A$9:$I$180,6,FALSE)/$AI7 -> 86.416015 | DP7: =VLOOKUP($F7,Activities!$A$9:$I$180,7,FALSE)/$AI7 -> 86.807635 | DQ7: =VLOOKUP($F7,Activities!$A$9:$I$180,8,FALSE)/$AI7 -> 86.712007 | DR7: =VLOOKUP($F7,Activities!$A$9:$I$180,9,FALSE)/$AI7 -> 86.329494
A8: Res01_02 | B8: Gebouwde omgeving | C8: Final | D8: Residential | E8: Appliances | F8: Electricity demand - Residential | G8: Flexible standard electricity consumption - Residential | H8: [PJ/y] | I8: 0.5 | J8: 0.5 | K8: 0.5 | L8: 0.3 | M8: 0.1 | N8: 0 | O8: 0 | P8: 0 | Q8: 0 | R8: 0 | S8: 0 | T8: 0 | U8: 0 | V8: 0 | W8: 0 | X8: 0 | Y8: 0 | Z8: 0 | AA8: 0 | AB8: 0 | AC8: 0 | AD8: 0 | AE8: 0.08 | AF8: 0 | AG8: 15 | AH8: 15 | AI8: 1 | AJ8: Operation | AK8: Standard Load | AY8: DR shifting | AZ8: Electricity NL - LV | BA8: 1 | BC8: 1 day [d] | BD8: 0.02 | BE8: 0.8 | BN8: 0.5 | BQ8: 0.5 | BU8: =IF(BL8=1,BN8,0) -> 0 | CB8: 0.5 | CC8: 1 | CD8: 2 | CE8: 4 | CF8: 8 | CG8: 20 | CH8: 32 | DK8: [1],[12] | DL8: =VLOOKUP($F8,Activities!$A$9:$I$180,3,FALSE)/$AI8 -> 80.1 | DM8: =VLOOKUP($F8,Activities!$A$9:$I$180,4,FALSE)/$AI8 -> 83.547169 | DN8: =VLOOKUP($F8,Activities!$A$9:$I$180,5,FALSE)/$AI8 -> 85.414196 | DO8: =VLOOKUP($F8,Activities!$A$9:$I$180,6,FALSE)/$AI8 -> 86.416015 | DP8: =VLOOKUP($F8,Activities!$A$9:$I$180,7,FALSE)/$AI8 -> 86.807635 | DQ8: =VLOOKUP($F8,Activities!$A$9:$I$180,8,FALSE)/$AI8 -> 86.712007 | DR8: =VLOOKUP($F8,Activities!$A$9:$I$180,9,FALSE)/$AI8 -> 86.329494
A9: Res02_01 | B9: Gebouwde omgeving | C9: Final | D9: Residential | E9: Flats | F9: Houses - Residential Flats | G9: House with insulation GFE - Residential Flats | H9: [khouses/y] | I9: 0 | J9: 0 | K9: 0 | L9: 0 | M9: 0 | N9: 0 | O9: 0 | P9: 0 | Q9: 0 | R9: 0 | S9: 0 | T9: 0 | U9: 0 | V9: 0 | W9: 0 | X9: 0 | Y9: 0 | Z9: 0 | AA9: 0 | AB9: 0 | AC9: 0 | AD9: 0 | AE9: 0.08 | AF9: 0 | AG9: 40 | AH9: 40 | AI9: 1 | AJ9: Operation | AK9: Built Environment | AY9: none | BL9: 1 | BN9: =IF(SUM(CB9:CB9)<DL9,CB9,DL9-SUM(CB9:CB9)) -> 1000 | BT9: 0 | BU9: =IF(BL9=1,BN9,0) -> 1000 | CB9: 1000 | CC9: =DM9 -> 3041.4924 | CD9: =DN9 -> 3109.4606 | CE9: =DO9 -> 3145.9313 | CF9: =DP9 -> 3160.1881 | CG9: =DQ9 -> 3156.7068 | CH9: =DR9 -> 3142.7816 | CX9: 1 | CY9: 1 | CZ9: 1 | DA9: 1 | DB9: 1 | DC9: 1 | DK9: [1],[12] | DL9: =VLOOKUP($F9,Activities!$A$9:$I$180,3,FALSE)/$AI9 -> 2916 | DM9: =VLOOKUP($F9,Activities!$A$9:$I$180,4,FALSE)/$AI9 -> 3041.4924 | DN9: =VLOOKUP($F9,Activities!$A$9:$I$180,5,FALSE)/$AI9 -> 3109.4606 | DO9: =VLOOKUP($F9,Activities!$A$9:$I$180,6,FALSE)/$AI9 -> 3145.9313 | DP9: =VLOOKUP($F9,Activities!$A$9:$I$180,7,FALSE)/$AI9 -> 3160.1881 | DQ9: =VLOOKUP($F9,Activities!$A$9:$I$180,8,FALSE)/$AI9 -> 3156.7068 | DR9: =VLOOKUP($F9,Activities!$A$9:$I$180,9,FALSE)/$AI9 -> 3142.7816
A10: Res02_02 | B10: Gebouwde omgeving | C10: Final | D10: Residential | E10: Flats | F10: Houses - Residential Flats | G10: House with insulation DC - Residential Flats | H10: [khouses/y] | I10: 2.37 | J10: 2.37 | K10: 2.37 | L10: 0 | M10: 0 | N10: 0 | O10: 0 | P10: 0 | Q10: 0 | R10: 0 | S10: 0 | T10: 0 | U10: 0 | V10: 0 | W10: 0 | X10: 0 | Y10: 0 | Z10: 0 | AA10: 0 | AB10: 0 | AC10: 0 | AD10: 0 | AE10: 0.08 | AF10: 0 | AG10: 40 | AH10: 40 | AI10: 1 | AJ10: Operation | AK10: Built Environment | AY10: none | BL10: 1 | BN10: =IF(SUM(CB9:CB10)<DL10,CB10,DL10-SUM(CB9:CB9)) -> 1150 | BU10: 1050 | CB10: 1150 | CC10: =DM10 -> 3041.4924 | CD10: =DN10 -> 3109.4606 | CE10: =DO10 -> 3145.9313 | CF10: =DP10 -> 3160.1881 | CG10: =DQ10 -> 3156.7068 | CH10: =DR10 -> 3142.7816 | CY10: 1 | CZ10: 1 | DA10: 1 | DB10: 1 | DC10: 1 | DK10: [1],[12] | DL10: =VLOOKUP($F10,Activities!$A$9:$I$180,3,FALSE)/$AI10 -> 2916 | DM10: =VLOOKUP($F10,Activities!$A$9:$I$180,4,FALSE)/$AI10 -> 3041.4924 | DN10: =VLOOKUP($F10,Activities!$A$9:$I$180,5,FALSE)/$AI10 -> 3109.4606 | DO10: =VLOOKUP($F10,Activities!$A$9:$I$180,6,FALSE)/$AI10 -> 3145.9313 | DP10: =VLOOKUP($F10,Activities!$A$9:$I$180,7,FALSE)/$AI10 -> 3160.1881 | DQ10: =VLOOKUP($F10,Activities!$A$9:$I$180,8,FALSE)/$AI10 -> 3156.7068 | DR10: =VLOOKUP($F10,Activities!$A$9:$I$180,9,FALSE)/$AI10 -> 3142.7816
A11: Res02_03 | B11: Gebouwde omgeving | C11: Final | D11: Residential | E11: Flats | F11: Houses - Residential Flats | G11: House with insulation B - Residential Flats | H11: [khouses/y] | I11: 8.2 | J11: 8.2 | K11: 8.2 | L11: 5.8 | M11: 5.8 | N11: 0 | O11: 0 | P11: 0 | Q11: 0 | R11: 0 | S11: 0 | T11: 0 | U11: 0 | V11: 0 | W11: 0 | X11: 0 | Y11: 0 | Z11: 0 | AA11: 0 | AB11: 0 | AC11: 0 | AD11: 0 | AE11: 0.08 | AF11: 0 | AG11: 40 | AH11: 40 | AI11: 1 | AJ11: Operation | AK11: Built Environment | AY11: none | BL11: 1 | BN11: =IF(SUM(CB9:CB11)<DL11,CB11,DL11-SUM(CB9:CB10)) -> 500 | BU11: =IF(BL11=1,BN11,0) -> 500 | CB11: 500 | CC11: =DM11 -> 3041.4924 | CD11: =DN11 -> 3109.4606 | CE11: =DO11 -> 3145.9313 | CF11: =DP11 -> 3160.1881 | CG11: =DQ11 -> 3156.7068 | CH11: =DR11 -> 3142.7816 | CZ11: 1 | DA11: 1 | DB11: 1 | DC11: 1 | DK11: [1],[12] | DL11: =VLOOKUP($F11,Activities!$A$9:$I$180,3,FALSE)/$AI11 -> 2916 | DM11: =VLOOKUP($F11,Activities!$A$9:$I$180,4,FALSE)/$AI11 -> 3041.4924 | DN11: =VLOOKUP($F11,Activities!$A$9:$I$180,5,FALSE)/$AI11 -> 3109.4606 | DO11: =VLOOKUP($F11,Activities!$A$9:$I$180,6,FALSE)/$AI11 -> 3145.9313 | DP11: =VLOOKUP($F11,Activities!$A$9:$I$180,7,FALSE)/$AI11 -> 3160.1881 | DQ11: =VLOOKUP($F11,Activities!$A$9:$I$180,8,FALSE)/$AI11 -> 3156.7068 | DR11: =VLOOKUP($F11,Activities!$A$9:$I$180,9,FALSE)/$AI11 -> 3142.7816
A12: Res02_04 | B12: Gebouwde omgeving | C12: Final | D12: Residential | E12: Flats | F12: Houses - Residential Flats | G12: House with insulation A - Residential Flats | H12: [khouses/y] | I12: 10.37 | J12: 10.11 | K12: 9.85 | L12: 7.2 | M12: 7.1 | N12: 1.3 | O12: 1.3 | P12: 0 | Q12: 0 | R12: 0 | S12: 0 | T12: 0 | U12: 0 | V12: 0 | W12: 0 | X12: 0 | Y12: 0 | Z12: 0 | AA12: 0 | AB12: 0 | AC12: 0 | AD12: 0 | AE12: 0.08 | AF12: 0 | AG12: 40 | AH12: 40 | AI12: 1 | AJ12: Operation | AK12: Built Environment | AY12: none | BN12: =IF(SUM(CB9:CB12)<DL12,CB12,DL12-SUM(CB9:CB11)) -> 250 | BU12: =IF(BL12=1,BN12,0) -> 0 | CB12: 250 | CC12: =DM12 -> 3041.4924 | CD12: =DN12 -> 3109.4606 | CE12: =DO12 -> 3145.9313 | CF12: =DP12 -> 3160.1881 | CG12: =DQ12 -> 3156.7068 | CH12: =DR12 -> 3142.7816 | DF12: 1 | DG12: 1 | DH12: 1 | DI12: 1 | DJ12: 1 | DK12: [1],[12] | DL12: =VLOOKUP($F12,Activities!$A$9:$I$180,3,FALSE)/$AI12 -> 2916 | DM12: =VLOOKUP($F12,Activities!$A$9:$I$180,4,FALSE)/$AI12 -> 3041.4924 | DN12: =VLOOKUP($F12,Activities!$A$9:$I$180,5,FALSE)/$AI12 -> 3109.4606 | DO12: =VLOOKUP($F12,Activities!$A$9:$I$180,6,FALSE)/$AI12 -> 3145.9313 | DP12: =VLOOKUP($F12,Activities!$A$9:$I$180,7,FALSE)/$AI12 -> 3160.1881 | DQ12: =VLOOKUP($F12,Activities!$A$9:$I$180,8,FALSE)/$AI12 -> 3156.7068 | DR12: =VLOOKUP($F12,Activities!$A$9:$I$180,9,FALSE)/$AI12 -> 3142.7816
A13: Res02_05 | B13: Gebouwde omgeving | C13: Final | D13: Residential | E13: Flats | F13: Houses - Residential Flats | G13: House with insulation A+ - Residential Flats | H13: [khouses/y] | I13: 12.26 | J13: 11.65 | K13: 11.04 | L13: 8.1 | M13: 7.5 | N13: 1.7 | O13: 1.5 | P13: 0 | Q13: 0 | R13: 0 | S13: 0 | T13: 0 | U13: 0 | V13: 0 | W13: 0 | X13: 0 | Y13: 0 | Z13: 0 | AA13: 0 | AB13: 0 | AC13: 0 | AD13: 0 | AE13: 0.08 | AF13: 0 | AG13: 40 | AH13: 40 | AI13: 1 | AJ13: Operation | AK13: Built Environment | AY13: none | BN13: =IF(SUM(CB9:CB13)<DL13,CB13,DL13-SUM(CB9:CB12)) -> 16 | BU13: =IF(BL13=1,BN13,0) -> 0 | CB13: 100 | CC13: =DM13 -> 3041.4924 | CD13: =DN13 -> 3109.4606 | CE13: =DO13 -> 3145.9313 | CF13: =DP13 -> 3160.1881 | CG13: =DQ13 -> 3156.7068 | CH13: =DR13 -> 3142.7816 | DF13: 1 | DG13: 1 | DH13: 1 | DI13: 1 | DJ13: 1 | DK13: [1],[9],[12] | DL13: =VLOOKUP($F13,Activities!$A$9:$I$180,3,FALSE)/$AI13 -> 2916 | DM13: =VLOOKUP($F13,Activities!$A$9:$I$180,4,FALSE)/$AI13 -> 3041.4924 | DN13: =VLOOKUP($F13,Activities!$A$9:$I$180,5,FALSE)/$AI13 -> 3109.4606 | DO13: =VLOOKUP($F13,Activities!$A$9:$I$180,6,FALSE)/$AI13 -> 3145.9313 | DP13: =VLOOKUP($F13,Activities!$A$9:$I$180,7,FALSE)/$AI13 -> 3160.1881 | DQ13: =VLOOKUP($F13,Activities!$A$9:$I$180,8,FALSE)/$AI13 -> 3156.7068 | DR13: =VLOOKUP($F13,Activities!$A$9:$I$180,9,FALSE)/$AI13 -> 3142.7816
A14: Res03_01 | B14: Gebouwde omgeving | C14: Final | D14: Residential | E14: Terrace | F14: Houses - Residential Terrace | G14: House with insulation GFE - Residential Terrace | H14: [khouses/y] | I14: 0 | J14: 0 | K14: 0 | L14: 0 | M14: 0 | N14: 0 | O14: 0 | P14: 0 | Q14: 0 | R14: 0 | S14: 0 | T14: 0 | U14: 0 | V14: 0 | W14: 0 | X14: 0 | Y14: 0 | Z14: 0 | AA14: 0 | AB14: 0 | AC14: 0 | AD14: 0 | AE14: 0.08 | AF14: 0 | AG14: 40 | AH14: 40 | AI14: 1 | AJ14: Operation | AK14: Built Environment | AY14: none | BL14: 1 | BN14: =IF(SUM(CB14:CB14)<DL14,CB14,MAX(DL14-SUM(CB14:CB14),0)) -> 2000 | BU14: 800 | CB14: 2000 | CC14: =DM14 -> 3525.4611 | CD14: =DN14 -> 3604.2445 | CE14: =DO14 -> 3646.5185 | CF14: =DP14 -> 3663.0438 | CG14: =DQ14 -> 3659.0085 | CH14: =DR14 -> 3642.8675 | CX14: 1 | CY14: 1 | CZ14: 1 | DA14: 1 | DB14: 1 | DC14: 1 | DK14: [1],[9],[12] | DL14: =VLOOKUP($F14,Activities!$A$9:$I$180,3,FALSE)/$AI14 -> 3380 | DM14: =VLOOKUP($F14,Activities!$A$9:$I$180,4,FALSE)/$AI14 -> 3525.4611 | DN14: =VLOOKUP($F14,Activities!$A$9:$I$180,5,FALSE)/$AI14 -> 3604.2445 | DO14: =VLOOKUP($F14,Activities!$A$9:$I$180,6,FALSE)/$AI14 -> 3646.5185 | DP14: =VLOOKUP($F14,Activities!$A$9:$I$180,7,FALSE)/$AI14 -> 3663.0438 | DQ14: =VLOOKUP($F14,Activities!$A$9:$I$180,8,FALSE)/$AI14 -> 3659.0085 | DR14: =VLOOKUP($F14,Activities!$A$9:$I$180,9,FALSE)/$AI14 -> 3642.8675
A15: Res03_02 | B15: Gebouwde omgeving | C15: Final | D15: Residential | E15: Terrace | F15: Houses - Residential Terrace | G15: House with insulation DC - Residential Terrace | H15: [khouses/y] | I15: 3.18 | J15: 3.18 | K15: 3.18 | L15: 0 | M15: 0 | N15: 0 | O15: 0 | P15: 0 | Q15: 0 | R15: 0 | S15: 0 | T15: 0 | U15: 0 | V15: 0 | W15: 0 | X15: 0 | Y15: 0 | Z15: 0 | AA15: 0 | AB15: 0 | AC15: 0 | AD15: 0 | AE15: 0.08 | AF15: 0 | AG15: 40 | AH15: 40 | AI15: 1 | AJ15: Operation | AK15: Built Environment | AY15: none | BL15: 1 | BN15: =IF(SUM(CB14:CB15)<DL15,CB15,MAX(DL15-SUM(CB14:CB14),0)) -> 1270 | BU15: 870 | CB15: 1270 | CC15: =DM15 -> 3525.4611 | CD15: =DN15 -> 3604.2445 | CE15: =DO15 -> 3646.5185 | CF15: =DP15 -> 3663.0438 | CG15: =DQ15 -> 3659.0085 | CH15: =DR15 -> 3642.8675 | CY15: 1 | CZ15: 1 | DA15: 1 | DB15: 1 | DC15: 1 | DK15: [1],[37],[38] | DL15: =VLOOKUP($F15,Activities!$A$9:$I$180,3,FALSE)/$AI15 -> 3380 | DM15: =VLOOKUP($F15,Activities!$A$9:$I$180,4,FALSE)/$AI15 -> 3525.4611 | DN15: =VLOOKUP($F15,Activities!$A$9:$I$180,5,FALSE)/$AI15 -> 3604.2445 | DO15: =VLOOKUP($F15,Activities!$A$9:$I$180,6,FALSE)/$AI15 -> 3646.5185 | DP15: =VLOOKUP($F15,Activities!$A$9:$I$180,7,FALSE)/$AI15 -> 3663.0438 | DQ15: =VLOOKUP($F15,Activities!$A$9:$I$180,8,FALSE)/$AI15 -> 3659.0085 | DR15: =VLOOKUP($F15,Activities!$A$9:$I$180,9,FALSE)/$AI15 -> 3642.8675
A16: Res03_03 | B16: Gebouwde omgeving | C16: Final | D16: Residential | E16: Terrace | F16: Houses - Residential Terrace | G16: House with insulation B - Residential Terrace | H16: [khouses/y] | I16: 9.71 | J16: 9.71 | K16: 9.71 | L16: 6.5 | M16: 6.5 | N16: 0 | O16: 0 | P16: 0 | Q16: 0 | R16: 0 | S16: 0 | T16: 0 | U16: 0 | V16: 0 | W16: 0 | X16: 0 | Y16: 0 | Z16: 0 | AA16: 0 | AB16: 0 | AC16: 0 | AD16: 0 | AE16: 0.08 | AF16: 0 | AG16: 40 | AH16: 40 | AI16: 1 | AJ16: Operation | AK16: Built Environment | AY16: none | BL16: 1 | BN16: =IF(SUM(CB14:CB16)<DL16,CB16,MAX(DL16-SUM(CB14:CB15),0)) -> 110 | BU16: 500 | CB16: 840 | CC16: =DM16 -> 3525.4611 | CD16: =DN16 -> 3604.2445 | CE16: =DO16 -> 3646.5185 | CF16: =DP16 -> 3663.0438 | CG16: =DQ16 -> 3659.0085 | CH16: =DR16 -> 3642.8675 | CZ16: 1 | DA16: 1 | DB16: 1 | DC16: 1 | DK16: [1],[37],[38] | DL16: =VLOOKUP($F16,Activities!$A$9:$I$180,3,FALSE)/$AI16 -> 3380 | DM16: =VLOOKUP($F16,Activities!$A$9:$I$180,4,FALSE)/$AI16 -> 3525.4611 | DN16: =VLOOKUP($F16,Activities!$A$9:$I$180,5,FALSE)/$AI16 -> 3604.2445 | DO16: =VLOOKUP($F16,Activities!$A$9:$I$180,6,FALSE)/$AI16 -> 3646.5185 | DP16: =VLOOKUP($F16,Activities!$A$9:$I$180,7,FALSE)/$AI16 -> 3663.0438 | DQ16: =VLOOKUP($F16,Activities!$A$9:$I$180,8,FALSE)/$AI16 -> 3659.0085 | DR16: =VLOOKUP($F16,Activities!$A$9:$I$180,9,FALSE)/$AI16 -> 3642.8675
A17: Res03_04 | B17: Gebouwde omgeving | C17: Final | D17: Residential | E17: Terrace | F17: Houses - Residential Terrace | G17: House with insulation A - Residential Terrace | H17: [khouses/y] | I17: 12.9 | J17: 12.57 | K17: 12.25 | L17: 8.7 | M17: 8.4 | N17: 1.9 | O17: 1.9 | P17: 0 | Q17: 0 | R17: 0 | S17: 0 | T17: 0 | U17: 0 | V17: 0 | W17: 0 | X17: 0 | Y17: 0 | Z17: 0 | AA17: 0 | AB17: 0 | AC17: 0 | AD17: 0 | AE17: 0.08 | AF17: 0 | AG17: 40 | AH17: 40 | AI17: 1 | AJ17: Operation | AK17: Built Environment | AY17: none | BN17: =IF(SUM(CB14:CB17)<DL17,CB17,MAX(DL17-SUM(CB14:CB16),0)) -> 0 | BU17: =IF(BL17=1,BN17,0) -> 0 | CB17: 380 | CC17: =DM17 -> 3525.4611 | CD17: =DN17 -> 3604.2445 | CE17: =DO17 -> 3646.5185 | CF17: =DP17 -> 3663.0438 | CG17: =DQ17 -> 3659.0085 | CH17: =DR17 -> 3642.8675 | DF17: 1 | DG17: 1 | DH17: 1 | DI17: 1 | DJ17: 1 | DK17: [1],[37],[38] | DL17: =VLOOKUP($F17,Activities!$A$9:$I$180,3,FALSE)/$AI17 -> 3380 | DM17: =VLOOKUP($F17,Activities!$A$9:$I$180,4,FALSE)/$AI17 -> 3525.4611 | DN17: =VLOOKUP($F17,Activities!$A$9:$I$180,5,FALSE)/$AI17 -> 3604.2445 | DO17: =VLOOKUP($F17,Activities!$A$9:$I$180,6,FALSE)/$AI17 -> 3646.5185 | DP17: =VLOOKUP($F17,Activities!$A$9:$I$180,7,FALSE)/$AI17 -> 3663.0438 | DQ17: =VLOOKUP($F17,Activities!$A$9:$I$180,8,FALSE)/$AI17 -> 3659.0085 | DR17: =VLOOKUP($F17,Activities!$A$9:$I$180,9,FALSE)/$AI17 -> 3642.8675
A18: Res03_05 | B18: Gebouwde omgeving | C18: Final | D18: Residential | E18: Terrace | F18: Houses - Residential Terrace | G18: House with insulation A+ - Residential Terrace | H18: [khouses/y] | I18: 15.69 | J18: 14.91 | K18: 14.12 | L18: 10.2 | M18: 9.5 | N18: 3 | O18: 2.5 | P18: 0 | Q18: 0 | R18: 0 | S18: 0 | T18: 0 | U18: 0 | V18: 0 | W18: 0 | X18: 0 | Y18: 0 | Z18: 0 | AA18: 0 | AB18: 0 | AC18: 0 | AD18: 0 | AE18: 0.08 | AF18: 0 | AG18: 40 | AH18: 40 | AI18: 1 | AJ18: Operation | AK18: Built Environment | AY18: none | BN18: =IF(SUM(CB14:CB18)<DL18,CB18,MAX(DL18-SUM(CB14:CB17),0)) -> 0 | BU18: =IF(BL18=1,BN18,0) -> 0 | CB18: 120 | CC18: =DM18 -> 3525.4611 | CD18: =DN18 -> 3604.2445 | CE18: =DO18 -> 3646.5185 | CF18: =DP18 -> 3663.0438 | CG18: =DQ18 -> 3659.0085 | CH18: =DR18 -> 3642.8675 | DF18: 1 | DG18: 1 | DH18: 1 | DI18: 1 | DJ18: 1 | DK18: [1],[37],[38] | DL18: =VLOOKUP($F18,Activities!$A$9:$I$180,3,FALSE)/$AI18 -> 3380 | DM18: =VLOOKUP($F18,Activities!$A$9:$I$180,4,FALSE)/$AI18 -> 3525.4611 | DN18: =VLOOKUP($F18,Activities!$A$9:$I$180,5,FALSE)/$AI18 -> 3604.2445 | DO18: =VLOOKUP($F18,Activities!$A$9:$I$180,6,FALSE)/$AI18 -> 3646.5185 | DP18: =VLOOKUP($F18,Activities!$A$9:$I$180,7,FALSE)/$AI18 -> 3663.0438 | DQ18: =VLOOKUP($F18,Activities!$A$9:$I$180,8,FALSE)/$AI18 -> 3659.0085 | DR18: =VLOOKUP($F18,Activities!$A$9:$I$180,9,FALSE)/$AI18 -> 3642.8675
A19: Res04_01 | B19: Gebouwde omgeving | C19: Final | D19: Residential | E19: Dwellings | F19: Houses - Residential Dwellings | G19: House with insulation GFE - Residential Dwellings | H19: [khouses/y] | I19: 0 | J19: 0 | K19: 0 | L19: 0 | M19: 0 | N19: 0 | O19: 0 | P19: 0 | Q19: 0 | R19: 0 | S19: 0 | T19: 0 | U19: 0 | V19: 0 | W19: 0 | X19: 0 | Y19: 0 | Z19: 0 | AA19: 0 | AB19: 0 | AC19: 0 | AD19: 0 | AE19: 0.08 | AF19: 0 | AG19: 40 | AH19: 40 | AI19: 1 | AJ19: Operation | AK19: Built Environment | AY19: none | BL19: 1 | BN19: =IF(SUM(CB19:CB19)<DL19,CB19,MAX(DL19-SUM(CB19:CB19),0)) -> 500 | BU19: 500 | CB19: 500 | CC19: =DM19 -> 1822.1836 | CD19: =DN19 -> 1862.9039 | CE19: =DO19 -> 1884.7538 | CF19: =DP19 -> 1893.2951 | CG19: =DQ19 -> 1891.2094 | CH19: =DR19 -> 1882.8667 | CX19: 1 | CY19: 1 | CZ19: 1 | DA19: 1 | DB19: 1 | DC19: 1 | DK19: [1],[37],[38] | DL19: =VLOOKUP($F19,Activities!$A$9:$I$180,3,FALSE)/$AI19 -> 1747 | DM19: =VLOOKUP($F19,Activities!$A$9:$I$180,4,FALSE)/$AI19 -> 1822.1836 | DN19: =VLOOKUP($F19,Activities!$A$9:$I$180,5,FALSE)/$AI19 -> 1862.9039 | DO19: =VLOOKUP($F19,Activities!$A$9:$I$180,6,FALSE)/$AI19 -> 1884.7538 | DP19: =VLOOKUP($F19,Activities!$A$9:$I$180,7,FALSE)/$AI19 -> 1893.2951 | DQ19: =VLOOKUP($F19,Activities!$A$9:$I$180,8,FALSE)/$AI19 -> 1891.2094 | DR19: =VLOOKUP($F19,Activities!$A$9:$I$180,9,FALSE)/$AI19 -> 1882.8667
A20: Res04_02 | B20: Gebouwde omgeving | C20: Final | D20: Residential | E20: Dwellings | F20: Houses - Residential Dwellings | G20: House with insulation DC - Residential Dwellings | H20: [khouses/y] | I20: 5.6 | J20: 5.6 | K20: 5.6 | L20: 0 | M20: 0 | N20: 0 | O20: 0 | P20: 0 | Q20: 0 | R20: 0 | S20: 0 | T20: 0 | U20: 0 | V20: 0 | W20: 0 | X20: 0 | Y20: 0 | Z20: 0 | AA20: 0 | AB20: 0 | AC20: 0 | AD20: 0 | AE20: 0.08 | AF20: 0 | AG20: 40 | AH20: 40 | AI20: 1 | AJ20: Operation | AK20: Built Environment | AY20: none | BL20: 1 | BN20: 500 | BU20: 500 | CB20: 810 | CC20: =DM20 -> 1822.1836 | CD20: =DN20 -> 1862.9039 | CE20: =DO20 -> 1884.7538 | CF20: =DP20 -> 1893.2951 | CG20: =DQ20 -> 1891.2094 | CH20: =DR20 -> 1882.8667 | CY20: 1 | CZ20: 1 | DA20: 1 | DB20: 1 | DC20: 1 | DK20: [12] | DL20: =VLOOKUP($F20,Activities!$A$9:$I$180,3,FALSE)/$AI20 -> 1747 | DM20: =VLOOKUP($F20,Activities!$A$9:$I$180,4,FALSE)/$AI20 -> 1822.1836 | DN20: =VLOOKUP($F20,Activities!$A$9:$I$180,5,FALSE)/$AI20 -> 1862.9039 | DO20: =VLOOKUP($F20,Activities!$A$9:$I$180,6,FALSE)/$AI20 -> 1884.7538 | DP20: =VLOOKUP($F20,Activities!$A$9:$I$180,7,FALSE)/$AI20 -> 1893.2951 | DQ20: =VLOOKUP($F20,Activities!$A$9:$I$180,8,FALSE)/$AI20 -> 1891.2094 | DR20: =VLOOKUP($F20,Activities!$A$9:$I$180,9,FALSE)/$AI20 -> 1882.8667
A21: Res04_03 | B21: Gebouwde omgeving | C21: Final | D21: Residential | E21: Dwellings | F21: Houses - Residential Dwellings | G21: House with insulation B - Residential Dwellings | H21: [khouses/y] | I21: 17.19 | J21: 17.19 | K21: 17.19 | L21: 11.6 | M21: 11.6 | N21: 0 | O21: 0 | P21: 0 | Q21: 0 | R21: 0 | S21: 0 | T21: 0 | U21: 0 | V21: 0 | W21: 0 | X21: 0 | Y21: 0 | Z21: 0 | AA21: 0 | AB21: 0 | AC21: 0 | AD21: 0 | AE21: 0.08 | AF21: 0 | AG21: 40 | AH21: 40 | AI21: 1 | AJ21: Operation | AK21: Built Environment | AY21: none | BL21: 1 | BN21: 500 | BU21: 500 | CB21: 710 | CC21: =DM21 -> 1822.1836 | CD21: =DN21 -> 1862.9039 | CE21: =DO21 -> 1884.7538 | CF21: =DP21 -> 1893.2951 | CG21: =DQ21 -> 1891.2094 | CH21: =DR21 -> 1882.8667 | CZ21: 1 | DA21: 1 | DB21: 1 | DC21: 1 | DK21: [1],[12] | DL21: =VLOOKUP($F21,Activities!$A$9:$I$180,3,FALSE)/$AI21 -> 1747 | DM21: =VLOOKUP($F21,Activities!$A$9:$I$180,4,FALSE)/$AI21 -> 1822.1836 | DN21: =VLOOKUP($F21,Activities!$A$9:$I$180,5,FALSE)/$AI21 -> 1862.9039 | DO21: =VLOOKUP($F21,Activities!$A$9:$I$180,6,FALSE)/$AI21 -> 1884.7538 | DP21: =VLOOKUP($F21,Activities!$A$9:$I$180,7,FALSE)/$AI21 -> 1893.2951 | DQ21: =VLOOKUP($F21,Activities!$A$9:$I$180,8,FALSE)/$AI21 -> 1891.2094 | DR21: =VLOOKUP($F21,Activities!$A$9:$I$180,9,FALSE)/$AI21 -> 1882.8667
A22: Res04_04 | B22: Gebouwde omgeving | C22: Final | D22: Residential | E22: Dwellings | F22: Houses - Residential Dwellings | G22: House with insulation A - Residential Dwellings | H22: [khouses/y] | I22: 23.09 | J22: 22.51 | K22: 21.93 | L22: 15.8 | M22: 15 | N22: 3.4 | O22: 3.4 | P22: 0 | Q22: 0 | R22: 0 | S22: 0 | T22: 0 | U22: 0 | V22: 0 | W22: 0 | X22: 0 | Y22: 0 | Z22: 0 | AA22: 0 | AB22: 0 | AC22: 0 | AD22: 0 | AE22: 0.08 | AF22: 0 | AG22: 40 | AH22: 40 | AI22: 1 | AJ22: Operation | AK22: Built Environment | AY22: none | BN22: 100 | BU22: 100 | CB22: 260 | CC22: =DM22 -> 1822.1836 | CD22: =DN22 -> 1862.9039 | CE22: =DO22 -> 1884.7538 | CF22: =DP22 -> 1893.2951 | CG22: =DQ22 -> 1891.2094 | CH22: =DR22 -> 1882.8667 | DF22: 1 | DG22: 1 | DH22: 1 | DI22: 1 | DJ22: 1 | DK22: [1],[12] | DL22: =VLOOKUP($F22,Activities!$A$9:$I$180,3,FALSE)/$AI22 -> 1747 | DM22: =VLOOKUP($F22,Activities!$A$9:$I$180,4,FALSE)/$AI22 -> 1822.1836 | DN22: =VLOOKUP($F22,Activities!$A$9:$I$180,5,FALSE)/$AI22 -> 1862.9039 | DO22: =VLOOKUP($F22,Activities!$A$9:$I$180,6,FALSE)/$AI22 -> 1884.7538 | DP22: =VLOOKUP($F22,Activities!$A$9:$I$180,7,FALSE)/$AI22 -> 1893.2951 | DQ22: =VLOOKUP($F22,Activities!$A$9:$I$180,8,FALSE)/$AI22 -> 1891.2094 | DR22: =VLOOKUP($F22,Activities!$A$9:$I$180,9,FALSE)/$AI22 -> 1882.8667
A23: Res04_05 | B23: Gebouwde omgeving | C23: Final | D23: Residential | E23: Dwellings | F23: Houses - Residential Dwellings | G23: House with insulation A+ - Residential Dwellings | H23: [khouses/y] | I23: 28.28 | J23: 26.86 | K23: 25.45 | L23: 18.6 | M23: 18 | N23: 6 | O23: 5 | P23: 0 | Q23: 0 | R23: 0 | S23: 0 | T23: 0 | U23: 0 | V23: 0 | W23: 0 | X23: 0 | Y23: 0 | Z23: 0 | AA23: 0 | AB23: 0 | AC23: 0 | AD23: 0 | AE23: 0.08 | AF23: 0 | AG23: 40 | AH23: 40 | AI23: 1 | AJ23: Operation | AK23: Built Environment | AY23: none | BN23: 100 | BU23: 100 | CB23: 160 | CC23: =DM23 -> 1822.1836 | CD23: =DN23 -> 1862.9039 | CE23: =DO23 -> 1884.7538 | CF23: =DP23 -> 1893.2951 | CG23: =DQ23 -> 1891.2094 | CH23: =DR23 -> 1882.8667 | DF23: 1 | DG23: 1 | DH23: 1 | DI23: 1 | DJ23: 1 | DK23: [1],[D] | DL23: =VLOOKUP($F23,Activities!$A$9:$I$180,3,FALSE)/$AI23 -> 1747 | DM23: =VLOOKUP($F23,Activities!$A$9:$I$180,4,FALSE)/$AI23 -> 1822.1836 | DN23: =VLOOKUP($F23,Activities!$A$9:$I$180,5,FALSE)/$AI23 -> 1862.9039 | DO23: =VLOOKUP($F23,Activities!$A$9:$I$180,6,FALSE)/$AI23 -> 1884.7538 | DP23: =VLOOKUP($F23,Activities!$A$9:$I$180,7,FALSE)/$AI23 -> 1893.2951 | DQ23: =VLOOKUP($F23,Activities!$A$9:$I$180,8,FALSE)/$AI23 -> 1891.2094 | DR23: =VLOOKUP($F23,Activities!$A$9:$I$180,9,FALSE)/$AI23 -> 1882.8667
A24: Ser01_01 | B24: Gebouwde omgeving | C24: Final | D24: Services | E24: Appliances | F24: Electricity demand - Services | G24: Dummy standard electricity consumption - Services | H24: [PJ/y] | I24: 0 | J24: 0 | K24: 0 | L24: 0 | M24: 0 | N24: 0 | O24: 0 | P24: 0 | Q24: 0 | R24: 0 | S24: 0 | T24: 0 | U24: 0 | V24: 0 | W24: 0 | X24: 0 | Y24: 0 | Z24: 0 | AA24: 0 | AB24: 0 | AC24: 0 | AD24: 0 | AE24: 0.08 | AF24: 0 | AG24: 1 | AH24: 1 | AI24: 1 | AJ24: Operation | AK24: Standard Load | AY24: none | BL24: 1 | BN24: =DL24 -> 124.9 | BU24: =IF(BL24=1,BN24,0) -> 124.9 | CB24: =DL24 -> 124.9 | CC24: =DM24 -> 127.18872 | CD24: =DN24 -> 138.74361 | CE24: =DO24 -> 148.80423 | CF24: =DP24 -> 160.86911 | CG24: =DQ24 -> 175.1944 | CH24: =DR24 -> 190.288 | DK24: [39] | DL24: =VLOOKUP($F24,Activities!$A$9:$I$180,3,FALSE)/$AI24 -> 124.9 | DM24: =VLOOKUP($F24,Activities!$A$9:$I$180,4,FALSE)/$AI24 -> 127.18872 | DN24: =VLOOKUP($F24,Activities!$A$9:$I$180,5,FALSE)/$AI24 -> 138.74361 | DO24: =VLOOKUP($F24,Activities!$A$9:$I$180,6,FALSE)/$AI24 -> 148.80423 | DP24: =VLOOKUP($F24,Activities!$A$9:$I$180,7,FALSE)/$AI24 -> 160.86911 | DQ24: =VLOOKUP($F24,Activities!$A$9:$I$180,8,FALSE)/$AI24 -> 175.1944 | DR24: =VLOOKUP($F24,Activities!$A$9:$I$180,9,FALSE)/$AI24 -> 190.288
A25: Ser01_02 | B25: Gebouwde omgeving | C25: Final | D25: Services | E25: Appliances | F25: Electricity demand - Services | G25: Flexible standard electricity consumption - Services | H25: [PJ/y] | I25: 0.5 | J25: 0.5 | K25: 0.5 | L25: 0.3 | M25: 0.1 | N25: 0 | O25: 0 | P25: 0 | Q25: 0 | R25: 0 | S25: 0 | T25: 0 | U25: 0 | V25: 0 | W25: 0 | X25: 0 | Y25: 0 | Z25: 0 | AA25: 0 | AB25: 0 | AC25: 0 | AD25: 0 | AE25: 0.08 | AF25: 0 | AG25: 15 | AH25: 15 | AI25: 1 | AJ25: Operation | AK25: Standard Load | AY25: DR shifting | AZ25: Electricity NL - LV | BA25: 1 | BC25: 1 day [d] | BD25: 0.02 | BE25: 0.8 | BN25: =CB25 -> 0.5 | BU25: =IF(BL25=1,BN25,0) -> 0 | CB25: 0.5 | CC25: 1 | CD25: 2 | CE25: 4 | CF25: 10 | CG25: 20 | CH25: 40 | DK25: [39] | DL25: =VLOOKUP($F25,Activities!$A$9:$I$180,3,FALSE)/$AI25 -> 124.9 | DM25: =VLOOKUP($F25,Activities!$A$9:$I$180,4,FALSE)/$AI25 -> 127.18872 | DN25: =VLOOKUP($F25,Activities!$A$9:$I$180,5,FALSE)/$AI25 -> 138.74361 | DO25: =VLOOKUP($F25,Activities!$A$9:$I$180,6,FALSE)/$AI25 -> 148.80423 | DP25: =VLOOKUP($F25,Activities!$A$9:$I$180,7,FALSE)/$AI25 -> 160.86911 | DQ25: =VLOOKUP($F25,Activities!$A$9:$I$180,8,FALSE)/$AI25 -> 175.1944 | DR25: =VLOOKUP($F25,Activities!$A$9:$I$180,9,FALSE)/$AI25 -> 190.288
A26: Ser02_01 | B26: Gebouwde omgeving | C26: Final | D26: Services | E26: Buildings | F26: Space - Services | G26: Space with insulation GFE - Services | H26: [Mm2/y] | I26: 0 | J26: 0 | K26: 0 | L26: 0 | M26: 0 | N26: 0 | O26: 0 | P26: 0 | Q26: 0.32 | R26: 0.32 | S26: 0.32 | T26: 0.32 | U26: 0.32 | V26: 0.32 | W26: 0.32 | X26: 0 | Y26: 0 | Z26: 0 | AA26: 0 | AB26: 0 | AC26: 0 | AD26: 0 | AE26: 0.08 | AF26: 0 | AG26: 25 | AH26: 25 | AI26: 1 | AJ26: Operation | AK26: Built Environment | AY26: none | BL26: 1 | BN26: =IF(SUM(CB26:CB26)<DL26,CB26,MAX(DL26-SUM(CB26:CB26),0)) -> 190 | BU26: 135 | CB26: 190 | CC26: =DM26 -> 446.76845 | CD26: =DN26 -> 487.35663 | CE26: =DO26 -> 522.696 | CF26: =DP26 -> 565.07562 | CG26: =DQ26 -> 615.39523 | CH26: =DR26 -> 668.41365 | CX26: 1 | CY26: 1 | CZ26: 1 | DA26: 1 | DB26: 1 | DC26: 1 | DK26: [39] | DL26: =VLOOKUP($F26,Activities!$A$9:$I$180,3,FALSE)/$AI26 -> 438.729 | DM26: =VLOOKUP($F26,Activities!$A$9:$I$180,4,FALSE)/$AI26 -> 446.76845 | DN26: =VLOOKUP($F26,Activities!$A$9:$I$180,5,FALSE)/$AI26 -> 487.35663 | DO26: =VLOOKUP($F26,Activities!$A$9:$I$180,6,FALSE)/$AI26 -> 522.696 | DP26: =VLOOKUP($F26,Activities!$A$9:$I$180,7,FALSE)/$AI26 -> 565.07562 | DQ26: =VLOOKUP($F26,Activities!$A$9:$I$180,8,FALSE)/$AI26 -> 615.39523 | DR26: =VLOOKUP($F26,Activities!$A$9:$I$180,9,FALSE)/$AI26 -> 668.41365
A27: Ser02_02 | B27: Gebouwde omgeving | C27: Final | D27: Services | E27: Buildings | F27: Space - Services | G27: Space with insulation DC - Services | H27: [Mm2/y] | I27: 21.9 | J27: 21.9 | K27: 21.9 | L27: 0 | M27: 0 | N27: 0 | O27: 0 | P27: 0 | Q27: 0.32 | R27: 0.32 | S27: 0.32 | T27: 0.32 | U27: 0.32 | V27: 0.32 | W27: 0.32 | X27: 0 | Y27: 0 | Z27: 0 | AA27: 0 | AB27: 0 | AC27: 0 | AD27: 0 | AE27: 0.08 | AF27: 0 | AG27: 25 | AH27: 25 | AI27: 1 | AJ27: Operation | AK27: Built Environment | AY27: none | BL27: 1 | BN27: =IF(SUM(CB26:CB27)<DL27,CB27,MAX(DL27-SUM(CB26:CB26),0)) -> 100 | BU27: =IF(BL27=1,BN27,0) -> 100 | CB27: 100 | CC27: =DM27 -> 446.76845 | CD27: =DN27 -> 487.35663 | CE27: =DO27 -> 522.696 | CF27: =DP27 -> 565.07562 | CG27: =DQ27 -> 615.39523 | CH27: =DR27 -> 668.41365 | CY27: 1 | CZ27: 1 | DA27: 1 | DB27: 1 | DC27: 1 | DK27: [1] | DL27: =VLOOKUP($F27,Activities!$A$9:$I$180,3,FALSE)/$AI27 -> 438.729 | DM27: =VLOOKUP($F27,Activities!$A$9:$I$180,4,FALSE)/$AI27 -> 446.76845 | DN27: =VLOOKUP($F27,Activities!$A$9:$I$180,5,FALSE)/$AI27 -> 487.35663 | DO27: =VLOOKUP($F27,Activities!$A$9:$I$180,6,FALSE)/$AI27 -> 522.696 | DP27: =VLOOKUP($F27,Activities!$A$9:$I$180,7,FALSE)/$AI27 -> 565.07562 | DQ27: =VLOOKUP($F27,Activities!$A$9:$I$180,8,FALSE)/$AI27 -> 615.39523 | DR27: =VLOOKUP($F27,Activities!$A$9:$I$180,9,FALSE)/$AI27 -> 668.41365
A28: Ser02_03 | B28: Gebouwde omgeving | C28: Final | D28: Services | E28: Buildings | F28: Space - Services | G28: Space with insulation B - Services | H28: [Mm2/y] | I28: 95.3 | J28: 95.3 | K28: 95.3 | L28: 73.1 | M28: 73.1 | N28: 22 | O28: 22 | P28: 0 | Q28: 0.32 | R28: 0.32 | S28: 0.32 | T28: 0.32 | U28: 0.32 | V28: 0.32 | W28: 0.32 | X28: 0 | Y28: 0 | Z28: 0 | AA28: 0 | AB28: 0 | AC28: 0 | AD28: 0 | AE28: 0.08 | AF28: 0 | AG28: 25 | AH28: 25 | AI28: 1 | AJ28: Operation | AK28: Built Environment | AY28: none | BN28: =IF(SUM(CB26:CB28)<DL28,CB28,MAX(DL28-SUM(CB26:CB27),0)) -> 148.729 | BU28: 180 | CB28: 210 | CC28: =DM28 -> 446.76845 | CD28: =DN28 -> 487.35663 | CE28: =DO28 -> 522.696 | CF28: =DP28 -> 565.07562 | CG28: =DQ28 -> 615.39523 | CH28: =DR28 -> 668.41365 | CZ28: 1 | DA28: 1 | DB28: 1 | DC28: 1 | DK28: [1],[12] | DL28: =VLOOKUP($F28,Activities!$A$9:$I$180,3,FALSE)/$AI28 -> 438.729 | DM28: =VLOOKUP($F28,Activities!$A$9:$I$180,4,FALSE)/$AI28 -> 446.76845 | DN28: =VLOOKUP($F28,Activities!$A$9:$I$180,5,FALSE)/$AI28 -> 487.35663 | DO28: =VLOOKUP($F28,Activities!$A$9:$I$180,6,FALSE)/$AI28 -> 522.696 | DP28: =VLOOKUP($F28,Activities!$A$9:$I$180,7,FALSE)/$AI28 -> 565.07562 | DQ28: =VLOOKUP($F28,Activities!$A$9:$I$180,8,FALSE)/$AI28 -> 615.39523 | DR28: =VLOOKUP($F28,Activities!$A$9:$I$180,9,FALSE)/$AI28 -> 668.41365
A29: Ser02_04 | B29: Gebouwde omgeving | C29: Final | D29: Services | E29: Buildings | F29: Space - Services | G29: Space with insulation A - Services | H29: [Mm2/y] | I29: 109.9 | J29: 107.2 | K29: 104.5 | L29: 82.6 | M29: 77.7 | N29: 26 | O29: 24 | P29: 0 | Q29: 0.32 | R29: 0.32 | S29: 0.32 | T29: 0.32 | U29: 0.32 | V29: 0.32 | W29: 0.32 | X29: 0 | Y29: 0 | Z29: 0 | AA29: 0 | AB29: 0 | AC29: 0 | AD29: 0 | AE29: 0.08 | AF29: 0 | AG29: 25 | AH29: 25 | AI29: 1 | AJ29: Operation | AK29: Built Environment | AY29: none | BN29: =IF(SUM(CB26:CB29)<DL29,CB29,MAX(DL29-SUM(CB26:CB28),0)) -> 0 | BQ29: 0 | BR29: 0 | BT29: 0 | BU29: =IF(BL29=1,BN29,0) -> 0 | CB29: 10 | CC29: =DM29 -> 446.76845 | CD29: =DN29 -> 487.35663 | CE29: =DO29 -> 522.696 | CF29: =DP29 -> 565.07562 | CG29: =DQ29 -> 615.39523 | CH29: =DR29 -> 668.41365 | DF29: 1 | DG29: 1 | DH29: 1 | DI29: 1 | DJ29: 1 | DK29: [12] | DL29: =VLOOKUP($F29,Activities!$A$9:$I$180,3,FALSE)/$AI29 -> 438.729 | DM29: =VLOOKUP($F29,Activities!$A$9:$I$180,4,FALSE)/$AI29 -> 446.76845 | DN29: =VLOOKUP($F29,Activities!$A$9:$I$180,5,FALSE)/$AI29 -> 487.35663 | DO29: =VLOOKUP($F29,Activities!$A$9:$I$180,6,FALSE)/$AI29 -> 522.696 | DP29: =VLOOKUP($F29,Activities!$A$9:$I$180,7,FALSE)/$AI29 -> 565.07562 | DQ29: =VLOOKUP($F29,Activities!$A$9:$I$180,8,FALSE)/$AI29 -> 615.39523 | DR29: =VLOOKUP($F29,Activities!$A$9:$I$180,9,FALSE)/$AI29 -> 668.41365
A30: Ser02_05 | B30: Gebouwde omgeving | C30: Final | D30: Services | E30: Buildings | F30: Space - Services | G30: Space with insulation A+ - Services | H30: [Mm2/y] | I30: 122.64 | J30: 116.5 | K30: 110.4 | L30: 88.5 | M30: 82.5 | N30: 30 | O30: 28 | P30: 0 | Q30: 0.32 | R30: 0.32 | S30: 0.32 | T30: 0.32 | U30: 0.32 | V30: 0.32 | W30: 0.32 | X30: 0 | Y30: 0 | Z30: 0 | AA30: 0 | AB30: 0 | AC30: 0 | AD30: 0 | AE30: 0.08 | AF30: 0 | AG30: 25 | AH30: 25 | AI30: 1 | AJ30: Operation | AK30: Built Environment | AY30: none | BN30: =IF(SUM(CB26:CB30)<DL30,CB30,MAX(DL30-SUM(CB26:CB29),0)) -> 0 | BQ30: 0 | BR30: 0 | BT30: 0 | BU30: =IF(BL30=1,BN30,0) -> 0 | CB30: 5 | CC30: =DM30 -> 446.76845 | CD30: =DN30 -> 487.35663 | CE30: =DO30 -> 522.696 | CF30: =DP30 -> 565.07562 | CG30: =DQ30 -> 615.39523 | CH30: =DR30 -> 668.41365 | DF30: 1 | DG30: 1 | DH30: 1 | DI30: 1 | DJ30: 1 | DK30: [12] | DL30: =VLOOKUP($F30,Activities!$A$9:$I$180,3,FALSE)/$AI30 -> 438.729 | DM30: =VLOOKUP($F30,Activities!$A$9:$I$180,4,FALSE)/$AI30 -> 446.76845 | DN30: =VLOOKUP($F30,Activities!$A$9:$I$180,5,FALSE)/$AI30 -> 487.35663 | DO30: =VLOOKUP($F30,Activities!$A$9:$I$180,6,FALSE)/$AI30 -> 522.696 | DP30: =VLOOKUP($F30,Activities!$A$9:$I$180,7,FALSE)/$AI30 -> 565.07562 | DQ30: =VLOOKUP($F30,Activities!$A$9:$I$180,8,FALSE)/$AI30 -> 615.39523 | DR30: =VLOOKUP($F30,Activities!$A$9:$I$180,9,FALSE)/$AI30 -> 668.41365
A31: Agr01_01 | B31: Landbouw | C31: Final | D31: Agriculture | E31: Appliances | F31: Electricity demand - Agricuture | G31: Dummy standard electricity consumption - Agriculture | H31: [PJ/y] | I31: 0 | J31: 0 | K31: 0 | L31: 0 | M31: 0 | N31: 0 | O31: 0 | P31: 0 | Q31: 0 | R31: 0 | S31: 0 | T31: 0 | U31: 0 | V31: 0 | W31: 0 | X31: 0 | Y31: 0 | Z31: 0 | AA31: 0 | AB31: 0 | AC31: 0 | AD31: 0 | AE31: 0.08 | AF31: 0 | AG31: 1 | AH31: 1 | AI31: 1 | AJ31: Operation | AK31: Standard Load | AY31: none | BL31: 1 | BN31: =CB31 -> 25.2 | BQ31: 0 | BR31: 0 | BS31: 0 | BT31: 0 | BU31: =IF(BL31=1,BN31,0) -> 25.2 | CB31: =DL31 -> 25.2 | CC31: =DM31 -> 25.661775 | CD31: =DN31 -> 27.993106 | CE31: =DO31 -> 30.022951 | CF31: =DP31 -> 32.457179 | CG31: =DQ31 -> 35.347469 | CH31: =DR31 -> 38.392775 | DK31: [1],[9],[12] | DL31: =VLOOKUP($F31,Activities!$A$9:$I$180,3,FALSE)/$AI31 -> 25.2 | DM31: =VLOOKUP($F31,Activities!$A$9:$I$180,4,FALSE)/$AI31 -> 25.661775 | DN31: =VLOOKUP($F31,Activities!$A$9:$I$180,5,FALSE)/$AI31 -> 27.993106 | DO31: =VLOOKUP($F31,Activities!$A$9:$I$180,6,FALSE)/$AI31 -> 30.022951 | DP31: =VLOOKUP($F31,Activities!$A$9:$I$180,7,FALSE)/$AI31 -> 32.457179 | DQ31: =VLOOKUP($F31,Activities!$A$9:$I$180,8,FALSE)/$AI31 -> 35.347469 | DR31: =VLOOKUP($F31,Activities!$A$9:$I$180,9,FALSE)/$AI31 -> 38.392775
A32: Agr02_01 | B32: Landbouw | C32: Final | D32: Agriculture | E32: Heat demand horticulture | F32: Heat demand - Agriculture | G32: Dummy balance heat consumption - Agriculture Horticulture | H32: [PJ/y] | I32: 0 | J32: 0 | K32: 0 | L32: 0 | M32: 0 | N32: 0 | O32: 0 | P32: 0 | Q32: 0 | R32: 0 | S32: 0 | T32: 0 | U32: 0 | V32: 0 | W32: 0 | X32: 0 | Y32: 0 | Z32: 0 | AA32: 0 | AB32: 0 | AC32: 0 | AD32: 0 | AE32: 0.08 | AF32: 0 | AG32: 1 | AH32: 1 | AI32: 1 | AJ32: Operation | AK32: Flat high spread | AY32: none | BL32: 1 | BN32: =DL32 -> 72.53 | BO32: 0 | BP32: 0 | BQ32: 0 | BR32: 0 | BS32: 0 | BT32: 0 | BU32: =IF(BL32=1,BN32,0) -> 72.53 | CB32: =DL32 -> 72.53 | CC32: =DM32 -> 72.53 | CD32: =DN32 -> 72.53 | CE32: =DO32 -> 72.53 | CF32: =DP32 -> 72.53 | CG32: =DQ32 -> 72.53 | CH32: =DR32 -> 72.53 | DK32: [1],[9],[12] | DL32: =VLOOKUP($F32,Activities!$A$9:$I$180,3,FALSE)/$AI32 -> 72.53 | DM32: =VLOOKUP($F32,Activities!$A$9:$I$180,4,FALSE)/$AI32 -> 72.53 | DN32: =VLOOKUP($F32,Activities!$A$9:$I$180,5,FALSE)/$AI32 -> 72.53 | DO32: =VLOOKUP($F32,Activities!$A$9:$I$180,6,FALSE)/$AI32 -> 72.53 | DP32: =VLOOKUP($F32,Activities!$A$9:$I$180,7,FALSE)/$AI32 -> 72.53 | DQ32: =VLOOKUP($F32,Activities!$A$9:$I$180,8,FALSE)/$AI32 -> 72.53 | DR32: =VLOOKUP($F32,Activities!$A$9:$I$180,9,FALSE)/$AI32 -> 72.53
A33: Agr04_01 | B33: Mobiliteit | C33: Final | D33: Agriculture | E33: Machinery | F33: Machinery - Agriculture | G33: Fuel based Machinery - Agriculture | H33: [PJ/y] | I33: 265 | J33: 265 | K33: 265 | L33: 265 | M33: 265 | N33: 265 | O33: 265 | P33: 0 | Q33: 0 | R33: 0 | S33: 0 | T33: 0 | U33: 0 | V33: 0 | W33: 0 | X33: 0 | Y33: 0 | Z33: 0 | AA33: 0 | AB33: 0 | AC33: 0 | AD33: 0 | AE33: 0.08 | AF33: 0 | AG33: 15 | AH33: 15 | AI33: 1 | AJ33: Operation | AK33: Flat high spread | AY33: none | BN33: =DL33-BN34 -> 23.1 | BO33: 6.9 | BP33: 5 | BU33: =BN33 -> 23.1 | CB33: =DL33 -> 25.2 | CC33: =DM33 -> 25.2 | CD33: =DN33 -> 25.2 | CE33: =DO33 -> 25.2 | CF33: =DP33 -> 25.2 | CG33: =DQ33 -> 25.2 | CH33: =DR33 -> 25.2 | DK33: [12] | DL33: =VLOOKUP($F33,Activities!$A$9:$I$180,3,FALSE)/$AI33 -> 25.2 | DM33: =VLOOKUP($F33,Activities!$A$9:$I$180,4,FALSE)/$AI33 -> 25.2 | DN33: =VLOOKUP($F33,Activities!$A$9:$I$180,5,FALSE)/$AI33 -> 25.2 | DO33: =VLOOKUP($F33,Activities!$A$9:$I$180,6,FALSE)/$AI33 -> 25.2 | DP33: =VLOOKUP($F33,Activities!$A$9:$I$180,7,FALSE)/$AI33 -> 25.2 | DQ33: =VLOOKUP($F33,Activities!$A$9:$I$180,8,FALSE)/$AI33 -> 25.2 | DR33: =VLOOKUP($F33,Activities!$A$9:$I$180,9,FALSE)/$AI33 -> 25.2
A34: Agr04_02 | B34: Mobiliteit | C34: Final | D34: Agriculture | E34: Machinery | F34: Machinery - Agriculture | G34: Hybrid Machinery - Agriculture | H34: [PJ/y] | I34: 570 | J34: 541.5 | K34: 514.43 | L34: 488.7 | M34: 464.27 | N34: 441.06 | O34: 419 | P34: 0 | Q34: 0 | R34: 0 | S34: 0 | T34: 0 | U34: 0 | V34: 0 | W34: 0 | X34: 0 | Y34: 0 | Z34: 0 | AA34: 0 | AB34: 0 | AC34: 0 | AD34: 0 | AE34: 0.08 | AF34: 0 | AG34: 15 | AH34: 15 | AI34: 1 | AJ34: Operation | AK34: Flat high spread | AY34: none | BN34: 2.1 | BO34: 0.07 | BP34: 0.5 | BQ34: 1.5 | BU34: =BN34 -> 2.1 | CB34: =DL34 -> 25.2 | CC34: =DM34 -> 25.2 | CD34: =DN34 -> 25.2 | CE34: =DO34 -> 25.2 | CF34: =DP34 -> 25.2 | CG34: =DQ34 -> 25.2 | CH34: =DR34 -> 25.2 | DK34: [1] | DL34: =VLOOKUP($F34,Activities!$A$9:$I$180,3,FALSE)/$AI34 -> 25.2 | DM34: =VLOOKUP($F34,Activities!$A$9:$I$180,4,FALSE)/$AI34 -> 25.2 | DN34: =VLOOKUP($F34,Activities!$A$9:$I$180,5,FALSE)/$AI34 -> 25.2 | DO34: =VLOOKUP($F34,Activities!$A$9:$I$180,6,FALSE)/$AI34 -> 25.2 | DP34: =VLOOKUP($F34,Activities!$A$9:$I$180,7,FALSE)/$AI34 -> 25.2 | DQ34: =VLOOKUP($F34,Activities!$A$9:$I$180,8,FALSE)/$AI34 -> 25.2 | DR34: =VLOOKUP($F34,Activities!$A$9:$I$180,9,FALSE)/$AI34 -> 25.2
A35: IBM01_01 | B35: Industrie | C35: Final | D35: Industry | E35: Basic Metals | F35: Steel production - Basic Metals Industry | G35: Blast furnace BOF - Steel Production | H35: [Mton_Steel/y] | I35: 550.5 | J35: 550.5 | K35: 550.5 | L35: 550.5 | M35: 550.5 | N35: 550.5 | O35: 550.5 | P35: 0 | Q35: 34.6 | R35: 34.6 | S35: 34.6 | T35: 34.6 | U35: 34.6 | V35: 34.6 | W35: 34.6 | X35: 170 | Y35: 170 | Z35: 170 | AA35: 170 | AB35: 170 | AC35: 170 | AD35: 170 | AE35: 0.08 | AF35: 0 | AG35: 30 | AH35: 30 | AI35: 1 | AJ35: Operation | AK35: Flat | AY35: none | BL35: 1 | BN35: =DL35 -> 6.143 | BU35: =IF(BL35=1,BN35,0) -> 6.143 | CB35: =DL35 -> 6.143 | CC35: =DM35 -> 6.143 | CD35: =DN35 -> 6.143 | CE35: =DO35 -> 6.143 | CF35: =DP35 -> 6.143 | CG35: =DQ35 -> 6.143 | CX35: 1 | CY35: 1 | CZ35: 1 | DA35: 1 | DB35: 1 | DC35: 1 | DK35: [51] | DL35: =VLOOKUP($F35,Activities!$A$9:$I$180,3,FALSE)/$AI35 -> 6.143 | DM35: =VLOOKUP($F35,Activities!$A$9:$I$180,4,FALSE)/$AI35 -> 6.143 | DN35: =VLOOKUP($F35,Activities!$A$9:$I$180,5,FALSE)/$AI35 -> 6.143 | DO35: =VLOOKUP($F35,Activities!$A$9:$I$180,6,FALSE)/$AI35 -> 6.143 | DP35: =VLOOKUP($F35,Activities!$A$9:$I$180,7,FALSE)/$AI35 -> 6.143 | DQ35: =VLOOKUP($F35,Activities!$A$9:$I$180,8,FALSE)/$AI35 -> 6.143 | DR35: =VLOOKUP($F35,Activities!$A$9:$I$180,9,FALSE)/$AI35 -> 6.143
A36: IBM01_02 | B36: Industrie | C36: Final | D36: Industry | E36: Basic Metals | F36: Steel production - Basic Metals Industry | G36: Blast furnace BOF wCCUS (end-of-pipe) - Steel Production | H36: [Mton_Steel/y] | I36: 795 | J36: 795 | K36: 795 | L36: 795 | M36: 795 | N36: 795 | O36: 795 | P36: 0 | Q36: 60.9 | R36: 60.9 | S36: 60.9 | T36: 60.9 | U36: 60.9 | V36: 60.9 | W36: 60.9 | X36: 170 | Y36: 170 | Z36: 170 | AA36: 170 | AB36: 170 | AC36: 170 | AD36: 170 | AE36: 0.08 | AF36: 0 | AG36: 30 | AH36: 30 | AI36: 1 | AJ36: Operation | AK36: Flat | AY36: none | BN36: 0 | BU36: =IF(BL36=1,BN36,0) -> 0 | CB36: 0 | CC36: 4 | CD36: =DN36 -> 6.143 | CE36: =DO36 -> 6.143 | CF36: =DP36 -> 6.143 | CG36: =DQ36 -> 6.143 | CH36: =DR36 -> 6.143 | DK36: [51] | DL36: =VLOOKUP($F36,Activities!$A$9:$I$180,3,FALSE)/$AI36 -> 6.143 | DM36: =VLOOKUP($F36,Activities!$A$9:$I$180,4,FALSE)/$AI36 -> 6.143 | DN36: =VLOOKUP($F36,Activities!$A$9:$I$180,5,FALSE)/$AI36 -> 6.143 | DO36: =VLOOKUP($F36,Activities!$A$9:$I$180,6,FALSE)/$AI36 -> 6.143 | DP36: =VLOOKUP($F36,Activities!$A$9:$I$180,7,FALSE)/$AI36 -> 6.143 | DQ36: =VLOOKUP($F36,Activities!$A$9:$I$180,8,FALSE)/$AI36 -> 6.143 | DR36: =VLOOKUP($F36,Activities!$A$9:$I$180,9,FALSE)/$AI36 -> 6.143
A37: IBM01_03 | B37: Industrie | C37: Final | D37: Industry | E37: Basic Metals | F37: Steel production - Basic Metals Industry | G37: Blast furnace BOF with top gas recycling wCCUS (end-of-pipe) - Steel Production | H37: [Mton_Steel/y] | I37: 815 | J37: 815 | K37: 815 | L37: 815 | M37: 815 | N37: 815 | O37: 815 | P37: 0 | Q37: 67.8 | R37: 67.8 | S37: 67.8 | T37: 67.8 | U37: 67.8 | V37: 67.8 | W37: 67.8 | X37: 170 | Y37: 170 | Z37: 170 | AA37: 170 | AB37: 170 | AC37: 170 | AD37: 170 | AE37: 0.08 | AF37: 0 | AG37: 30 | AH37: 30 | AI37: 1 | AJ37: Operation | AK37: Flat | AY37: none | BN37: 0 | BU37: =IF(BL37=1,BN37,0) -> 0 | CB37: 0 | CC37: 4 | CD37: =DN37 -> 6.143 | CE37: =DO37 -> 6.143 | CF37: =DP37 -> 6.143 | CG37: =DQ37 -> 6.143 | CH37: =DR37 -> 6.143 | DK37: [51] | DL37: =VLOOKUP($F37,Activities!$A$9:$I$180,3,FALSE)/$AI37 -> 6.143 | DM37: =VLOOKUP($F37,Activities!$A$9:$I$180,4,FALSE)/$AI37 -> 6.143 | DN37: =VLOOKUP($F37,Activities!$A$9:$I$180,5,FALSE)/$AI37 -> 6.143 | DO37: =VLOOKUP($F37,Activities!$A$9:$I$180,6,FALSE)/$AI37 -> 6.143 | DP37: =VLOOKUP($F37,Activities!$A$9:$I$180,7,FALSE)/$AI37 -> 6.143 | DQ37: =VLOOKUP($F37,Activities!$A$9:$I$180,8,FALSE)/$AI37 -> 6.143 | DR37: =VLOOKUP($F37,Activities!$A$9:$I$180,9,FALSE)/$AI37 -> 6.143
A38: IBM01_04 | B38: Industrie | C38: Final | D38: Industry | E38: Basic Metals | F38: Steel production - Basic Metals Industry | G38: Hisarna - Steel Production | H38: [Mton_Steel/y] | I38: 575 | J38: 470 | K38: 370 | L38: 360 | M38: 345 | N38: 335 | O38: 320 | P38: 0 | Q38: 70.9 | R38: 70.9 | S38: 62.6 | T38: 62.6 | U38: 52 | V38: 52 | W38: 42.2 | X38: 170 | Y38: 170 | Z38: 170 | AA38: 170 | AB38: 170 | AC38: 170 | AD38: 170 | AE38: 0.08 | AF38: 0 | AG38: 30 | AH38: 30 | AI38: 1 | AJ38: Operation | AK38: Flat | AY38: none | BN38: 0 | BU38: =IF(BL38=1,BN38,0) -> 0 | CC38: 0.06 | CD38: =DN38 -> 6.143 | CE38: =DO38 -> 6.143 | CF38: =DP38 -> 6.143 | CG38: =DQ38 -> 6.143 | CH38: =DR38 -> 6.143 | DK38: [51] | DL38: =VLOOKUP($F38,Activities!$A$9:$I$180,3,FALSE)/$AI38 -> 6.143 | DM38: =VLOOKUP($F38,Activities!$A$9:$I$180,4,FALSE)/$AI38 -> 6.143 | DN38: =VLOOKUP($F38,Activities!$A$9:$I$180,5,FALSE)/$AI38 -> 6.143 | DO38: =VLOOKUP($F38,Activities!$A$9:$I$180,6,FALSE)/$AI38 -> 6.143 | DP38: =VLOOKUP($F38,Activities!$A$9:$I$180,7,FALSE)/$AI38 -> 6.143 | DQ38: =VLOOKUP($F38,Activities!$A$9:$I$180,8,FALSE)/$AI38 -> 6.143 | DR38: =VLOOKUP($F38,Activities!$A$9:$I$180,9,FALSE)/$AI38 -> 6.143
A39: IBM01_05 | B39: Industrie | C39: Final | D39: Industry | E39: Basic Metals | F39: Steel production - Basic Metals Industry | G39: Hisarna wCCUS (cryogenic) - Steel Production | H39: [Mton_Steel/y] | I39: 840 | J39: 690 | K39: 545 | L39: 545 | M39: 545 | N39: 545 | O39: 545 | P39: 0 | Q39: 97.7 | R39: 97.7 | S39: 86.3 | T39: 86.3 | U39: 77 | V39: 77 | W39: 68.3 | X39: 170 | Y39: 170 | Z39: 170 | AA39: 170 | AB39: 170 | AC39: 170 | AD39: 170 | AE39: 0.08 | AF39: 0 | AG39: 30 | AH39: 30 | AI39: 1 | AJ39: Operation | AK39: Flat | AY39: none | BN39: 0 | BU39: =IF(BL39=1,BN39,0) -> 0 | CB39: 0 | CC39: 0.06 | CD39: =DN39 -> 6.143 | CE39: =DO39 -> 6.143 | CF39: =DP39 -> 6.143 | CG39: =DQ39 -> 6.143 | CH39: =DR39 -> 6.143 | DK39: [51] | DL39: =VLOOKUP($F39,Activities!$A$9:$I$180,3,FALSE)/$AI39 -> 6.143 | DM39: =VLOOKUP($F39,Activities!$A$9:$I$180,4,FALSE)/$AI39 -> 6.143 | DN39: =VLOOKUP($F39,Activities!$A$9:$I$180,5,FALSE)/$AI39 -> 6.143 | DO39: =VLOOKUP($F39,Activities!$A$9:$I$180,6,FALSE)/$AI39 -> 6.143 | DP39: =VLOOKUP($F39,Activities!$A$9:$I$180,7,FALSE)/$AI39 -> 6.143 | DQ39: =VLOOKUP($F39,Activities!$A$9:$I$180,8,FALSE)/$AI39 -> 6.143 | DR39: =VLOOKUP($F39,Activities!$A$9:$I$180,9,FALSE)/$AI39 -> 6.143
A40: IBM01_06 | B40: Industrie | C40: Final | D40: Industry | E40: Basic Metals | F40: Steel production - Basic Metals Industry | G40: Hisarna biomass wCCUS (cryogenic) - Steel Production | H40: [Mton_Steel/y] | I40: 900 | J40: 750 | K40: 600 | L40: 600 | M40: 600 | N40: 600 | O40: 600 | P40: 0 | Q40: 105 | R40: 105 | S40: 90 | T40: 90 | U40: 80 | V40: 80 | W40: 70 | X40: 170 | Y40: 170 | Z40: 170 | AA40: 170 | AB40: 170 | AC40: 170 | AD40: 170 | AE40: 0.08 | AF40: 0 | AG40: 30 | AH40: 30 | AI40: 1 | AJ40: Operation | AK40: Flat | AY40: none | BN40: 0 | BU40: =IF(BL40=1,BN40,0) -> 0 | CB40: 0 | CC40: 4 | CD40: =DN40 -> 6.143 | CE40: =DO40 -> 6.143 | CF40: =DP40 -> 6.143 | CG40: =DQ40 -> 6.143 | CH40: =DR40 -> 6.143 | DK40: [51] | DL40: =VLOOKUP($F40,Activities!$A$9:$I$180,3,FALSE)/$AI40 -> 6.143 | DM40: =VLOOKUP($F40,Activities!$A$9:$I$180,4,FALSE)/$AI40 -> 6.143 | DN40: =VLOOKUP($F40,Activities!$A$9:$I$180,5,FALSE)/$AI40 -> 6.143 | DO40: =VLOOKUP($F40,Activities!$A$9:$I$180,6,FALSE)/$AI40 -> 6.143 | DP40: =VLOOKUP($F40,Activities!$A$9:$I$180,7,FALSE)/$AI40 -> 6.143 | DQ40: =VLOOKUP($F40,Activities!$A$9:$I$180,8,FALSE)/$AI40 -> 6.143 | DR40: =VLOOKUP($F40,Activities!$A$9:$I$180,9,FALSE)/$AI40 -> 6.143
A41: IBM01_07 | B41: Industrie | C41: Final | D41: Industry | E41: Basic Metals | F41: Steel production - Basic Metals Industry | G41: Direct reduction from natural gas - Steel Production | H41: [Mton_Steel/y] | I41: 435 | J41: 435 | K41: 435 | L41: 435 | M41: 435 | N41: 435 | O41: 435 | P41: 0 | Q41: 13 | R41: 13 | S41: 13 | T41: 13 | U41: 13 | V41: 13 | W41: 13 | X41: 170 | Y41: 170 | Z41: 170 | AA41: 170 | AB41: 170 | AC41: 170 | AD41: 170 | AE41: 0.08 | AF41: 0 | AG41: 30 | AH41: 30 | AI41: 1 | AJ41: Operation | AK41: Flat | AY41: none | BN41: 0 | BU41: =IF(BL41=1,BN41,0) -> 0 | CB41: 0 | CC41: 4 | CD41: =DN41 -> 6.143 | CE41: =DO41 -> 6.143 | CF41: =DP41 -> 6.143 | CG41: =DQ41 -> 6.143 | CH41: =DR41 -> 6.143 | DK41: [51] | DL41: =VLOOKUP($F41,Activities!$A$9:$I$180,3,FALSE)/$AI41 -> 6.143 | DM41: =VLOOKUP($F41,Activities!$A$9:$I$180,4,FALSE)/$AI41 -> 6.143 | DN41: =VLOOKUP($F41,Activities!$A$9:$I$180,5,FALSE)/$AI41 -> 6.143 | DO41: =VLOOKUP($F41,Activities!$A$9:$I$180,6,FALSE)/$AI41 -> 6.143 | DP41: =VLOOKUP($F41,Activities!$A$9:$I$180,7,FALSE)/$AI41 -> 6.143 | DQ41: =VLOOKUP($F41,Activities!$A$9:$I$180,8,FALSE)/$AI41 -> 6.143 | DR41: =VLOOKUP($F41,Activities!$A$9:$I$180,9,FALSE)/$AI41 -> 6.143
A42: IBM01_08 | B42: Industrie | C42: Final | D42: Industry | E42: Basic Metals | F42: Steel production - Basic Metals Industry | G42: Direct reduction from hydrogen - Steel Production | H42: [Mton_Steel/y] | I42: 435 | J42: 435 | K42: 435 | L42: 435 | M42: 435 | N42: 435 | O42: 435 | P42: 0 | Q42: 13 | R42: 13 | S42: 13 | T42: 13 | U42: 13 | V42: 13 | W42: 13 | X42: 170 | Y42: 170 | Z42: 170 | AA42: 170 | AB42: 170 | AC42: 170 | AD42: 170 | AE42: 0.08 | AF42: 0 | AG42: 30 | AH42: 30 | AI42: 1 | AJ42: Operation | AK42: Flat | AY42: none | BN42: 0 | BU42: =IF(BL42=1,BN42,0) -> 0 | CB42: 0 | CD42: =DN42 -> 6.143 | CE42: =DO42 -> 6.143 | CF42: =DP42 -> 6.143 | CG42: =DQ42 -> 6.143 | CH42: =DR42 -> 6.143 | DK42: [51] | DL42: =VLOOKUP($F42,Activities!$A$9:$I$180,3,FALSE)/$AI42 -> 6.143 | DM42: =VLOOKUP($F42,Activities!$A$9:$I$180,4,FALSE)/$AI42 -> 6.143 | DN42: =VLOOKUP($F42,Activities!$A$9:$I$180,5,FALSE)/$AI42 -> 6.143 | DO42: =VLOOKUP($F42,Activities!$A$9:$I$180,6,FALSE)/$AI42 -> 6.143 | DP42: =VLOOKUP($F42,Activities!$A$9:$I$180,7,FALSE)/$AI42 -> 6.143 | DQ42: =VLOOKUP($F42,Activities!$A$9:$I$180,8,FALSE)/$AI42 -> 6.143 | DR42: =VLOOKUP($F42,Activities!$A$9:$I$180,9,FALSE)/$AI42 -> 6.143
A43: IBM01_09 | B43: Industrie | C43: Final | D43: Industry | E43: Basic Metals | F43: Steel production - Basic Metals Industry | G43: Direct reduction from hydrogen w/biomass - Steel Production | H43: [Mton_Steel/y] | I43: 435 | J43: 435 | K43: 435 | L43: 435 | M43: 435 | N43: 435 | O43: 435 | P43: 0 | Q43: 13 | R43: 13 | S43: 13 | T43: 13 | U43: 13 | V43: 13 | W43: 13 | X43: 170 | Y43: 170 | Z43: 170 | AA43: 170 | AB43: 170 | AC43: 170 | AD43: 170 | AE43: 0.08 | AF43: 0 | AG43: 30 | AH43: 30 | AI43: 1 | AJ43: Operation | AK43: Flat | AY43: none | BN43: 0 | BU43: =IF(BL43=1,BN43,0) -> 0 | CB43: 0 | CD43: =DN43 -> 6.143 | CE43: =DO43 -> 6.143 | CF43: =DP43 -> 6.143 | CG43: =DQ43 -> 6.143 | CH43: =DR43 -> 6.143 | DK43: [51] | DL43: =VLOOKUP($F43,Activities!$A$9:$I$180,3,FALSE)/$AI43 -> 6.143 | DM43: =VLOOKUP($F43,Activities!$A$9:$I$180,4,FALSE)/$AI43 -> 6.143 | DN43: =VLOOKUP($F43,Activities!$A$9:$I$180,5,FALSE)/$AI43 -> 6.143 | DO43: =VLOOKUP($F43,Activities!$A$9:$I$180,6,FALSE)/$AI43 -> 6.143 | DP43: =VLOOKUP($F43,Activities!$A$9:$I$180,7,FALSE)/$AI43 -> 6.143 | DQ43: =VLOOKUP($F43,Activities!$A$9:$I$180,8,FALSE)/$AI43 -> 6.143 | DR43: =VLOOKUP($F43,Activities!$A$9:$I$180,9,FALSE)/$AI43 -> 6.143
A44: IBM01_10 | B44: Industrie | C44: Final | D44: Industry | E44: Basic Metals | F44: Steel production - Basic Metals Industry | G44: Low temperature electro winning (ULCOWIN) - Steel Production | H44: [Mton_Steel/y] | I44: 1000 | J44: 950 | K44: 900 | L44: 835 | M44: 770 | N44: 705 | O44: 640 | P44: 0 | Q44: 70 | R44: 70 | S44: 60 | T44: 60 | U44: 53 | V44: 53 | W44: 45 | X44: 170 | Y44: 170 | Z44: 170 | AA44: 170 | AB44: 170 | AC44: 170 | AD44: 170 | AE44: 0.08 | AF44: 0 | AG44: 30 | AH44: 30 | AI44: 1 | AJ44: Shedding | AK44: Flat | AS44: 0.5 | AU44: 1 hour [h] | AY44: none | BN44: 0 | BU44: =IF(BL44=1,BN44,0) -> 0 | CE44: 4 | CF44: =DP44 -> 6.143 | CG44: =DQ44 -> 6.143 | CH44: =DR44 -> 6.143 | DK44: [51] | DL44: =VLOOKUP($F44,Activities!$A$9:$I$180,3,FALSE)/$AI44 -> 6.143 | DM44: =VLOOKUP($F44,Activities!$A$9:$I$180,4,FALSE)/$AI44 -> 6.143 | DN44: =VLOOKUP($F44,Activities!$A$9:$I$180,5,FALSE)/$AI44 -> 6.143 | DO44: =VLOOKUP($F44,Activities!$A$9:$I$180,6,FALSE)/$AI44 -> 6.143 | DP44: =VLOOKUP($F44,Activities!$A$9:$I$180,7,FALSE)/$AI44 -> 6.143 | DQ44: =VLOOKUP($F44,Activities!$A$9:$I$180,8,FALSE)/$AI44 -> 6.143 | DR44: =VLOOKUP($F44,Activities!$A$9:$I$180,9,FALSE)/$AI44 -> 6.143
A45: IBM01_11 | B45: Industrie | C45: Final | D45: Industry | E45: Basic Metals | F45: Steel production - Basic Metals Industry | G45: High temperature electro winning - Steel Production | H45: [Mton_Steel/y] | I45: 1100 | J45: 980 | K45: 950 | L45: 890 | M45: 830 | N45: 770 | O45: 710 | P45: 0 | Q45: 85 | R45: 85 | S45: 75 | T45: 75 | U45: 66 | V45: 66 | W45: 58 | X45: 170 | Y45: 170 | Z45: 170 | AA45: 170 | AB45: 170 | AC45: 170 | AD45: 170 | AE45: 0.08 | AF45: 0 | AG45: 30 | AH45: 30 | AI45: 1 | AJ45: Shedding | AK45: Flat | AS45: 0.5 | AU45: 1 hour [h] | AY45: none | BN45: 0 | BU45: =IF(BL45=1,BN45,0) -> 0 | CE45: 4 | CF45: =DP45 -> 6.143 | CG45: =DQ45 -> 6.143 | CH45: =DR45 -> 6.143 | DK45: [51] | DL45: =VLOOKUP($F45,Activities!$A$9:$I$180,3,FALSE)/$AI45 -> 6.143 | DM45: =VLOOKUP($F45,Activities!$A$9:$I$180,4,FALSE)/$AI45 -> 6.143 | DN45: =VLOOKUP($F45,Activities!$A$9:$I$180,5,FALSE)/$AI45 -> 6.143 | DO45: =VLOOKUP($F45,Activities!$A$9:$I$180,6,FALSE)/$AI45 -> 6.143 | DP45: =VLOOKUP($F45,Activities!$A$9:$I$180,7,FALSE)/$AI45 -> 6.143 | DQ45: =VLOOKUP($F45,Activities!$A$9:$I$180,8,FALSE)/$AI45 -> 6.143 | DR45: =VLOOKUP($F45,Activities!$A$9:$I$180,9,FALSE)/$AI45 -> 6.143
A46: IBM01_12 | B46: Industrie | C46: Final | D46: Industry | E46: Basic Metals | F46: Steel production - Basic Metals Industry | G46: Scrap-fed EAF - Steel Production | H46: [Mton_Steel/y] | I46: =455*(103.88/100) -> 472.654 | J46: =455*(103.88/100) -> 472.654 | K46: =455*(103.88/100) -> 472.654 | L46: =455*(103.88/100) -> 472.654 | M46: =455*(103.88/100) -> 472.654 | N46: =455*(103.88/100) -> 472.654 | O46: =455*(103.88/100) -> 472.654 | P46: 0 | Q46: =39*(103.88/100) -> 40.5132 | R46: =39*(103.88/100) -> 40.5132 | S46: =39*(103.88/100) -> 40.5132 | T46: =39*(103.88/100) -> 40.5132 | U46: =39*(103.88/100) -> 40.5132 | V46: =39*(103.88/100) -> 40.5132 | W46: =39*(103.88/100) -> 40.5132 | X46: =X35*1.2 -> 204 | Y46: =Y35*1.2 -> 204 | Z46: =Z35*1.2 -> 204 | AA46: =AA35*1.2 -> 204 | AB46: =AB35*1.2 -> 204 | AC46: =AC35*1.2 -> 204 | AD46: =AD35*1.2 -> 204 | AE46: 0.08 | AF46: 0 | AG46: 20 | AH46: 20 | AI46: 1 | AJ46: Operation | AK46: Flat | AY46: none | BN46: 0 | CC46: 4 | CD46: =DN46 -> 6.143 | CE46: =DO46 -> 6.143 | CF46: =DP46 -> 6.143 | CG46: =DQ46 -> 6.143 | CH46: =DR46 -> 6.143 | DL46: =VLOOKUP($F46,Activities!$A$9:$I$180,3,FALSE)/$AI46 -> 6.143 | DM46: =VLOOKUP($F46,Activities!$A$9:$I$180,4,FALSE)/$AI46 -> 6.143 | DN46: =VLOOKUP($F46,Activities!$A$9:$I$180,5,FALSE)/$AI46 -> 6.143 | DO46: =VLOOKUP($F46,Activities!$A$9:$I$180,6,FALSE)/$AI46 -> 6.143 | DP46: =VLOOKUP($F46,Activities!$A$9:$I$180,7,FALSE)/$AI46 -> 6.143 | DQ46: =VLOOKUP($F46,Activities!$A$9:$I$180,8,FALSE)/$AI46 -> 6.143 | DR46: =VLOOKUP($F46,Activities!$A$9:$I$180,9,FALSE)/$AI46 -> 6.143
A47: IBM01_13 | B47: Industrie | C47: Final | D47: Industry | E47: Basic Metals | F47: Steel production - Basic Metals Industry | G47: Scrap-fed EAF with syngas fuel - Steel Production | H47: [Mton_Steel/y] | I47: =455*(103.88/100) -> 472.654 | J47: =455*(103.88/100) -> 472.654 | K47: =455*(103.88/100) -> 472.654 | L47: =455*(103.88/100) -> 472.654 | M47: =455*(103.88/100) -> 472.654 | N47: =455*(103.88/100) -> 472.654 | O47: =455*(103.88/100) -> 472.654 | P47: 0 | Q47: =39*(103.88/100) -> 40.5132 | R47: =39*(103.88/100) -> 40.5132 | S47: =39*(103.88/100) -> 40.5132 | T47: =39*(103.88/100) -> 40.5132 | U47: =39*(103.88/100) -> 40.5132 | V47: =39*(103.88/100) -> 40.5132 | W47: =39*(103.88/100) -> 40.5132 | X47: =X36*1.2 -> 204 | Y47: =Y36*1.2 -> 204 | Z47: =Z36*1.2 -> 204 | AA47: =AA36*1.2 -> 204 | AB47: =AB36*1.2 -> 204 | AC47: =AC36*1.2 -> 204 | AD47: =AD36*1.2 -> 204 | AE47: 0.08 | AF47: 0 | AG47: 20 | AH47: 20 | AI47: 1 | AJ47: Operation | AK47: Flat | AY47: none | BN47: 0 | CC47: 4 | CD47: =DN47 -> 6.143 | CE47: =DO47 -> 6.143 | CF47: =DP47 -> 6.143 | CG47: =DQ47 -> 6.143 | CH47: =DR47 -> 6.143 | DL47: =VLOOKUP($F47,Activities!$A$9:$I$180,3,FALSE)/$AI47 -> 6.143 | DM47: =VLOOKUP($F47,Activities!$A$9:$I$180,4,FALSE)/$AI47 -> 6.143 | DN47: =VLOOKUP($F47,Activities!$A$9:$I$180,5,FALSE)/$AI47 -> 6.143 | DO47: =VLOOKUP($F47,Activities!$A$9:$I$180,6,FALSE)/$AI47 -> 6.143 | DP47: =VLOOKUP($F47,Activities!$A$9:$I$180,7,FALSE)/$AI47 -> 6.143 | DQ47: =VLOOKUP($F47,Activities!$A$9:$I$180,8,FALSE)/$AI47 -> 6.143 | DR47: =VLOOKUP($F47,Activities!$A$9:$I$180,9,FALSE)/$AI47 -> 6.143
A48: IBM01_15 | B48: Industrie | C48: Final | D48: Industry | E48: Basic Metals | F48: Steel production - Basic Metals Industry | G48: DRI-fed EAF - Steel Production | H48: [Mton_Steel/y] | I48: =455*(103.88/100) -> 472.654 | J48: =455*(103.88/100) -> 472.654 | K48: =455*(103.88/100) -> 472.654 | L48: =455*(103.88/100) -> 472.654 | M48: =455*(103.88/100) -> 472.654 | N48: =455*(103.88/100) -> 472.654 | O48: =455*(103.88/100) -> 472.654 | P48: 0 | Q48: =39*(103.88/100) -> 40.5132 | R48: =39*(103.88/100) -> 40.5132 | S48: =39*(103.88/100) -> 40.5132 | T48: =39*(103.88/100) -> 40.5132 | U48: =39*(103.88/100) -> 40.5132 | V48: =39*(103.88/100) -> 40.5132 | W48: =39*(103.88/100) -> 40.5132 | X48: =X38*1.2 -> 204 | Y48: =Y38*1.2 -> 204 | Z48: =Z38*1.2 -> 204 | AA48: =AA38*1.2 -> 204 | AB48: =AB38*1.2 -> 204 | AC48: =AC38*1.2 -> 204 | AD48: =AD38*1.2 -> 204 | AE48: 0.08 | AF48: 0 | AG48: 20 | AH48: 20 | AI48: 1 | AJ48: Operation | AK48: Flat | AY48: none | BN48: 0 | CC48: 4 | CD48: =DN48 -> 6.143 | CE48: =DO48 -> 6.143 | CF48: =DP48 -> 6.143 | CG48: =DQ48 -> 6.143 | CH48: =DR48 -> 6.143 | DL48: =VLOOKUP($F48,Activities!$A$9:$I$180,3,FALSE)/$AI48 -> 6.143 | DM48: =VLOOKUP($F48,Activities!$A$9:$I$180,4,FALSE)/$AI48 -> 6.143 | DN48: =VLOOKUP($F48,Activities!$A$9:$I$180,5,FALSE)/$AI48 -> 6.143 | DO48: =VLOOKUP($F48,Activities!$A$9:$I$180,6,FALSE)/$AI48 -> 6.143 | DP48: =VLOOKUP($F48,Activities!$A$9:$I$180,7,FALSE)/$AI48 -> 6.143 | DQ48: =VLOOKUP($F48,Activities!$A$9:$I$180,8,FALSE)/$AI48 -> 6.143 | DR48: =VLOOKUP($F48,Activities!$A$9:$I$180,9,FALSE)/$AI48 -> 6.143
A49: IBM01_16 | B49: Industrie | C49: Final | D49: Industry | E49: Basic Metals | F49: Steel production - Basic Metals Industry | G49: DRI-fed EAF with syngas fuel - Steel Production | H49: [Mton_Steel/y] | I49: =455*(103.88/100) -> 472.654 | J49: =455*(103.88/100) -> 472.654 | K49: =455*(103.88/100) -> 472.654 | L49: =455*(103.88/100) -> 472.654 | M49: =455*(103.88/100) -> 472.654 | N49: =455*(103.88/100) -> 472.654 | O49: =455*(103.88/100) -> 472.654 | P49: 0 | Q49: =39*(103.88/100) -> 40.5132 | R49: =39*(103.88/100) -> 40.5132 | S49: =39*(103.88/100) -> 40.5132 | T49: =39*(103.88/100) -> 40.5132 | U49: =39*(103.88/100) -> 40.5132 | V49: =39*(103.88/100) -> 40.5132 | W49: =39*(103.88/100) -> 40.5132 | X49: =X39*1.2 -> 204 | Y49: =Y39*1.2 -> 204 | Z49: =Z39*1.2 -> 204 | AA49: =AA39*1.2 -> 204 | AB49: =AB39*1.2 -> 204 | AC49: =AC39*1.2 -> 204 | AD49: =AD39*1.2 -> 204 | AE49: 0.08 | AF49: 0 | AG49: 20 | AH49: 20 | AI49: 1 | AJ49: Operation | AK49: Flat | AY49: none | BN49: 0 | CC49: 4 | CD49: =DN49 -> 6.143 | CE49: =DO49 -> 6.143 | CF49: =DP49 -> 6.143 | CG49: =DQ49 -> 6.143 | CH49: =DR49 -> 6.143 | DL49: =VLOOKUP($F49,Activities!$A$9:$I$180,3,FALSE)/$AI49 -> 6.143 | DM49: =VLOOKUP($F49,Activities!$A$9:$I$180,4,FALSE)/$AI49 -> 6.143 | DN49: =VLOOKUP($F49,Activities!$A$9:$I$180,5,FALSE)/$AI49 -> 6.143 | DO49: =VLOOKUP($F49,Activities!$A$9:$I$180,6,FALSE)/$AI49 -> 6.143 | DP49: =VLOOKUP($F49,Activities!$A$9:$I$180,7,FALSE)/$AI49 -> 6.143 | DQ49: =VLOOKUP($F49,Activities!$A$9:$I$180,8,FALSE)/$AI49 -> 6.143 | DR49: =VLOOKUP($F49,Activities!$A$9:$I$180,9,FALSE)/$AI49 -> 6.143
A50: IBM01_17 | B50: Industrie | C50: Final | D50: Industry | E50: Basic Metals | F50: Steel production - Basic Metals Industry | G50: DRI-fed EAF with syngas fuel and biomass reducing agent - Steel Production | H50: [Mton_Steel/y] | I50: =455*(103.88/100) -> 472.654 | J50: =455*(103.88/100) -> 472.654 | K50: =455*(103.88/100) -> 472.654 | L50: =455*(103.88/100) -> 472.654 | M50: =455*(103.88/100) -> 472.654 | N50: =455*(103.88/100) -> 472.654 | O50: =455*(103.88/100) -> 472.654 | P50: 0 | Q50: =39*(103.88/100) -> 40.5132 | R50: =39*(103.88/100) -> 40.5132 | S50: =39*(103.88/100) -> 40.5132 | T50: =39*(103.88/100) -> 40.5132 | U50: =39*(103.88/100) -> 40.5132 | V50: =39*(103.88/100) -> 40.5132 | W50: =39*(103.88/100) -> 40.5132 | X50: =X40*1.2 -> 204 | Y50: =Y40*1.2 -> 204 | Z50: =Z40*1.2 -> 204 | AA50: =AA40*1.2 -> 204 | AB50: =AB40*1.2 -> 204 | AC50: =AC40*1.2 -> 204 | AD50: =AD40*1.2 -> 204 | AE50: 0.08 | AF50: 0 | AG50: 20 | AH50: 20 | AI50: 1 | AJ50: Operation | AK50: Flat | AY50: none | BN50: 0 | CC50: 4 | CD50: =DN50 -> 6.143 | CE50: =DO50 -> 6.143 | CF50: =DP50 -> 6.143 | CG50: =DQ50 -> 6.143 | CH50: =DR50 -> 6.143 | DL50: =VLOOKUP($F50,Activities!$A$9:$I$180,3,FALSE)/$AI50 -> 6.143 | DM50: =VLOOKUP($F50,Activities!$A$9:$I$180,4,FALSE)/$AI50 -> 6.143 | DN50: =VLOOKUP($F50,Activities!$A$9:$I$180,5,FALSE)/$AI50 -> 6.143 | DO50: =VLOOKUP($F50,Activities!$A$9:$I$180,6,FALSE)/$AI50 -> 6.143 | DP50: =VLOOKUP($F50,Activities!$A$9:$I$180,7,FALSE)/$AI50 -> 6.143 | DQ50: =VLOOKUP($F50,Activities!$A$9:$I$180,8,FALSE)/$AI50 -> 6.143 | DR50: =VLOOKUP($F50,Activities!$A$9:$I$180,9,FALSE)/$AI50 -> 6.143
A51: IFE01_01 | B51: Industrie | C51: Final | D51: Industry | E51: Fertilizers | F51: Nitric Acid production - Fertilizers Industry | G51: Nitric Acid production from Ammonia -Fertilizers | H51: [Mton_AN] | I51: 130 | J51: 130 | K51: 130 | L51: 130 | M51: 130 | N51: 130 | O51: 130 | P51: 0 | Q51: 3.9 | R51: 3.9 | S51: 3.9 | T51: 3.9 | U51: 3.9 | V51: 3.9 | W51: 3.9 | X51: 0 | Y51: 0 | Z51: 0 | AA51: 0 | AB51: 0 | AC51: 0 | AD51: 0 | AE51: 0.08 | AF51: 0 | AG51: 30 | AH51: 30 | AI51: 1 | AJ51: Operation | AK51: Flat | AY51: none | BN51: =CB51 -> 2.4 | BO51: =$BN$51/4 -> 0.6 | BP51: =$BN$51/4 -> 0.6 | BQ51: =$BN$51/4 -> 0.6 | BR51: =$BN$51/4 -> 0.6 | BU51: =IF(BL51=1,BN51,0) -> 0 | CB51: =DL51 -> 2.4 | CC51: =DM51 -> 2.4 | CD51: =DN51 -> 2.4 | CE51: =DO51 -> 2.4 | CF51: =DP51 -> 2.4 | CG51: =DQ51 -> 2.4 | CH51: =DR51 -> 2.4 | DK51: [54],[36] | DL51: =VLOOKUP($F51,Activities!$A$9:$I$180,3,FALSE)/$AI51 -> 2.4 | DM51: =VLOOKUP($F51,Activities!$A$9:$I$180,4,FALSE)/$AI51 -> 2.4 | DN51: =VLOOKUP($F51,Activities!$A$9:$I$180,5,FALSE)/$AI51 -> 2.4 | DO51: =VLOOKUP($F51,Activities!$A$9:$I$180,6,FALSE)/$AI51 -> 2.4 | DP51: =VLOOKUP($F51,Activities!$A$9:$I$180,7,FALSE)/$AI51 -> 2.4 | DQ51: =VLOOKUP($F51,Activities!$A$9:$I$180,8,FALSE)/$AI51 -> 2.4 | DR51: =VLOOKUP($F51,Activities!$A$9:$I$180,9,FALSE)/$AI51 -> 2.4
A52: IFE02_02 | B52: Industrie | C52: Final | D52: Industry | E52: Fertilizers | F52: Urea production - Fertilizers Industry | G52: Urea production from Ammonia and CCUS - Fertilizers | H52: [Mton_Urea] | I52: 185 | J52: 185 | K52: 185 | L52: 185 | M52: 185 | N52: 185 | O52: 185 | P52: 0 | Q52: 6 | R52: 6 | S52: 6 | T52: 6 | U52: 6 | V52: 6 | W52: 6 | X52: 0 | Y52: 0 | Z52: 0 | AA52: 0 | AB52: 0 | AC52: 0 | AD52: 0 | AE52: 0.08 | AF52: 0 | AG52: 30 | AH52: 30 | AI52: 1 | AJ52: Operation | AK52: Flat | AY52: none | BN52: 0 | BU52: =IF(BL52=1,BN52,0) -> 0 | CB52: =DL52 -> 1.8 | CC52: =DM52 -> 1.8 | CD52: =DN52 -> 1.8 | CE52: =DO52 -> 1.8 | CF52: =DP52 -> 1.8 | CG52: =DQ52 -> 1.8 | CH52: =DR52 -> 1.8 | DK52: [54],[36] | DL52: =VLOOKUP($F52,Activities!$A$9:$I$180,3,FALSE)/$AI52 -> 1.8 | DM52: =VLOOKUP($F52,Activities!$A$9:$I$180,4,FALSE)/$AI52 -> 1.8 | DN52: =VLOOKUP($F52,Activities!$A$9:$I$180,5,FALSE)/$AI52 -> 1.8 | DO52: =VLOOKUP($F52,Activities!$A$9:$I$180,6,FALSE)/$AI52 -> 1.8 | DP52: =VLOOKUP($F52,Activities!$A$9:$I$180,7,FALSE)/$AI52 -> 1.8 | DQ52: =VLOOKUP($F52,Activities!$A$9:$I$180,8,FALSE)/$AI52 -> 1.8 | DR52: =VLOOKUP($F52,Activities!$A$9:$I$180,9,FALSE)/$AI52 -> 1.8
A53: IFE03_01 | B53: Industrie | C53: Final | D53: Industry | E53: Fertilizers | F53: Other Ammonia based fertilizers - Fertilizers Industry | G53: Ammonia demand for other fertilizers - Fertilizers | H53: [Mton_NH3] | I53: 0 | J53: 0 | K53: 0 | L53: 0 | M53: 0 | N53: 0 | O53: 0 | P53: 0 | Q53: 0 | R53: 0 | S53: 0 | T53: 0 | U53: 0 | V53: 0 | W53: 0 | X53: 0 | Y53: 0 | Z53: 0 | AA53: 0 | AB53: 0 | AC53: 0 | AD53: 0 | AE53: 0.08 | AF53: 0 | AG53: 1 | AH53: 1 | AI53: 1 | AJ53: Operation | AK53: Flat | AY53: none | BN53: =CB53 -> 1.2 | BU53: =IF(BL53=1,BN53,0) -> 0 | CB53: =DL53 -> 1.2 | CC53: =DM53 -> 1.2 | CD53: =DN53 -> 1.2 | CE53: =DO53 -> 1.2 | CF53: =DP53 -> 1.2 | CG53: =DQ53 -> 1.2 | CH53: =DR53 -> 1.2 | DK53: [54],[36] | DL53: =VLOOKUP($F53,Activities!$A$9:$I$180,3,FALSE)/$AI53 -> 1.2 | DM53: =VLOOKUP($F53,Activities!$A$9:$I$180,4,FALSE)/$AI53 -> 1.2 | DN53: =VLOOKUP($F53,Activities!$A$9:$I$180,5,FALSE)/$AI53 -> 1.2 | DO53: =VLOOKUP($F53,Activities!$A$9:$I$180,6,FALSE)/$AI53 -> 1.2 | DP53: =VLOOKUP($F53,Activities!$A$9:$I$180,7,FALSE)/$AI53 -> 1.2 | DQ53: =VLOOKUP($F53,Activities!$A$9:$I$180,8,FALSE)/$AI53 -> 1.2 | DR53: =VLOOKUP($F53,Activities!$A$9:$I$180,9,FALSE)/$AI53 -> 1.2
A54: ICH01_01 | B54: Industrie | C54: Conversion | D54: Industry | E54: Chemicals | F54: Ethylene intermediate | G54: Existing naphtha steam cracker - Petrochemical industry | H54: [Mton_Ey/y] | I54: 1939.543 | J54: 1939.543 | K54: 1939.543 | L54: 1939.543 | M54: 1939.543 | N54: 1939.543 | O54: 1939.543 | P54: 0 | Q54: 77.581721 | R54: 77.581721 | S54: 77.581721 | T54: 77.581721 | U54: 77.581721 | V54: 77.581721 | W54: 77.581721 | X54: 0 | Y54: 0 | Z54: 0 | AA54: 0 | AB54: 0 | AC54: 0 | AD54: 0 | AE54: 0.08 | AF54: 0 | AG54: 25 | AH54: 25 | AI54: 1 | AJ54: Operation | AK54: Flat | AY54: none | BN54: 4 | BQ54: 1.3 | BR54: 1.3 | BS54: 1.28 | BU54: =IF(BL54=1,BN54,0) -> 0 | CB54: 10 | CC54: 4 | CD54: 4 | CE54: 4 | CF54: 4 | CG54: 4 | CH54: 4 | CZ54: 1 | DA54: 1 | DB54: 1 | DC54: 1 | DK54: [103] | DL54: =VLOOKUP($F54,Activities!$A$9:$I$180,3,FALSE)/$AI54 -> 0 | DM54: =VLOOKUP($F54,Activities!$A$9:$I$180,4,FALSE)/$AI54 -> 0 | DN54: =VLOOKUP($F54,Activities!$A$9:$I$180,5,FALSE)/$AI54 -> 0 | DO54: =VLOOKUP($F54,Activities!$A$9:$I$180,6,FALSE)/$AI54 -> 0 | DP54: =VLOOKUP($F54,Activities!$A$9:$I$180,7,FALSE)/$AI54 -> 0 | DQ54: =VLOOKUP($F54,Activities!$A$9:$I$180,8,FALSE)/$AI54 -> 0 | DR54: =VLOOKUP($F54,Activities!$A$9:$I$180,9,FALSE)/$AI54 -> 0
A55: ICH01_02 | B55: Industrie | C55: Conversion | D55: Industry | E55: Chemicals | F55: Ethylene intermediate | G55: Existing naphtha steam cracker wCCUS (MEA postcombustion) - Petrochemical industry | H55: [Mton_Ey/y] | I55: 2160.0087 | J55: 2160.0087 | K55: 2160.0087 | L55: 2160.0087 | M55: 2160.0087 | N55: 2160.0087 | O55: 2160.0087 | P55: 0 | Q55: 86.400348 | R55: 86.400348 | S55: 86.400348 | T55: 86.400348 | U55: 86.400348 | V55: 86.400348 | W55: 86.400348 | X55: 0 | Y55: 0 | Z55: 0 | AA55: 0 | AB55: 0 | AC55: 0 | AD55: 0 | AE55: 0.08 | AF55: 0 | AG55: 25 | AH55: 25 | AI55: 1 | AJ55: Operation | AK55: Flat | AY55: none | BN55: 0 | BU55: =IF(BL55=1,BN55,0) -> 0 | CC55: 2 | CD55: 4 | CE55: =CE54 -> 4 | CF55: =CF54 -> 4 | CG55: =CG54 -> 4 | CH55: =CH54 -> 4 | DK55: [103] | DL55: =VLOOKUP($F55,Activities!$A$9:$I$180,3,FALSE)/$AI55 -> 0 | DM55: =VLOOKUP($F55,Activities!$A$9:$I$180,4,FALSE)/$AI55 -> 0 | DN55: =VLOOKUP($F55,Activities!$A$9:$I$180,5,FALSE)/$AI55 -> 0 | DO55: =VLOOKUP($F55,Activities!$A$9:$I$180,6,FALSE)/$AI55 -> 0 | DP55: =VLOOKUP($F55,Activities!$A$9:$I$180,7,FALSE)/$AI55 -> 0 | DQ55: =VLOOKUP($F55,Activities!$A$9:$I$180,8,FALSE)/$AI55 -> 0 | DR55: =VLOOKUP($F55,Activities!$A$9:$I$180,9,FALSE)/$AI55 -> 0
A56: ICH01_03 | B56: Industrie | C56: Conversion | D56: Industry | E56: Chemicals | F56: Ethylene intermediate | G56: Existing bio-naphtha steam cracker wCCUS (MEA postcombustion) - Petrochemical industry | H56: [Mton_Ey/y] | I56: 2181.6088 | J56: 2181.6088 | K56: 2181.6088 | L56: 2181.6088 | M56: 2181.6088 | N56: 2181.6088 | O56: 2181.6088 | P56: 0 | Q56: =Q55*1.01 -> 87.264352 | R56: =R55*1.01 -> 87.264352 | S56: =S55*1.01 -> 87.264352 | T56: =T55*1.01 -> 87.264352 | U56: =U55*1.01 -> 87.264352 | V56: =V55*1.01 -> 87.264352 | W56: =W55*1.01 -> 87.264352 | X56: 0 | Y56: 0 | Z56: 0 | AA56: 0 | AB56: 0 | AC56: 0 | AD56: 0 | AE56: 0.08 | AF56: 0 | AG56: 25 | AH56: 25 | AI56: 1 | AJ56: Operation | AK56: Flat | AY56: none | BN56: 0 | BU56: =IF(BL56=1,BN56,0) -> 0 | CC56: 2 | CD56: 4 | CE56: 4 | CF56: 4 | CG56: 4 | CH56: 4 | DK56: [103] | DL56: =VLOOKUP($F56,Activities!$A$9:$I$180,3,FALSE)/$AI56 -> 0 | DM56: =VLOOKUP($F56,Activities!$A$9:$I$180,4,FALSE)/$AI56 -> 0 | DN56: =VLOOKUP($F56,Activities!$A$9:$I$180,5,FALSE)/$AI56 -> 0 | DO56: =VLOOKUP($F56,Activities!$A$9:$I$180,6,FALSE)/$AI56 -> 0 | DP56: =VLOOKUP($F56,Activities!$A$9:$I$180,7,FALSE)/$AI56 -> 0 | DQ56: =VLOOKUP($F56,Activities!$A$9:$I$180,8,FALSE)/$AI56 -> 0 | DR56: =VLOOKUP($F56,Activities!$A$9:$I$180,9,FALSE)/$AI56 -> 0
A57: ICH01_04 | B57: Industrie | C57: Conversion | D57: Industry | E57: Chemicals | F57: Ethylene intermediate | G57: Existing syn-naphtha steam cracker wCCUS (MEA postcombustion) - Petrochemical industry | H57: [Mton_Ey/y] | I57: 2160.0087 | J57: 2160.0087 | K57: 2160.0087 | L57: 2160.0087 | M57: 2160.0087 | N57: 2160.0087 | O57: 2160.0087 | P57: 0 | Q57: =Q55 -> 86.400348 | R57: =R55 -> 86.400348 | S57: =S55 -> 86.400348 | T57: =T55 -> 86.400348 | U57: =U55 -> 86.400348 | V57: =V55 -> 86.400348 | W57: =W55 -> 86.400348 | X57: 0 | Y57: 0 | Z57: 0 | AA57: 0 | AB57: 0 | AC57: 0 | AD57: 0 | AE57: 0.08 | AF57: 0 | AG57: 25 | AH57: 25 | AI57: 1 | AJ57: Operation | AK57: Flat | AY57: none | BN57: 0 | BU57: =IF(BL57=1,BN57,0) -> 0 | CC57: 2 | CD57: 4 | CE57: 4 | CF57: 4 | CG57: 4 | CH57: 4 | DK57: [103] | DL57: =VLOOKUP($F57,Activities!$A$9:$I$180,3,FALSE)/$AI57 -> 0 | DM57: =VLOOKUP($F57,Activities!$A$9:$I$180,4,FALSE)/$AI57 -> 0 | DN57: =VLOOKUP($F57,Activities!$A$9:$I$180,5,FALSE)/$AI57 -> 0 | DO57: =VLOOKUP($F57,Activities!$A$9:$I$180,6,FALSE)/$AI57 -> 0 | DP57: =VLOOKUP($F57,Activities!$A$9:$I$180,7,FALSE)/$AI57 -> 0 | DQ57: =VLOOKUP($F57,Activities!$A$9:$I$180,8,FALSE)/$AI57 -> 0 | DR57: =VLOOKUP($F57,Activities!$A$9:$I$180,9,FALSE)/$AI57 -> 0
A58: ICH01_05 | B58: Industrie | C58: Conversion | D58: Industry | E58: Chemicals | F58: Ethylene intermediate | G58: Electrified naphtha steam cracker - Petrochemical industry | H58: [Mton_Ey/y] | I58: 1939.543 | J58: 1939.543 | K58: 1939.543 | L58: 1939.543 | M58: 1939.543 | N58: 1939.543 | O58: 1939.543 | P58: 0 | Q58: =Q54 -> 77.581721 | R58: =R54 -> 77.581721 | S58: =S54 -> 77.581721 | T58: =T54 -> 77.581721 | U58: =U54 -> 77.581721 | V58: =V54 -> 77.581721 | W58: =W54 -> 77.581721 | X58: 0 | Y58: 0 | Z58: 0 | AA58: 0 | AB58: 0 | AC58: 0 | AD58: 0 | AE58: 0.08 | AF58: 0 | AG58: 25 | AH58: 25 | AI58: 1 | AJ58: Operation | AK58: Flat | AY58: none | BN58: 0 | BU58: 0 | CB58: 0 | CC58: 0.1 | CD58: 2 | CE58: 4 | CF58: 4 | CG58: 4 | DK58: [103] | DL58: =VLOOKUP($F58,Activities!$A$9:$I$180,3,FALSE)/$AI58 -> 0 | DM58: =VLOOKUP($F58,Activities!$A$9:$I$180,4,FALSE)/$AI58 -> 0 | DN58: =VLOOKUP($F58,Activities!$A$9:$I$180,5,FALSE)/$AI58 -> 0 | DO58: =VLOOKUP($F58,Activities!$A$9:$I$180,6,FALSE)/$AI58 -> 0 | DP58: =VLOOKUP($F58,Activities!$A$9:$I$180,7,FALSE)/$AI58 -> 0 | DQ58: =VLOOKUP($F58,Activities!$A$9:$I$180,8,FALSE)/$AI58 -> 0 | DR58: =VLOOKUP($F58,Activities!$A$9:$I$180,9,FALSE)/$AI58 -> 0
A59: ICH01_06 | B59: Industrie | C59: Conversion | D59: Industry | E59: Chemicals | F59: Ethylene intermediate | G59: Electrified bio-naphtha steam cracker - Petrochemical industry | H59: [Mton_Ey/y] | I59: =I58*1.01 -> 1958.9385 | J59: =J58*1.01 -> 1958.9385 | K59: =K58*1.01 -> 1958.9385 | L59: =L58*1.01 -> 1958.9385 | M59: =M58*1.01 -> 1958.9385 | N59: =N58*1.01 -> 1958.9385 | O59: =O58*1.01 -> 1958.9385 | P59: 0 | Q59: =Q54*1.01 -> 78.357538 | R59: =R54*1.01 -> 78.357538 | S59: =S54*1.01 -> 78.357538 | T59: =T54*1.01 -> 78.357538 | U59: =U54*1.01 -> 78.357538 | V59: =V54*1.01 -> 78.357538 | W59: =W54*1.01 -> 78.357538 | X59: 0 | Y59: 0 | Z59: 0 | AA59: 0 | AB59: 0 | AC59: 0 | AD59: 0 | AE59: 0.08 | AF59: 0 | AG59: 25 | AH59: 25 | AI59: 1 | AJ59: Operation | AK59: Flat | AY59: none | BN59: 0 | BU59: =IF(BL59=1,BN59,0) -> 0 | CB59: 0 | CC59: 0.1 | CD59: 2 | CE59: 4 | CF59: 4 | CG59: 4 | CH59: 4 | DK59: [103] | DL59: =VLOOKUP($F59,Activities!$A$9:$I$180,3,FALSE)/$AI59 -> 0 | DM59: =VLOOKUP($F59,Activities!$A$9:$I$180,4,FALSE)/$AI59 -> 0 | DN59: =VLOOKUP($F59,Activities!$A$9:$I$180,5,FALSE)/$AI59 -> 0 | DO59: =VLOOKUP($F59,Activities!$A$9:$I$180,6,FALSE)/$AI59 -> 0 | DP59: =VLOOKUP($F59,Activities!$A$9:$I$180,7,FALSE)/$AI59 -> 0 | DQ59: =VLOOKUP($F59,Activities!$A$9:$I$180,8,FALSE)/$AI59 -> 0 | DR59: =VLOOKUP($F59,Activities!$A$9:$I$180,9,FALSE)/$AI59 -> 0
A60: ICH01_07 | B60: Industrie | C60: Conversion | D60: Industry | E60: Chemicals | F60: Ethylene intermediate | G60: Electrified syn-naphtha steam cracker - Petrochemical industry | H60: [Mton_Ey/y] | I60: =I59 -> 1958.9385 | J60: =J59 -> 1958.9385 | K60: =K59 -> 1958.9385 | L60: =L59 -> 1958.9385 | M60: =M59 -> 1958.9385 | N60: =N59 -> 1958.9385 | O60: =O59 -> 1958.9385 | P60: 0 | Q60: =Q54 -> 77.581721 | R60: =R54 -> 77.581721 | S60: =S54 -> 77.581721 | T60: =T54 -> 77.581721 | U60: =U54 -> 77.581721 | V60: =V54 -> 77.581721 | W60: =W54 -> 77.581721 | X60: 0 | Y60: 0 | Z60: 0 | AA60: 0 | AB60: 0 | AC60: 0 | AD60: 0 | AE60: 0.08 | AF60: 0 | AG60: 25 | AH60: 25 | AI60: 1 | AJ60: Operation | AK60: Flat | AY60: none | BN60: 0 | BU60: =IF(BL60=1,BN60,0) -> 0 | CC60: 0.1 | CD60: 2 | CE60: 4 | CF60: 4 | CG60: 4 | CH60: 4 | DK60: [103] | DL60: =VLOOKUP($F60,Activities!$A$9:$I$180,3,FALSE)/$AI60 -> 0 | DM60: =VLOOKUP($F60,Activities!$A$9:$I$180,4,FALSE)/$AI60 -> 0 | DN60: =VLOOKUP($F60,Activities!$A$9:$I$180,5,FALSE)/$AI60 -> 0 | DO60: =VLOOKUP($F60,Activities!$A$9:$I$180,6,FALSE)/$AI60 -> 0 | DP60: =VLOOKUP($F60,Activities!$A$9:$I$180,7,FALSE)/$AI60 -> 0 | DQ60: =VLOOKUP($F60,Activities!$A$9:$I$180,8,FALSE)/$AI60 -> 0 | DR60: =VLOOKUP($F60,Activities!$A$9:$I$180,9,FALSE)/$AI60 -> 0
A61: ICH01_08 | B61: Industrie | C61: Conversion | D61: Industry | E61: Chemicals | F61: Ethylene intermediate | G61: Hydrogen fueled naphtha steam cracker - Petrochemical industry | H61: [Mton_Ey/y] | I61: =I54 -> 1939.543 | J61: =J54 -> 1939.543 | K61: =K54 -> 1939.543 | L61: =L54 -> 1939.543 | M61: =M54 -> 1939.543 | N61: =N54 -> 1939.543 | O61: =O54 -> 1939.543 | P61: 0 | Q61: =Q54 -> 77.581721 | R61: =R54 -> 77.581721 | S61: =S54 -> 77.581721 | T61: =T54 -> 77.581721 | U61: =U54 -> 77.581721 | V61: =V54 -> 77.581721 | W61: =W54 -> 77.581721 | X61: 0 | Y61: 0 | Z61: 0 | AA61: 0 | AB61: 0 | AC61: 0 | AD61: 0 | AE61: 0.08 | AF61: 0 | AG61: 25 | AH61: 25 | AI61: 1 | AJ61: Operation | AK61: Flat | AY61: none | BN61: 0 | BU61: 0 | CB61: 0 | CC61: 0.1 | CD61: 2 | CE61: 4 | CF61: 4 | CG61: 4 | CH61: 4 | DK61: [103] | DL61: =VLOOKUP($F61,Activities!$A$9:$I$180,3,FALSE)/$AI61 -> 0 | DM61: =VLOOKUP($F61,Activities!$A$9:$I$180,4,FALSE)/$AI61 -> 0 | DN61: =VLOOKUP($F61,Activities!$A$9:$I$180,5,FALSE)/$AI61 -> 0 | DO61: =VLOOKUP($F61,Activities!$A$9:$I$180,6,FALSE)/$AI61 -> 0 | DP61: =VLOOKUP($F61,Activities!$A$9:$I$180,7,FALSE)/$AI61 -> 0 | DQ61: =VLOOKUP($F61,Activities!$A$9:$I$180,8,FALSE)/$AI61 -> 0 | DR61: =VLOOKUP($F61,Activities!$A$9:$I$180,9,FALSE)/$AI61 -> 0
A62: ICH01_09 | B62: Industrie | C62: Conversion | D62: Industry | E62: Chemicals | F62: Ethylene intermediate | G62: Hydrogen fueled bio-naphtha steam cracker - Petrochemical industry | H62: [Mton_Ey/y] | I62: =I61 -> 1939.543 | J62: =J61 -> 1939.543 | K62: =K61 -> 1939.543 | L62: =L61 -> 1939.543 | M62: =M61 -> 1939.543 | N62: =N61 -> 1939.543 | O62: =O61 -> 1939.543 | P62: 0 | Q62: =Q54 -> 77.581721 | R62: =R54 -> 77.581721 | S62: =S54 -> 77.581721 | T62: =T54 -> 77.581721 | U62: =U54 -> 77.581721 | V62: =V54 -> 77.581721 | W62: =W54 -> 77.581721 | X62: 0 | Y62: 0 | Z62: 0 | AA62: 0 | AB62: 0 | AC62: 0 | AD62: 0 | AE62: 0.08 | AF62: 0 | AG62: 25 | AH62: 25 | AI62: 1 | AJ62: Operation | AK62: Flat | AY62: none | BN62: 0 | BU62: =IF(BL62=1,BN62,0) -> 0 | CC62: 0.1 | CD62: 2 | CE62: 4 | CF62: 4 | CG62: 4 | CH62: 4 | DK62: [103] | DL62: =VLOOKUP($F62,Activities!$A$9:$I$180,3,FALSE)/$AI62 -> 0 | DM62: =VLOOKUP($F62,Activities!$A$9:$I$180,4,FALSE)/$AI62 -> 0 | DN62: =VLOOKUP($F62,Activities!$A$9:$I$180,5,FALSE)/$AI62 -> 0 | DO62: =VLOOKUP($F62,Activities!$A$9:$I$180,6,FALSE)/$AI62 -> 0 | DP62: =VLOOKUP($F62,Activities!$A$9:$I$180,7,FALSE)/$AI62 -> 0 | DQ62: =VLOOKUP($F62,Activities!$A$9:$I$180,8,FALSE)/$AI62 -> 0 | DR62: =VLOOKUP($F62,Activities!$A$9:$I$180,9,FALSE)/$AI62 -> 0
A63: ICH01_10 | B63: Industrie | C63: Conversion | D63: Industry | E63: Chemicals | F63: Ethylene intermediate | G63: Hydrogen fueled syn-naphtha steam cracker - Petrochemical industry | H63: [Mton_Ey/y] | I63: =I62 -> 1939.543 | J63: =J62 -> 1939.543 | K63: =K62 -> 1939.543 | L63: =L62 -> 1939.543 | M63: =M62 -> 1939.543 | N63: =N62 -> 1939.543 | O63: =O62 -> 1939.543 | P63: 0 | Q63: =Q54 -> 77.581721 | R63: =R54 -> 77.581721 | S63: =S54 -> 77.581721 | T63: =T54 -> 77.581721 | U63: =U54 -> 77.581721 | V63: =V54 -> 77.581721 | W63: =W54 -> 77.581721 | X63: 0 | Y63: 0 | Z63: 0 | AA63: 0 | AB63: 0 | AC63: 0 | AD63: 0 | AE63: 0.08 | AF63: 0 | AG63: 25 | AH63: 25 | AI63: 1 | AJ63: Operation | AK63: Flat | AY63: none | BN63: 0 | BU63: =IF(BL63=1,BN63,0) -> 0 | CC63: 0.1 | CD63: 2 | CE63: 4 | CF63: 4 | CG63: 4 | CH63: 4 | DK63: [103] | DL63: =VLOOKUP($F63,Activities!$A$9:$I$180,3,FALSE)/$AI63 -> 0 | DM63: =VLOOKUP($F63,Activities!$A$9:$I$180,4,FALSE)/$AI63 -> 0 | DN63: =VLOOKUP($F63,Activities!$A$9:$I$180,5,FALSE)/$AI63 -> 0 | DO63: =VLOOKUP($F63,Activities!$A$9:$I$180,6,FALSE)/$AI63 -> 0 | DP63: =VLOOKUP($F63,Activities!$A$9:$I$180,7,FALSE)/$AI63 -> 0 | DQ63: =VLOOKUP($F63,Activities!$A$9:$I$180,8,FALSE)/$AI63 -> 0 | DR63: =VLOOKUP($F63,Activities!$A$9:$I$180,9,FALSE)/$AI63 -> 0
A64: ICH01_11 | B64: Industrie | C64: Conversion | D64: Industry | E64: Chemicals | F64: Ethylene intermediate | G64: Ethylene from bioethanol dehydration - Petrochemical industry | H64: [Mton_Ey/y] | I64: 188.69348 | J64: 188.69348 | K64: 188.69348 | L64: 188.69348 | M64: 188.69348 | N64: 188.69348 | O64: 188.69348 | P64: 0 | Q64: 7.5477391 | R64: 7.5477391 | S64: 7.5477391 | T64: 7.5477391 | U64: 7.5477391 | V64: 7.5477391 | W64: 7.5477391 | X64: 0 | Y64: 0 | Z64: 0 | AA64: 0 | AB64: 0 | AC64: 0 | AD64: 0 | AE64: 0.08 | AF64: 0 | AG64: 25 | AH64: 25 | AI64: 1 | AJ64: Operation | AK64: Flat | AY64: none | BN64: 0 | BU64: =IF(BL64=1,BN64,0) -> 0 | CC64: 4 | CD64: 4 | CE64: 4 | CF64: 4 | CG64: 4 | CH64: 4 | DK64: [103] | DL64: =VLOOKUP($F64,Activities!$A$9:$I$180,3,FALSE)/$AI64 -> 0 | DM64: =VLOOKUP($F64,Activities!$A$9:$I$180,4,FALSE)/$AI64 -> 0 | DN64: =VLOOKUP($F64,Activities!$A$9:$I$180,5,FALSE)/$AI64 -> 0 | DO64: =VLOOKUP($F64,Activities!$A$9:$I$180,6,FALSE)/$AI64 -> 0 | DP64: =VLOOKUP($F64,Activities!$A$9:$I$180,7,FALSE)/$AI64 -> 0 | DQ64: =VLOOKUP($F64,Activities!$A$9:$I$180,8,FALSE)/$AI64 -> 0 | DR64: =VLOOKUP($F64,Activities!$A$9:$I$180,9,FALSE)/$AI64 -> 0
A65: ICH01_12 | B65: Industrie | C65: Conversion | D65: Industry | E65: Chemicals | F65: Propylene intermediate | G65: Methanol to olefins - Petrochemical industry | H65: [Mton_Py/y] | I65: 629.02088 | J65: 629.02088 | K65: 629.02088 | L65: 629.02088 | M65: 629.02088 | N65: 629.02088 | O65: 629.02088 | P65: 0 | Q65: 15.725522 | R65: 15.725522 | S65: 15.725522 | T65: 15.725522 | U65: 15.725522 | V65: 15.725522 | W65: 15.725522 | X65: 0 | Y65: 0 | Z65: 0 | AA65: 0 | AB65: 0 | AC65: 0 | AD65: 0 | AE65: 0.08 | AF65: 0 | AG65: 25 | AH65: 25 | AI65: 1 | AJ65: Operation | AK65: Flat | AY65: none | BN65: 0 | BU65: =IF(BL65=1,BN65,0) -> 0 | CC65: 1 | CD65: 4 | CE65: 4 | CF65: 4 | CG65: 4 | CH65: 4 | DK65: [103] | DL65: =VLOOKUP($F65,Activities!$A$9:$I$180,3,FALSE)/$AI65 -> 0 | DM65: =VLOOKUP($F65,Activities!$A$9:$I$180,4,FALSE)/$AI65 -> 0 | DN65: =VLOOKUP($F65,Activities!$A$9:$I$180,5,FALSE)/$AI65 -> 0 | DO65: =VLOOKUP($F65,Activities!$A$9:$I$180,6,FALSE)/$AI65 -> 0 | DP65: =VLOOKUP($F65,Activities!$A$9:$I$180,7,FALSE)/$AI65 -> 0 | DQ65: =VLOOKUP($F65,Activities!$A$9:$I$180,8,FALSE)/$AI65 -> 0 | DR65: =VLOOKUP($F65,Activities!$A$9:$I$180,9,FALSE)/$AI65 -> 0
A66: ICH01_13 | B66: Industrie | C66: Primary | D66: Material | E66: Chemicals | F66: Ethylene intermediate | G66: Ethylene imports - Petrochemical industry | H66: [Mton_Ey/y] | I66: 0 | J66: 0 | K66: 0 | L66: 0 | M66: 0 | N66: 0 | O66: 0 | P66: 0 | Q66: 0 | R66: 0 | S66: 0 | T66: 0 | U66: 0 | V66: 0 | W66: 0 | X66: 1049.6176 | Y66: 1049.6176 | Z66: 1049.6176 | AA66: 1049.6176 | AB66: 1049.6176 | AC66: 1049.6176 | AD66: 1049.6176 | AE66: 0.08 | AF66: 0 | AG66: 1 | AH66: 1 | AI66: 1 | AJ66: Operation | AK66: Flat | AY66: none | BN66: 0 | BU66: =IF(BL66=1,BN66,0) -> 0 | CB66: 0 | CC66: 0 | CD66: 0 | CE66: 0 | CF66: 0 | CG66: 0 | CH66: 0 | DK66: [55] | DL66: =VLOOKUP($F66,Activities!$A$9:$I$180,3,FALSE)/$AI66 -> 0 | DM66: =VLOOKUP($F66,Activities!$A$9:$I$180,4,FALSE)/$AI66 -> 0 | DN66: =VLOOKUP($F66,Activities!$A$9:$I$180,5,FALSE)/$AI66 -> 0 | DO66: =VLOOKUP($F66,Activities!$A$9:$I$180,6,FALSE)/$AI66 -> 0 | DP66: =VLOOKUP($F66,Activities!$A$9:$I$180,7,FALSE)/$AI66 -> 0 | DQ66: =VLOOKUP($F66,Activities!$A$9:$I$180,8,FALSE)/$AI66 -> 0 | DR66: =VLOOKUP($F66,Activities!$A$9:$I$180,9,FALSE)/$AI66 -> 0
A67: ICH01_14 | B67: Industrie | C67: Conversion | D67: Industry | E67: Chemicals | F67: Propylene intermediate | G67: Propylene from PDH alkenation of LPG - Petrochemicals | H67: [Mton_Py/y] | I67: 1180.5315 | J67: 1180.5315 | K67: 1180.5315 | L67: 1180.5315 | M67: 1180.5315 | N67: 1180.5315 | O67: 1180.5315 | P67: 0 | Q67: 53.123919 | R67: 53.123919 | S67: 53.123919 | T67: 53.123919 | U67: 53.123919 | V67: 53.123919 | W67: 53.123919 | X67: 0 | Y67: 0 | Z67: 0 | AA67: 0 | AB67: 0 | AC67: 0 | AD67: 0 | AE67: 0.08 | AG67: 25 | AH67: 25 | AI67: 1 | AJ67: Operation | AK67: Flat | AY67: none | BN67: 0.12 | BP67: 0.12 | BU67: =IF(BL67=1,BN67,0) -> 0 | CB67: 1 | CC67: 1 | CD67: 1 | CE67: 1 | CF67: 1 | CG67: 1 | CH67: 1 | DK67: [103] | DL67: =VLOOKUP($F67,Activities!$A$9:$I$180,3,FALSE)/$AI67 -> 0 | DM67: =VLOOKUP($F67,Activities!$A$9:$I$180,4,FALSE)/$AI67 -> 0 | DN67: =VLOOKUP($F67,Activities!$A$9:$I$180,5,FALSE)/$AI67 -> 0 | DO67: =VLOOKUP($F67,Activities!$A$9:$I$180,6,FALSE)/$AI67 -> 0 | DP67: =VLOOKUP($F67,Activities!$A$9:$I$180,7,FALSE)/$AI67 -> 0 | DQ67: =VLOOKUP($F67,Activities!$A$9:$I$180,8,FALSE)/$AI67 -> 0 | DR67: =VLOOKUP($F67,Activities!$A$9:$I$180,9,FALSE)/$AI67 -> 0
A68: ICH01_15 | B68: Industrie | C68: Conversion | D68: Industry | E68: Chemicals | F68: Propylene intermediate | G68: Propylene from ethanol dehydration, ethene dimerization and metathesis - Petrochemicals | H68: [Mton_Py/y] | I68: =193.4/0.027*(103.328/124.163)/1.1195 -> 5324.6913 | J68: =I68 -> 5324.6913 | K68: =J68 -> 5324.6913 | L68: =K68 -> 5324.6913 | M68: =L68 -> 5324.6913 | N68: =M68 -> 5324.6913 | O68: =N68 -> 5324.6913 | P68: 0 | Q68: =(1.2+3.2)/(25.4*0.27*8760/10^6)*(103.328/124.163)/1.1195 -> 54.44435 | R68: =(1.2+3.2)/(25.4*0.27*8760/10^6)*(103.328/124.163)/1.1195 -> 54.44435 | S68: =(1.2+3.2)/(25.4*0.27*8760/10^6)*(103.328/124.163)/1.1195 -> 54.44435 | T68: =(1.2+3.2)/(25.4*0.27*8760/10^6)*(103.328/124.163)/1.1195 -> 54.44435 | U68: =(1.2+3.2)/(25.4*0.27*8760/10^6)*(103.328/124.163)/1.1195 -> 54.44435 | V68: =(1.2+3.2)/(25.4*0.27*8760/10^6)*(103.328/124.163)/1.1195 -> 54.44435 | W68: =(1.2+3.2)/(25.4*0.27*8760/10^6)*(103.328/124.163)/1.1195 -> 54.44435 | X68: =(48.3)/(25.4*0.27*8760/10^6)*(103.328/124.163)/1.1195 -> 597.65048 | Y68: =(48.3)/(25.4*0.27*8760/10^6)*(103.328/124.163)/1.1195 -> 597.65048 | Z68: =(48.3)/(25.4*0.27*8760/10^6)*(103.328/124.163)/1.1195 -> 597.65048 | AA68: =(48.3)/(25.4*0.27*8760/10^6)*(103.328/124.163)/1.1195 -> 597.65048 | AB68: =(48.3)/(25.4*0.27*8760/10^6)*(103.328/124.163)/1.1195 -> 597.65048 | AC68: =(48.3)/(25.4*0.27*8760/10^6)*(103.328/124.163)/1.1195 -> 597.65048 | AD68: =(48.3)/(25.4*0.27*8760/10^6)*(103.328/124.163)/1.1195 -> 597.65048 | AE68: 0.08 | AG68: 25 | AH68: 25 | AI68: 1 | AJ68: Operation | AK68: Flat | AY68: none | BN68: 0 | BU68: =IF(BL68=1,BN68,0) -> 0 | CB68: 0 | CC68: 0 | CD68: 0 | CE68: 0 | CF68: 0 | CG68: 0 | CH68: 0 | DK68: [102] | DL68: =VLOOKUP($F68,Activities!$A$9:$I$180,3,FALSE)/$AI68 -> 0 | DM68: =VLOOKUP($F68,Activities!$A$9:$I$180,4,FALSE)/$AI68 -> 0 | DN68: =VLOOKUP($F68,Activities!$A$9:$I$180,5,FALSE)/$AI68 -> 0 | DO68: =VLOOKUP($F68,Activities!$A$9:$I$180,6,FALSE)/$AI68 -> 0 | DP68: =VLOOKUP($F68,Activities!$A$9:$I$180,7,FALSE)/$AI68 -> 0 | DQ68: =VLOOKUP($F68,Activities!$A$9:$I$180,8,FALSE)/$AI68 -> 0 | DR68: =VLOOKUP($F68,Activities!$A$9:$I$180,9,FALSE)/$AI68 -> 0
A69: ICH01_16 | B69: Industrie | C69: Primary | D69: Material | E69: Chemicals | F69: Propylene intermediate | G69: Propylene imports - Petrochemical industry | H69: [Mton_Py/y] | I69: 0 | J69: 0 | K69: 0 | L69: 0 | M69: 0 | N69: 0 | O69: 0 | P69: 0 | Q69: 0 | R69: 0 | S69: 0 | T69: 0 | U69: 0 | V69: 0 | W69: 0 | X69: 1042.0867 | Y69: 1042.0867 | Z69: 1042.0867 | AA69: 1042.0867 | AB69: 1042.0867 | AC69: 1042.0867 | AD69: 1042.0867 | AE69: 0.08 | AF69: 0 | AG69: 1 | AH69: 1 | AI69: 1 | AJ69: Operation | AK69: Flat | AY69: none | BU69: =IF(BL69=1,BN69,0) -> 0 | CB69: 0.1 | CC69: 0.1 | CD69: 0.1 | CE69: 0.1 | CF69: 0.1 | CG69: 0.1 | CH69: 0.1 | DK69: [55] | DL69: =VLOOKUP($F69,Activities!$A$9:$I$180,3,FALSE)/$AI69 -> 0 | DM69: =VLOOKUP($F69,Activities!$A$9:$I$180,4,FALSE)/$AI69 -> 0 | DN69: =VLOOKUP($F69,Activities!$A$9:$I$180,5,FALSE)/$AI69 -> 0 | DO69: =VLOOKUP($F69,Activities!$A$9:$I$180,6,FALSE)/$AI69 -> 0 | DP69: =VLOOKUP($F69,Activities!$A$9:$I$180,7,FALSE)/$AI69 -> 0 | DQ69: =VLOOKUP($F69,Activities!$A$9:$I$180,8,FALSE)/$AI69 -> 0 | DR69: =VLOOKUP($F69,Activities!$A$9:$I$180,9,FALSE)/$AI69 -> 0
A70: ICH01_17 | B70: Industrie | C70: Primary | D70: Material | E70: Chemicals | F70: Butadiene production - Chemical Industry | G70: Butadiene imports - Petrochemical industry | H70: [Mton_Butadiene/y] | I70: 0 | J70: 0 | K70: 0 | L70: 0 | M70: 0 | N70: 0 | O70: 0 | P70: 0 | Q70: 0 | R70: 0 | S70: 0 | T70: 0 | U70: 0 | V70: 0 | W70: 0 | X70: 938.34354 | Y70: 938.34354 | Z70: 938.34354 | AA70: 938.34354 | AB70: 938.34354 | AC70: 938.34354 | AD70: 938.34354 | AE70: 0.08 | AF70: 0 | AG70: 1 | AH70: 1 | AI70: 1 | AJ70: Operation | AK70: Flat | AY70: none | BN70: 0 | BU70: =IF(BL70=1,BN70,0) -> 0 | CB70: =DL70 -> 0.344 | CC70: =DM70 -> 0.344 | CD70: =DN70 -> 0.344 | CE70: =DO70 -> 0.344 | CF70: =DP70 -> 0.344 | CG70: =DQ70 -> 0.344 | CH70: =DR70 -> 0.344 | DK70: [55] | DL70: =VLOOKUP($F70,Activities!$A$9:$I$180,3,FALSE)/$AI70 -> 0.344 | DM70: =VLOOKUP($F70,Activities!$A$9:$I$180,4,FALSE)/$AI70 -> 0.344 | DN70: =VLOOKUP($F70,Activities!$A$9:$I$180,5,FALSE)/$AI70 -> 0.344 | DO70: =VLOOKUP($F70,Activities!$A$9:$I$180,6,FALSE)/$AI70 -> 0.344 | DP70: =VLOOKUP($F70,Activities!$A$9:$I$180,7,FALSE)/$AI70 -> 0.344 | DQ70: =VLOOKUP($F70,Activities!$A$9:$I$180,8,FALSE)/$AI70 -> 0.344 | DR70: =VLOOKUP($F70,Activities!$A$9:$I$180,9,FALSE)/$AI70 -> 0.344
A71: ICH01_18 | B71: Industrie | C71: Final | D71: Industry | E71: Chemicals | F71: LDPE production - Chemical Industry | G71: High-pressure polymerisation of low-density polyethylene (LDPE) | H71: [Mton_LDPE/y] | I71: =(141*1.0658)/0.3 -> 500.926 | J71: =(141*1.0658)/0.3 -> 500.926 | K71: =(141*1.0658)/0.3 -> 500.926 | L71: =(141*1.0658)/0.3 -> 500.926 | M71: =(141*1.0658)/0.3 -> 500.926 | N71: =(141*1.0658)/0.3 -> 500.926 | O71: =(141*1.0658)/0.3 -> 500.926 | P71: 0 | Q71: =I71*0.05 -> 25.0463 | R71: =J71*0.05 -> 25.0463 | S71: =K71*0.05 -> 25.0463 | T71: =L71*0.05 -> 25.0463 | U71: =M71*0.05 -> 25.0463 | V71: =N71*0.05 -> 25.0463 | W71: =O71*0.05 -> 25.0463 | X71: =(18*1.0658) -> 19.1844 | Y71: =(18*1.0658) -> 19.1844 | Z71: =(18*1.0658) -> 19.1844 | AA71: =(18*1.0658) -> 19.1844 | AB71: =(18*1.0658) -> 19.1844 | AC71: =(18*1.0658) -> 19.1844 | AD71: =(18*1.0658) -> 19.1844 | AE71: 0.08 | AG71: 25 | AH71: 25 | AI71: 1 | AJ71: Operation | AK71: Flat | AY71: none | BN71: =DL71 -> 0.584 | BR71: =BQ71 -> 0 | BU71: =IF(BL71=1,BN71,0) -> 0 | CB71: 5 | CC71: =DM71 -> 0.584 | CD71: =DN71 -> 0.584 | CE71: =DO71 -> 0.584 | CF71: =DP71 -> 0.584 | CG71: =DQ71 -> 0.584 | CH71: =DR71 -> 0.584 | DK71: [D] | DL71: =VLOOKUP($F71,Activities!$A$9:$I$180,3,FALSE)/$AI71 -> 0.584 | DM71: =VLOOKUP($F71,Activities!$A$9:$I$180,4,FALSE)/$AI71 -> 0.584 | DN71: =VLOOKUP($F71,Activities!$A$9:$I$180,5,FALSE)/$AI71 -> 0.584 | DO71: =VLOOKUP($F71,Activities!$A$9:$I$180,6,FALSE)/$AI71 -> 0.584 | DP71: =VLOOKUP($F71,Activities!$A$9:$I$180,7,FALSE)/$AI71 -> 0.584 | DQ71: =VLOOKUP($F71,Activities!$A$9:$I$180,8,FALSE)/$AI71 -> 0.584 | DR71: =VLOOKUP($F71,Activities!$A$9:$I$180,9,FALSE)/$AI71 -> 0.584
A72: ICH01_19 | B72: Industrie | C72: Final | D72: Industry | E72: Chemicals | F72: LLDPE production - Chemical Industry | G72: Solution polymerisation of linear low-density polyethylene (LLDPE) | H72: [Mton_LLDPE/y] | I72: =(154*1.0658)/0.25 -> 656.5328 | J72: =(154*1.0658)/0.25 -> 656.5328 | K72: =(154*1.0658)/0.25 -> 656.5328 | L72: =(154*1.0658)/0.25 -> 656.5328 | M72: =(154*1.0658)/0.25 -> 656.5328 | N72: =(154*1.0658)/0.25 -> 656.5328 | O72: =(154*1.0658)/0.25 -> 656.5328 | P72: 0 | Q72: =I72*0.05 -> 32.82664 | R72: =J72*0.05 -> 32.82664 | S72: =K72*0.05 -> 32.82664 | T72: =L72*0.05 -> 32.82664 | U72: =M72*0.05 -> 32.82664 | V72: =N72*0.05 -> 32.82664 | W72: =O72*0.05 -> 32.82664 | X72: =(36*1.0658) -> 38.3688 | Y72: =(36*1.0658) -> 38.3688 | Z72: =(36*1.0658) -> 38.3688 | AA72: =(36*1.0658) -> 38.3688 | AB72: =(36*1.0658) -> 38.3688 | AC72: =(36*1.0658) -> 38.3688 | AD72: =(36*1.0658) -> 38.3688 | AE72: 0.08 | AG72: 25 | AH72: 25 | AI72: 1 | AJ72: Operation | AK72: Flat | AY72: none | BN72: =DL72 -> 0.64 | BR72: =BN72 -> 0.64 | BU72: =IF(BL72=1,BN72,0) -> 0 | CB72: 5 | CC72: =DM72 -> 0.64 | CD72: =DN72 -> 0.64 | CE72: =DO72 -> 0.64 | CF72: =DP72 -> 0.64 | CG72: =DQ72 -> 0.64 | CH72: =DR72 -> 0.64 | DK72: [D] | DL72: =VLOOKUP($F72,Activities!$A$9:$I$180,3,FALSE)/$AI72 -> 0.64 | DM72: =VLOOKUP($F72,Activities!$A$9:$I$180,4,FALSE)/$AI72 -> 0.64 | DN72: =VLOOKUP($F72,Activities!$A$9:$I$180,5,FALSE)/$AI72 -> 0.64 | DO72: =VLOOKUP($F72,Activities!$A$9:$I$180,6,FALSE)/$AI72 -> 0.64 | DP72: =VLOOKUP($F72,Activities!$A$9:$I$180,7,FALSE)/$AI72 -> 0.64 | DQ72: =VLOOKUP($F72,Activities!$A$9:$I$180,8,FALSE)/$AI72 -> 0.64 | DR72: =VLOOKUP($F72,Activities!$A$9:$I$180,9,FALSE)/$AI72 -> 0.64
A73: ICH01_20 | B73: Industrie | C73: Final | D73: Industry | E73: Chemicals | F73: HDPE production - Chemical Industry | G73: Suspension/slurry polymerisation of high-density polyethylene (HDPE) | H73: [Mton_HDPE/y] | I73: =(AVERAGE(108,138)*1.0658)/0.2 -> 655.467 | J73: =(AVERAGE(108,138)*1.0658)/0.2 -> 655.467 | K73: =(AVERAGE(108,138)*1.0658)/0.2 -> 655.467 | L73: =(AVERAGE(108,138)*1.0658)/0.2 -> 655.467 | M73: =(AVERAGE(108,138)*1.0658)/0.2 -> 655.467 | N73: =(AVERAGE(108,138)*1.0658)/0.2 -> 655.467 | O73: =(AVERAGE(108,138)*1.0658)/0.2 -> 655.467 | P73: 0 | Q73: =I73*0.05 -> 32.77335 | R73: =J73*0.05 -> 32.77335 | S73: =K73*0.05 -> 32.77335 | T73: =L73*0.05 -> 32.77335 | U73: =M73*0.05 -> 32.77335 | V73: =N73*0.05 -> 32.77335 | W73: =O73*0.05 -> 32.77335 | X73: =(AVERAGE(30,30)*1.0658) -> 31.974 | Y73: =(AVERAGE(30,30)*1.0658) -> 31.974 | Z73: =(AVERAGE(30,30)*1.0658) -> 31.974 | AA73: =(AVERAGE(30,30)*1.0658) -> 31.974 | AB73: =(AVERAGE(30,30)*1.0658) -> 31.974 | AC73: =(AVERAGE(30,30)*1.0658) -> 31.974 | AD73: =(AVERAGE(30,30)*1.0658) -> 31.974 | AE73: 0.08 | AG73: 25 | AH73: 25 | AI73: 1 | AJ73: Operation | AK73: Flat | AY73: none | BN73: =DL73 -> 0.248 | BR73: =BN73 -> 0.248 | BU73: =IF(BL73=1,BN73,0) -> 0 | CB73: 5 | CC73: =DM73 -> 0.248 | CD73: =DN73 -> 0.248 | CE73: =DO73 -> 0.248 | CF73: =DP73 -> 0.248 | CG73: =DQ73 -> 0.248 | CH73: =DR73 -> 0.248 | DK73: [D] | DL73: =VLOOKUP($F73,Activities!$A$9:$I$180,3,FALSE)/$AI73 -> 0.248 | DM73: =VLOOKUP($F73,Activities!$A$9:$I$180,4,FALSE)/$AI73 -> 0.248 | DN73: =VLOOKUP($F73,Activities!$A$9:$I$180,5,FALSE)/$AI73 -> 0.248 | DO73: =VLOOKUP($F73,Activities!$A$9:$I$180,6,FALSE)/$AI73 -> 0.248 | DP73: =VLOOKUP($F73,Activities!$A$9:$I$180,7,FALSE)/$AI73 -> 0.248 | DQ73: =VLOOKUP($F73,Activities!$A$9:$I$180,8,FALSE)/$AI73 -> 0.248 | DR73: =VLOOKUP($F73,Activities!$A$9:$I$180,9,FALSE)/$AI73 -> 0.248
A74: ICH01_21 | B74: Industrie | C74: Final | D74: Industry | E74: Chemicals | F74: Polypropylene production - Chemical Industry | G74: Gas-phase polymerisation of polypropylene (PP) | H74: [Mton_PP/y] | I74: =(AVERAGE(90/0.2,114/0.25)*1.0658) -> 482.8074 | J74: =(AVERAGE(90/0.2,114/0.25)*1.0658) -> 482.8074 | K74: =(AVERAGE(90/0.2,114/0.25)*1.0658) -> 482.8074 | L74: =(AVERAGE(90/0.2,114/0.25)*1.0658) -> 482.8074 | M74: =(AVERAGE(90/0.2,114/0.25)*1.0658) -> 482.8074 | N74: =(AVERAGE(90/0.2,114/0.25)*1.0658) -> 482.8074 | O74: =(AVERAGE(90/0.2,114/0.25)*1.0658) -> 482.8074 | P74: 0 | Q74: =I74*0.05 -> 24.14037 | R74: =J74*0.05 -> 24.14037 | S74: =K74*0.05 -> 24.14037 | T74: =L74*0.05 -> 24.14037 | U74: =M74*0.05 -> 24.14037 | V74: =N74*0.05 -> 24.14037 | W74: =O74*0.05 -> 24.14037 | X74: =(AVERAGE(36,30)*1.0658) -> 35.1714 | Y74: =(AVERAGE(36,30)*1.0658) -> 35.1714 | Z74: =(AVERAGE(36,30)*1.0658) -> 35.1714 | AA74: =(AVERAGE(36,30)*1.0658) -> 35.1714 | AB74: =(AVERAGE(36,30)*1.0658) -> 35.1714 | AC74: =(AVERAGE(36,30)*1.0658) -> 35.1714 | AD74: =(AVERAGE(36,30)*1.0658) -> 35.1714 | AE74: 0.08 | AG74: 25 | AH74: 25 | AI74: 1 | AJ74: Operation | AK74: Flat | AY74: none | BN74: =DL74 -> 0.6 | BR74: =BN74 -> 0.6 | BU74: =IF(BL74=1,BN74,0) -> 0 | CB74: 5 | CC74: =DM74 -> 0.6 | CD74: =DN74 -> 0.6 | CE74: =DO74 -> 0.6 | CF74: =DP74 -> 0.6 | CG74: =DQ74 -> 0.6 | CH74: =DR74 -> 0.6 | DK74: [D] | DL74: =VLOOKUP($F74,Activities!$A$9:$I$180,3,FALSE)/$AI74 -> 0.6 | DM74: =VLOOKUP($F74,Activities!$A$9:$I$180,4,FALSE)/$AI74 -> 0.6 | DN74: =VLOOKUP($F74,Activities!$A$9:$I$180,5,FALSE)/$AI74 -> 0.6 | DO74: =VLOOKUP($F74,Activities!$A$9:$I$180,6,FALSE)/$AI74 -> 0.6 | DP74: =VLOOKUP($F74,Activities!$A$9:$I$180,7,FALSE)/$AI74 -> 0.6 | DQ74: =VLOOKUP($F74,Activities!$A$9:$I$180,8,FALSE)/$AI74 -> 0.6 | DR74: =VLOOKUP($F74,Activities!$A$9:$I$180,9,FALSE)/$AI74 -> 0.6
A75: ICH01_22 | B75: Industrie | C75: Final | D75: Industry | E75: Chemicals | F75: Propylene production - chemical industry | G75: Dummy - conversion of propylene use to propylene final | H75: [Mton_Py/y] | I75: 0 | J75: 0 | K75: 0 | L75: 0 | M75: 0 | N75: 0 | O75: 0 | P75: 0 | Q75: 0 | R75: 0 | S75: 0 | T75: 0 | U75: 0 | V75: 0 | W75: 0 | X75: 0 | Y75: 0 | Z75: 0 | AA75: 0 | AB75: 0 | AC75: 0 | AD75: 0 | AE75: 0.08 | AG75: 25 | AH75: 25 | AI75: 1 | AJ75: Operation | AK75: Flat | AY75: none | BN75: =DL75 -> 0.96522772 | BU75: 0 | CB75: 10 | CC75: 10 | CD75: 10 | CE75: 10 | CF75: 10 | CG75: 10 | CH75: 10 | DK75: [D] | DL75: =VLOOKUP($F75,Activities!$A$9:$I$180,3,FALSE)/$AI75 -> 0.96522772 | DM75: =VLOOKUP($F75,Activities!$A$9:$I$180,4,FALSE)/$AI75 -> 0.96522772 | DN75: =VLOOKUP($F75,Activities!$A$9:$I$180,5,FALSE)/$AI75 -> 0.96522772 | DO75: =VLOOKUP($F75,Activities!$A$9:$I$180,6,FALSE)/$AI75 -> 0.96522772 | DP75: =VLOOKUP($F75,Activities!$A$9:$I$180,7,FALSE)/$AI75 -> 0.96522772 | DQ75: =VLOOKUP($F75,Activities!$A$9:$I$180,8,FALSE)/$AI75 -> 0.96522772 | DR75: =VLOOKUP($F75,Activities!$A$9:$I$180,9,FALSE)/$AI75 -> 0.96522772
A76: ICH01_23 | B76: Industrie | C76: Final | D76: Industry | E76: Chemicals | F76: Ethylene production - chemical industry | G76: Dummy - conversion of ethylene use to ethylene final | H76: [Mton_Ey/y] | I76: 0 | J76: 0 | K76: 0 | L76: 0 | M76: 0 | N76: 0 | O76: 0 | P76: 0 | Q76: 0 | R76: 0 | S76: 0 | T76: 0 | U76: 0 | V76: 0 | W76: 0 | X76: 0 | Y76: 0 | Z76: 0 | AA76: 0 | AB76: 0 | AC76: 0 | AD76: 0 | AE76: 0.08 | AG76: 25 | AH76: 25 | AI76: 1 | AJ76: Operation | AK76: Flat | AY76: none | BN76: =DL76 -> 0.4003093 | BU76: 0 | CB76: 10 | CC76: 10 | CD76: 10 | CE76: 10 | CF76: 10 | CG76: 10 | CH76: 10 | DK76: [D] | DL76: =VLOOKUP($F76,Activities!$A$9:$I$180,3,FALSE)/$AI76 -> 0.4003093 | DM76: =VLOOKUP($F76,Activities!$A$9:$I$180,4,FALSE)/$AI76 -> 0.4003093 | DN76: =VLOOKUP($F76,Activities!$A$9:$I$180,5,FALSE)/$AI76 -> 0.4003093 | DO76: =VLOOKUP($F76,Activities!$A$9:$I$180,6,FALSE)/$AI76 -> 0.4003093 | DP76: =VLOOKUP($F76,Activities!$A$9:$I$180,7,FALSE)/$AI76 -> 0.4003093 | DQ76: =VLOOKUP($F76,Activities!$A$9:$I$180,8,FALSE)/$AI76 -> 0.4003093 | DR76: =VLOOKUP($F76,Activities!$A$9:$I$180,9,FALSE)/$AI76 -> 0.4003093
A77: ICH01_24 | B77: Industrie | C77: Final | D77: Industry | E77: Chemicals | F77: PTA production - Chemical Industry | G77: Dummy - conversion of PTA intermediate to PTA final | H77: [Mton_PTA/y] | I77: 0 | J77: 0 | K77: 0 | L77: 0 | M77: 0 | N77: 0 | O77: 0 | P77: 0 | Q77: 0 | R77: 0 | S77: 0 | T77: 0 | U77: 0 | V77: 0 | W77: 0 | X77: 0 | Y77: 0 | Z77: 0 | AA77: 0 | AB77: 0 | AC77: 0 | AD77: 0 | AE77: 0.08 | AG77: 25 | AH77: 25 | AI77: 1 | AJ77: Operation | AK77: Flat | AY77: none | BN77: =DL77 -> 0.2736 | BU77: 0 | CB77: 10 | CC77: 10 | CD77: 10 | CE77: 10 | CF77: 10 | CG77: 10 | CH77: 10 | DK77: [D] | DL77: =VLOOKUP($F77,Activities!$A$9:$I$180,3,FALSE)/$AI77 -> 0.2736 | DM77: =VLOOKUP($F77,Activities!$A$9:$I$180,4,FALSE)/$AI77 -> 0.2736 | DN77: =VLOOKUP($F77,Activities!$A$9:$I$180,5,FALSE)/$AI77 -> 0.2736 | DO77: =VLOOKUP($F77,Activities!$A$9:$I$180,6,FALSE)/$AI77 -> 0.2736 | DP77: =VLOOKUP($F77,Activities!$A$9:$I$180,7,FALSE)/$AI77 -> 0.2736 | DQ77: =VLOOKUP($F77,Activities!$A$9:$I$180,8,FALSE)/$AI77 -> 0.2736 | DR77: =VLOOKUP($F77,Activities!$A$9:$I$180,9,FALSE)/$AI77 -> 0.2736
A78: ICH01_25 | B78: Industrie | C78: Conversion | D78: Industry | E78: Chemicals | F78: PTA intermediate | G78: Paraxylene oxidation and crystallization | H78: [Mton_PTA/y] | I78: =I73 -> 655.467 | J78: =J73 -> 655.467 | K78: =K73 -> 655.467 | L78: =L73 -> 655.467 | M78: =M73 -> 655.467 | N78: =N73 -> 655.467 | O78: =O73 -> 655.467 | P78: 0 | Q78: =I78*0.05 -> 32.77335 | R78: =J78*0.05 -> 32.77335 | S78: =K78*0.05 -> 32.77335 | T78: =L78*0.05 -> 32.77335 | U78: =M78*0.05 -> 32.77335 | V78: =N78*0.05 -> 32.77335 | W78: =O78*0.05 -> 32.77335 | X78: =X73 -> 31.974 | Y78: =Y73 -> 31.974 | Z78: =Z73 -> 31.974 | AA78: =AA73 -> 31.974 | AB78: =AB73 -> 31.974 | AC78: =AC73 -> 31.974 | AD78: =AD73 -> 31.974 | AE78: 0.08 | AG78: 25 | AH78: 25 | AI78: 1 | AJ78: Operation | AK78: Flat | AY78: none | BN78: =BN77+0.84*Activities!C32 -> 0.559872 | BR78: =BN78 -> 0.559872 | BU78: 0 | CB78: 10 | CC78: 10 | CD78: 10 | CE78: 10 | CF78: 10 | CG78: 10 | CH78: 10 | DK78: [D] | DL78: =VLOOKUP($F78,Activities!$A$9:$I$180,3,FALSE)/$AI78 -> 0 | DM78: =VLOOKUP($F78,Activities!$A$9:$I$180,4,FALSE)/$AI78 -> 0 | DN78: =VLOOKUP($F78,Activities!$A$9:$I$180,5,FALSE)/$AI78 -> 0 | DO78: =VLOOKUP($F78,Activities!$A$9:$I$180,6,FALSE)/$AI78 -> 0 | DP78: =VLOOKUP($F78,Activities!$A$9:$I$180,7,FALSE)/$AI78 -> 0 | DQ78: =VLOOKUP($F78,Activities!$A$9:$I$180,8,FALSE)/$AI78 -> 0 | DR78: =VLOOKUP($F78,Activities!$A$9:$I$180,9,FALSE)/$AI78 -> 0
A79: ICH01_26 | B79: Industrie | C79: Conversion | D79: Industry | E79: Chemicals | F79: Polyethylene terephthalate (PET) | G79: Polymerization to PET (PTA & MEG) | H79: [Mton_PET/y] | I79: =(141*1.0658)/0.3 -> 500.926 | J79: =(141*1.0658)/0.3 -> 500.926 | K79: =(141*1.0658)/0.3 -> 500.926 | L79: =(141*1.0658)/0.3 -> 500.926 | M79: =(141*1.0658)/0.3 -> 500.926 | N79: =(141*1.0658)/0.3 -> 500.926 | O79: =(141*1.0658)/0.3 -> 500.926 | P79: 0 | Q79: =I79*0.05 -> 25.0463 | R79: =J79*0.05 -> 25.0463 | S79: =K79*0.05 -> 25.0463 | T79: =L79*0.05 -> 25.0463 | U79: =M79*0.05 -> 25.0463 | V79: =N79*0.05 -> 25.0463 | W79: =O79*0.05 -> 25.0463 | X79: =(18*1.0658) -> 19.1844 | Y79: =(18*1.0658) -> 19.1844 | Z79: =(18*1.0658) -> 19.1844 | AA79: =(18*1.0658) -> 19.1844 | AB79: =(18*1.0658) -> 19.1844 | AC79: =(18*1.0658) -> 19.1844 | AD79: =(18*1.0658) -> 19.1844 | AE79: 0.08 | AG79: 25 | AH79: 25 | AI79: 1 | AJ79: Operation | AK79: Flat | AY79: none | BN79: =Activities!C32 -> 0.3408 | BR79: =BN79 -> 0.3408 | BU79: 0 | CB79: 5 | CC79: 5 | CD79: 5 | CE79: 5 | CF79: 5 | CG79: 5 | CH79: 5 | DK79: [D] | DL79: =VLOOKUP($F79,Activities!$A$9:$I$180,3,FALSE)/$AI79 -> 0 | DM79: =VLOOKUP($F79,Activities!$A$9:$I$180,4,FALSE)/$AI79 -> 0 | DN79: =VLOOKUP($F79,Activities!$A$9:$I$180,5,FALSE)/$AI79 -> 0 | DO79: =VLOOKUP($F79,Activities!$A$9:$I$180,6,FALSE)/$AI79 -> 0 | DP79: =VLOOKUP($F79,Activities!$A$9:$I$180,7,FALSE)/$AI79 -> 0 | DQ79: =VLOOKUP($F79,Activities!$A$9:$I$180,8,FALSE)/$AI79 -> 0 | DR79: =VLOOKUP($F79,Activities!$A$9:$I$180,9,FALSE)/$AI79 -> 0
A80: ICH01_27 | B80: Industrie | C80: Final | D80: Industry | E80: Chemicals | F80: PVC production - Chemical Industry | G80: VCM production and polymerisation to PVC | H80: [Mton_PVC/y] | I80: =(AVERAGE(108,138)*1.0658)/0.2 -> 655.467 | J80: =(AVERAGE(108,138)*1.0658)/0.2 -> 655.467 | K80: =(AVERAGE(108,138)*1.0658)/0.2 -> 655.467 | L80: =(AVERAGE(108,138)*1.0658)/0.2 -> 655.467 | M80: =(AVERAGE(108,138)*1.0658)/0.2 -> 655.467 | N80: =(AVERAGE(108,138)*1.0658)/0.2 -> 655.467 | O80: =(AVERAGE(108,138)*1.0658)/0.2 -> 655.467 | P80: 0 | Q80: =I80*0.05 -> 32.77335 | R80: =J80*0.05 -> 32.77335 | S80: =K80*0.05 -> 32.77335 | T80: =L80*0.05 -> 32.77335 | U80: =M80*0.05 -> 32.77335 | V80: =N80*0.05 -> 32.77335 | W80: =O80*0.05 -> 32.77335 | X80: =(AVERAGE(30,30)*1.0658) -> 31.974 | Y80: =(AVERAGE(30,30)*1.0658) -> 31.974 | Z80: =(AVERAGE(30,30)*1.0658) -> 31.974 | AA80: =(AVERAGE(30,30)*1.0658) -> 31.974 | AB80: =(AVERAGE(30,30)*1.0658) -> 31.974 | AC80: =(AVERAGE(30,30)*1.0658) -> 31.974 | AD80: =(AVERAGE(30,30)*1.0658) -> 31.974 | AE80: 0.08 | AG80: 25 | AH80: 25 | AI80: 1 | AJ80: Operation | AK80: Flat | AY80: none | BN80: =DL80 -> 0.6 | BR80: =BN80 -> 0.6 | BU80: =IF(BL80=1,BN80,0) -> 0 | CB80: 5 | CC80: 5 | CD80: 5 | CE80: 5 | CF80: 5 | CG80: 5 | CH80: 5 | DK80: [D] | DL80: =VLOOKUP($F80,Activities!$A$9:$I$180,3,FALSE)/$AI80 -> 0.6 | DM80: =VLOOKUP($F80,Activities!$A$9:$I$180,4,FALSE)/$AI80 -> 0.6 | DN80: =VLOOKUP($F80,Activities!$A$9:$I$180,5,FALSE)/$AI80 -> 0.6 | DO80: =VLOOKUP($F80,Activities!$A$9:$I$180,6,FALSE)/$AI80 -> 0.6 | DP80: =VLOOKUP($F80,Activities!$A$9:$I$180,7,FALSE)/$AI80 -> 0.6 | DQ80: =VLOOKUP($F80,Activities!$A$9:$I$180,8,FALSE)/$AI80 -> 0.6 | DR80: =VLOOKUP($F80,Activities!$A$9:$I$180,9,FALSE)/$AI80 -> 0.6
A81: ICH01_28 | B81: Industrie | C81: Final | D81: Industry | E81: Chemicals | F81: PVC production - Chemical Industry | G81: VCM production and polymerisation to PVC with electric furnaces | H81: [Mton_PVC/y] | I81: =AVERAGE(35,50)+I80 -> 697.967 | J81: =AVERAGE(35,50)+J80 -> 697.967 | K81: =AVERAGE(35,50)+K80 -> 697.967 | L81: =AVERAGE(35,50)+L80 -> 697.967 | M81: =AVERAGE(35,50)+M80 -> 697.967 | N81: =AVERAGE(35,50)+N80 -> 697.967 | O81: =AVERAGE(35,50)+O80 -> 697.967 | P81: 0 | Q81: =0.02*I81 -> 13.95934 | R81: =0.02*J81 -> 13.95934 | S81: =0.02*K81 -> 13.95934 | T81: =0.02*L81 -> 13.95934 | U81: =0.02*M81 -> 13.95934 | V81: =0.02*N81 -> 13.95934 | W81: =0.02*O81 -> 13.95934 | X81: =(AVERAGE(30,30)*1.0658) -> 31.974 | Y81: =(AVERAGE(30,30)*1.0658) -> 31.974 | Z81: =(AVERAGE(30,30)*1.0658) -> 31.974 | AA81: =(AVERAGE(30,30)*1.0658) -> 31.974 | AB81: =(AVERAGE(30,30)*1.0658) -> 31.974 | AC81: =(AVERAGE(30,30)*1.0658) -> 31.974 | AD81: =(AVERAGE(30,30)*1.0658) -> 31.974 | AE81: 0.08 | AG81: 25 | AH81: 25 | AI81: 1 | AJ81: Operation | AK81: Flat | AY81: none | BU81: =IF(BL81=1,BN81,0) -> 0 | CB81: 5 | CC81: 5 | CD81: 5 | CE81: 5 | CF81: 5 | CG81: 5 | CH81: 5 | DK81: [D] | DL81: =VLOOKUP($F81,Activities!$A$9:$I$180,3,FALSE)/$AI81 -> 0.6 | DM81: =VLOOKUP($F81,Activities!$A$9:$I$180,4,FALSE)/$AI81 -> 0.6 | DN81: =VLOOKUP($F81,Activities!$A$9:$I$180,5,FALSE)/$AI81 -> 0.6 | DO81: =VLOOKUP($F81,Activities!$A$9:$I$180,6,FALSE)/$AI81 -> 0.6 | DP81: =VLOOKUP($F81,Activities!$A$9:$I$180,7,FALSE)/$AI81 -> 0.6 | DQ81: =VLOOKUP($F81,Activities!$A$9:$I$180,8,FALSE)/$AI81 -> 0.6 | DR81: =VLOOKUP($F81,Activities!$A$9:$I$180,9,FALSE)/$AI81 -> 0.6
A82: ICH01_29 | B82: Industrie | C82: Conversion | D82: Industry | E82: Chemicals | F82: Ethylene intermediate | G82: Existing naphtha steam cracker with 10% pyrolysis oil blending - Petrochemical industry | H82: [Mton_Ey/y] | I82: =I60 -> 1958.9385 | J82: =J60 -> 1958.9385 | K82: =K60 -> 1958.9385 | L82: =L60 -> 1958.9385 | M82: =M60 -> 1958.9385 | N82: =N60 -> 1958.9385 | O82: =O60 -> 1958.9385 | P82: 0 | Q82: =Q54 -> 77.581721 | R82: =R54 -> 77.581721 | S82: =S54 -> 77.581721 | T82: =T54 -> 77.581721 | U82: =U54 -> 77.581721 | V82: =V54 -> 77.581721 | W82: =W54 -> 77.581721 | X82: =X60 -> 0 | Y82: =Y60 -> 0 | Z82: =Z60 -> 0 | AA82: =AA60 -> 0 | AB82: =AB60 -> 0 | AC82: =AC60 -> 0 | AD82: =AD60 -> 0 | AE82: 0.08 | AF82: =AF60 -> 0 | AG82: =AG60 -> 25 | AH82: =AH60 -> 25 | AI82: 1 | AJ82: Operation | AK82: Flat | AY82: none | BN82: 0 | BU82: =IF(BL82=1,BN82,0) -> 0 | CC82: =CC54 -> 4 | CD82: =CD54 -> 4 | CE82: =CE54 -> 4 | CF82: =CF54 -> 4 | CG82: =CG54 -> 4 | CH82: =CH54 -> 4 | DK82: [103] | DL82: =VLOOKUP($F82,Activities!$A$9:$I$180,3,FALSE)/$AI82 -> 0 | DM82: =VLOOKUP($F82,Activities!$A$9:$I$180,4,FALSE)/$AI82 -> 0 | DN82: =VLOOKUP($F82,Activities!$A$9:$I$180,5,FALSE)/$AI82 -> 0 | DO82: =VLOOKUP($F82,Activities!$A$9:$I$180,6,FALSE)/$AI82 -> 0 | DP82: =VLOOKUP($F82,Activities!$A$9:$I$180,7,FALSE)/$AI82 -> 0 | DQ82: =VLOOKUP($F82,Activities!$A$9:$I$180,8,FALSE)/$AI82 -> 0 | DR82: =VLOOKUP($F82,Activities!$A$9:$I$180,9,FALSE)/$AI82 -> 0
A83: ICH01_30 | B83: Industrie | C83: Conversion | D83: Industry | E83: Chemicals | F83: Ethylene intermediate | G83: Existing naphtha steam cracker with 10% pyrolysis oil blending and CCUS - Petrochemical industry | H83: [Mton_Ey/y] | I83: =I61 -> 1939.543 | J83: =J61 -> 1939.543 | K83: =K61 -> 1939.543 | L83: =L61 -> 1939.543 | M83: =M61 -> 1939.543 | N83: =N61 -> 1939.543 | O83: =O61 -> 1939.543 | P83: 0 | Q83: =Q55 -> 86.400348 | R83: =R55 -> 86.400348 | S83: =S55 -> 86.400348 | T83: =T55 -> 86.400348 | U83: =U55 -> 86.400348 | V83: =V55 -> 86.400348 | W83: =W55 -> 86.400348 | X83: =X61 -> 0 | Y83: =Y61 -> 0 | Z83: =Z61 -> 0 | AA83: =AA61 -> 0 | AB83: =AB61 -> 0 | AC83: =AC61 -> 0 | AD83: =AD61 -> 0 | AE83: 0.08 | AF83: =AF61 -> 0 | AG83: =AG61 -> 25 | AH83: =AH61 -> 25 | AI83: 1 | AJ83: Operation | AK83: Flat | AY83: none | BN83: 0 | BU83: =IF(BL83=1,BN83,0) -> 0 | CC83: =CC55 -> 2 | CD83: =CD55 -> 4 | CE83: =CE55 -> 4 | CF83: =CF55 -> 4 | CG83: =CG55 -> 4 | CH83: =CH55 -> 4 | DK83: [103] | DL83: =VLOOKUP($F83,Activities!$A$9:$I$180,3,FALSE)/$AI83 -> 0 | DM83: =VLOOKUP($F83,Activities!$A$9:$I$180,4,FALSE)/$AI83 -> 0 | DN83: =VLOOKUP($F83,Activities!$A$9:$I$180,5,FALSE)/$AI83 -> 0 | DO83: =VLOOKUP($F83,Activities!$A$9:$I$180,6,FALSE)/$AI83 -> 0 | DP83: =VLOOKUP($F83,Activities!$A$9:$I$180,7,FALSE)/$AI83 -> 0 | DQ83: =VLOOKUP($F83,Activities!$A$9:$I$180,8,FALSE)/$AI83 -> 0 | DR83: =VLOOKUP($F83,Activities!$A$9:$I$180,9,FALSE)/$AI83 -> 0
A84: ICH01_31 | B84: Industrie | C84: Final | D84: Industry | E84: Chemicals | F84: Polyethylene terephthalate (PET) | G84: Polymerization to PET (BHET) | H84: [Mton_PET/y] | I84: =I79 -> 500.926 | J84: =J79 -> 500.926 | K84: =K79 -> 500.926 | L84: =L79 -> 500.926 | M84: =M79 -> 500.926 | N84: =N79 -> 500.926 | O84: =O79 -> 500.926 | P84: 0 | Q84: =Q79 -> 25.0463 | R84: =R79 -> 25.0463 | S84: =S79 -> 25.0463 | T84: =T79 -> 25.0463 | U84: =U79 -> 25.0463 | V84: =V79 -> 25.0463 | W84: =W79 -> 25.0463 | X84: =X79 -> 19.1844 | ... AD84: =AD79 -> 19.1844 | AE84: 0.08 | AF84: =AF79 -> 0 | AG84: =AG79 -> 25 | AH84: =AH79 -> 25 | AI84: =AI79 -> 1 | AJ84: =AJ79 -> Operation | AK84: =AK79 -> Flat | AY84: =AY79 -> none | BN84: =BN79 -> 0.3408 | BO84: =BO79 -> 0 | BP84: =BP79 -> 0 | BQ84: =BQ79 -> 0 | BR84: =BR79 -> 0.3408 | BS84: =BS79 -> 0 | BT84: =BT79 -> 0 | BU84: 0 | CB84: =CB79 -> 5 | CC84: =CC79 -> 5 | CD84: =CD79 -> 5 | CE84: =CE79 -> 5 | CF84: =CF79 -> 5 | CG84: =CG79 -> 5 | CH84: =CH79 -> 5 | DK84: =DK79 -> [D] | DL84: =VLOOKUP($F84,Activities!$A$9:$I$180,3,FALSE)/$AI84 -> 0 | DM84: =VLOOKUP($F84,Activities!$A$9:$I$180,4,FALSE)/$AI84 -> 0 | DN84: =VLOOKUP($F84,Activities!$A$9:$I$180,5,FALSE)/$AI84 -> 0 | DO84: =VLOOKUP($F84,Activities!$A$9:$I$180,6,FALSE)/$AI84 -> 0 | DP84: =VLOOKUP($F84,Activities!$A$9:$I$180,7,FALSE)/$AI84 -> 0 | DQ84: =VLOOKUP($F84,Activities!$A$9:$I$180,8,FALSE)/$AI84 -> 0 | DR84: =VLOOKUP($F84,Activities!$A$9:$I$180,9,FALSE)/$AI84 -> 0
A85: ICH01_32 | B85: Industrie | C85: Final | D85: Industry | E85: Chemicals | F85: Polyester production - Chemical Industry | G85: Dummy - conversion of PET to polyester | H85: [Mton_material/y] | I85: 0 | J85: 0 | K85: 0 | L85: 0 | M85: 0 | N85: 0 | O85: 0 | P85: 0 | Q85: 0 | R85: 0 | S85: 0 | T85: 0 | U85: 0 | V85: 0 | W85: 0 | X85: 0 | Y85: 0 | Z85: 0 | AA85: 0 | AB85: 0 | AC85: 0 | AD85: 0 | AE85: 0.08 | AG85: 25 | AH85: 25 | AI85: 1 | AJ85: Operation | AK85: Flat | AY85: none | BU85: 0 | CB85: 10 | CC85: 10 | CD85: 10 | CE85: 10 | CF85: 10 | CG85: 10 | CH85: 10 | DK85: [D] | DL85: =VLOOKUP($F85,Activities!$A$9:$I$180,3,FALSE)/$AI85 -> 0.3408 | DM85: =VLOOKUP($F85,Activities!$A$9:$I$180,4,FALSE)/$AI85 -> 0.3408 | DN85: =VLOOKUP($F85,Activities!$A$9:$I$180,5,FALSE)/$AI85 -> 0.3408 | DO85: =VLOOKUP($F85,Activities!$A$9:$I$180,6,FALSE)/$AI85 -> 0.3408 | DP85: =VLOOKUP($F85,Activities!$A$9:$I$180,7,FALSE)/$AI85 -> 0.3408 | DQ85: =VLOOKUP($F85,Activities!$A$9:$I$180,8,FALSE)/$AI85 -> 0.3408 | DR85: =VLOOKUP($F85,Activities!$A$9:$I$180,9,FALSE)/$AI85 -> 0.3408
A86: ICH01_33 | B86: Industrie | C86: Final | D86: Industry | E86: Chemicals | F86: Polyester production - Chemical Industry | G86: Dummy - conversion of bioplastics to polyester | H86: [Mton_material/y] | I86: 0 | J86: 0 | K86: 0 | L86: 0 | M86: 0 | N86: 0 | O86: 0 | P86: 0 | Q86: 0 | R86: 0 | S86: 0 | T86: 0 | U86: 0 | V86: 0 | W86: 0 | X86: 0 | Y86: 0 | Z86: 0 | AA86: 0 | AB86: 0 | AC86: 0 | AD86: 0 | AE86: 0.08 | AG86: 25 | AH86: 25 | AI86: 1 | AJ86: Operation | AK86: Flat | AY86: none | BU86: 0 | CB86: 10 | CC86: 10 | CD86: 10 | CE86: 10 | CF86: 10 | CG86: 10 | CH86: 10 | DK86: [D] | DL86: =VLOOKUP($F86,Activities!$A$9:$I$180,3,FALSE)/$AI86 -> 0.3408 | DM86: =VLOOKUP($F86,Activities!$A$9:$I$180,4,FALSE)/$AI86 -> 0.3408 | DN86: =VLOOKUP($F86,Activities!$A$9:$I$180,5,FALSE)/$AI86 -> 0.3408 | DO86: =VLOOKUP($F86,Activities!$A$9:$I$180,6,FALSE)/$AI86 -> 0.3408 | DP86: =VLOOKUP($F86,Activities!$A$9:$I$180,7,FALSE)/$AI86 -> 0.3408 | DQ86: =VLOOKUP($F86,Activities!$A$9:$I$180,8,FALSE)/$AI86 -> 0.3408 | DR86: =VLOOKUP($F86,Activities!$A$9:$I$180,9,FALSE)/$AI86 -> 0.3408
A87: ICH01_34 | B87: Industrie | C87: Conversion | D87: Industry | E87: Chemicals | F87: Ethylene oxide intermediate | G87: Ethylene oxide production | H87: [Mton_EO/y] | I87: =(75.9/0.305)/'Data Sources'!$I$7 -> 261.2522 | J87: =(75.9/0.305)/'Data Sources'!$I$7 -> 261.2522 | K87: =(75.9/0.305)/'Data Sources'!$I$7 -> 261.2522 | L87: =(75.9/0.305)/'Data Sources'!$I$7 -> 261.2522 | M87: =(75.9/0.305)/'Data Sources'!$I$7 -> 261.2522 | N87: =(75.9/0.305)/'Data Sources'!$I$7 -> 261.2522 | O87: =(75.9/0.305)/'Data Sources'!$I$7 -> 261.2522 | P87: 0 | Q87: =I87*0.05 -> 13.06261 | R87: =J87*0.05 -> 13.06261 | S87: =K87*0.05 -> 13.06261 | T87: =L87*0.05 -> 13.06261 | U87: =M87*0.05 -> 13.06261 | V87: =N87*0.05 -> 13.06261 | W87: =O87*0.05 -> 13.06261 | X87: 0 | Y87: 0 | Z87: 0 | AA87: 0 | AB87: 0 | AC87: 0 | AD87: 0 | AE87: 0.08 | AG87: 25 | AH87: 25 | AI87: 1 | AJ87: Operation | AK87: Flat | AY87: none | BN87: =DL87 -> 0 | BR87: =BN87 -> 0 | BU87: 0 | CB87: 10 | CC87: 10 | CD87: 10 | CE87: 10 | CF87: 10 | CG87: 10 | CH87: 10 | DL87: =VLOOKUP($F87,Activities!$A$9:$I$180,3,FALSE)/$AI87 -> 0 | DM87: =VLOOKUP($F87,Activities!$A$9:$I$180,4,FALSE)/$AI87 -> 0 | DN87: =VLOOKUP($F87,Activities!$A$9:$I$180,5,FALSE)/$AI87 -> 0 | DO87: =VLOOKUP($F87,Activities!$A$9:$I$180,6,FALSE)/$AI87 -> 0 | DP87: =VLOOKUP($F87,Activities!$A$9:$I$180,7,FALSE)/$AI87 -> 0 | DQ87: =VLOOKUP($F87,Activities!$A$9:$I$180,8,FALSE)/$AI87 -> 0 | DR87: =VLOOKUP($F87,Activities!$A$9:$I$180,9,FALSE)/$AI87 -> 0
A88: ICH01_35 | B88: Industrie | C88: Conversion | D88: Industry | E88: Chemicals | F88: Ethylene glycol | G88: Ethylene glycol production | H88: [Mton_EG/y] | I88: =(120.2/0.155)/'Data Sources'!$I$7 -> 814.12445 | J88: =(120.2/0.155)/'Data Sources'!$I$7 -> 814.12445 | K88: =(120.2/0.155)/'Data Sources'!$I$7 -> 814.12445 | L88: =(120.2/0.155)/'Data Sources'!$I$7 -> 814.12445 | M88: =(120.2/0.155)/'Data Sources'!$I$7 -> 814.12445 | N88: =(120.2/0.155)/'Data Sources'!$I$7 -> 814.12445 | O88: =(120.2/0.155)/'Data Sources'!$I$7 -> 814.12445 | P88: 0 | Q88: =I88*0.05 -> 40.706222 | R88: =J88*0.05 -> 40.706222 | S88: =K88*0.05 -> 40.706222 | T88: =L88*0.05 -> 40.706222 | U88: =M88*0.05 -> 40.706222 | V88: =N88*0.05 -> 40.706222 | W88: =O88*0.05 -> 40.706222 | X88: 0 | Y88: 0 | Z88: 0 | AA88: 0 | AB88: 0 | AC88: 0 | AD88: 0 | AE88: 0.08 | AG88: 25 | AH88: 25 | AI88: 1 | AJ88: Operation | AK88: Flat | AY88: none | BN88: =DL88 -> 0.155 | BR88: =BN88 -> 0.155 | BU88: 0 | CB88: 10 | CC88: 10 | CD88: 10 | CE88: 10 | CF88: 10 | CG88: 10 | CH88: 10 | DL88: 0.155 | DM88: 0.155 | DN88: 0.155 | DO88: 0.155 | DP88: 0.155 | DQ88: 0.155 | DR88: 0.155
A89: ICH01_36 | B89: Industrie | C89: Final | D89: Industry | E89: Chemicals | F89: Ethylene oxide production - Chemical Industry | G89: Dummy - conversion EO to final | H89: [Mton_EO/y] | I89: 0 | J89: 0 | K89: 0 | L89: 0 | M89: 0 | N89: 0 | O89: 0 | P89: 0 | Q89: 0 | R89: 0 | S89: 0 | T89: 0 | U89: 0 | V89: 0 | W89: 0 | X89: 0 | Y89: 0 | Z89: 0 | AA89: 0 | AB89: 0 | AC89: 0 | AD89: 0 | AE89: 0.08 | AG89: 25 | AH89: 25 | AI89: 1 | AJ89: Operation | AK89: Flat | AY89: none | BN89: =DL89 -> 0.1464 | BU89: 0 | CB89: 10 | CC89: 10 | CD89: 10 | CE89: 10 | CF89: 10 | CG89: 10 | CH89: 10 | DK89: [D] | DL89: =VLOOKUP($F89,Activities!$A$9:$I$180,3,FALSE)/$AI89 -> 0.1464 | DM89: =VLOOKUP($F89,Activities!$A$9:$I$180,4,FALSE)/$AI89 -> 0.1464 | DN89: =VLOOKUP($F89,Activities!$A$9:$I$180,5,FALSE)/$AI89 -> 0.1464 | DO89: =VLOOKUP($F89,Activities!$A$9:$I$180,6,FALSE)/$AI89 -> 0.1464 | DP89: =VLOOKUP($F89,Activities!$A$9:$I$180,7,FALSE)/$AI89 -> 0.1464 | DQ89: =VLOOKUP($F89,Activities!$A$9:$I$180,8,FALSE)/$AI89 -> 0.1464 | DR89: =VLOOKUP($F89,Activities!$A$9:$I$180,9,FALSE)/$AI89 -> 0.1464
A90: ICH01_37 | B90: Industrie | C90: Final | D90: Industry | E90: Chemicals | F90: BTX aromatics production - Chemical Industry | G90: Methanol to aromatics | H90: [Mton_BTX/y] | I90: =2.5*1.152 -> 2.88 | J90: =2.5*1.152 -> 2.88 | K90: =2.5*1.152 -> 2.88 | L90: =2.5*1.152 -> 2.88 | M90: =2.5*1.152 -> 2.88 | N90: =2.5*1.152 -> 2.88 | O90: =2.5*1.152 -> 2.88 | P90: 0 | Q90: =0.12*41.8 -> 5.016 | R90: =0.12*41.8 -> 5.016 | S90: =0.12*41.8 -> 5.016 | T90: =0.12*41.8 -> 5.016 | U90: =0.12*41.8 -> 5.016 | V90: =0.12*41.8 -> 5.016 | W90: =0.12*41.8 -> 5.016 | X90: 0 | Y90: 0 | Z90: 0 | AA90: 0 | AB90: 0 | AC90: 0 | AD90: 0 | AE90: 0.08 | AF90: 0 | AG90: 25 | AH90: 25 | AI90: 1 | AJ90: Operation | AK90: Flat | AY90: none | BN90: 0 | BU90: =IF(BL90=1,BN90,0) -> 0 | CB90: 1 | CC90: 1 | CD90: 5 | CE90: 5 | CF90: 5 | CG90: 5 | CH90: 5 | DK90: TNO 2024 | DL90: =VLOOKUP($F90,Activities!$A$9:$I$180,3,FALSE)/$AI90 -> 3 | DM90: =VLOOKUP($F90,Activities!$A$9:$I$180,4,FALSE)/$AI90 -> 3 | DN90: =VLOOKUP($F90,Activities!$A$9:$I$180,5,FALSE)/$AI90 -> 3 | DO90: =VLOOKUP($F90,Activities!$A$9:$I$180,6,FALSE)/$AI90 -> 3 | DP90: =VLOOKUP($F90,Activities!$A$9:$I$180,7,FALSE)/$AI90 -> 3 | DQ90: =VLOOKUP($F90,Activities!$A$9:$I$180,8,FALSE)/$AI90 -> 3 | DR90: =VLOOKUP($F90,Activities!$A$9:$I$180,9,FALSE)/$AI90 -> 3
A91: ICH01_38 | B91: Industrie | C91: Final | D91: Industry | E91: Chemicals | F91: BTX aromatics production - Chemical Industry | G91: Biomass to aromatics | H91: [Mton_BTX/y] | I91: 17.5 | J91: 17.5 | K91: 17.5 | L91: 17.5 | M91: 17.5 | N91: 17.5 | O91: 17.5 | P91: 0 | Q91: 0.88 | R91: 0.88 | S91: 0.88 | T91: 0.88 | U91: 0.88 | V91: 0.88 | W91: 0.88 | X91: 0 | Y91: 0 | Z91: 0 | AA91: 0 | AB91: 0 | AC91: 0 | AD91: 0 | AE91: 0.08 | AF91: 0 | AG91: 25 | AH91: 25 | AI91: 1 | AJ91: Operation | AK91: Flat | AY91: none | BN91: 0 | BU91: =IF(BL91=1,BN91,0) -> 0 | CB91: 1 | CC91: 1 | CD91: 5 | CE91: 5 | CF91: 5 | CG91: 5 | CH91: 5 | DK91: TNO 2024 | DL91: =VLOOKUP($F91,Activities!$A$9:$I$180,3,FALSE)/$AI91 -> 3 | DM91: =VLOOKUP($F91,Activities!$A$9:$I$180,4,FALSE)/$AI91 -> 3 | DN91: =VLOOKUP($F91,Activities!$A$9:$I$180,5,FALSE)/$AI91 -> 3 | DO91: =VLOOKUP($F91,Activities!$A$9:$I$180,6,FALSE)/$AI91 -> 3 | DP91: =VLOOKUP($F91,Activities!$A$9:$I$180,7,FALSE)/$AI91 -> 3 | DQ91: =VLOOKUP($F91,Activities!$A$9:$I$180,8,FALSE)/$AI91 -> 3 | DR91: =VLOOKUP($F91,Activities!$A$9:$I$180,9,FALSE)/$AI91 -> 3
A92: ICH01_39 | B92: Industrie | C92: Primary | D92: Material | E92: Chemicals | F92: BTX aromatics production - Chemical Industry | G92: Imported aromatics | H92: [Mton_BTX/y] | I92: 0 | J92: 0 | K92: 0 | L92: 0 | M92: 0 | N92: 0 | O92: 0 | P92: 0 | Q92: 0 | R92: 0 | S92: 0 | T92: 0 | U92: 0 | V92: 0 | W92: 0 | X92: 645.23538 | Y92: 599.0644 | Z92: 553.0589 | AA92: 553.0589 | AB92: 414.79417 | AC92: 398.49851 | AD92: 381.874 | AE92: 0.08 | AF92: 0 | AG92: 25 | AH92: 25 | AI92: 1 | AJ92: Operation | AK92: Flat | AY92: none | BN92: 0 | BU92: =IF(BL92=1,BN92,0) -> 0 | CB92: 6 | CC92: =CB92 -> 6 | CD92: =CC92 -> 6 | CE92: =CD92 -> 6 | CF92: =CE92 -> 6 | CG92: =CF92 -> 6 | CH92: =CG92 -> 6 | DK92: [D] | DL92: =VLOOKUP($F92,Activities!$A$9:$I$180,3,FALSE)/$AI92 -> 3 | DM92: =VLOOKUP($F92,Activities!$A$9:$I$180,4,FALSE)/$AI92 -> 3 | DN92: =VLOOKUP($F92,Activities!$A$9:$I$180,5,FALSE)/$AI92 -> 3 | DO92: =VLOOKUP($F92,Activities!$A$9:$I$180,6,FALSE)/$AI92 -> 3 | DP92: =VLOOKUP($F92,Activities!$A$9:$I$180,7,FALSE)/$AI92 -> 3 | DQ92: =VLOOKUP($F92,Activities!$A$9:$I$180,8,FALSE)/$AI92 -> 3 | DR92: =VLOOKUP($F92,Activities!$A$9:$I$180,9,FALSE)/$AI92 -> 3
A93: ICH01_40 | B93: Industrie | C93: Conversion | D93: Industry | E93: Chemicals | F93: Ethylene intermediate | G93: CO2 electrolysis | H93: [Mton_Ey/y] | I93: 1335.6864 | J93: 1335.6864 | K93: 1335.6864 | L93: 1335.6864 | M93: 1335.6864 | N93: 1335.6864 | O93: 1335.6864 | Q93: 26.713728 | R93: 26.713728 | S93: 26.713728 | T93: 26.713728 | U93: 26.713728 | V93: 26.713728 | W93: 26.713728 | X93: 0 | Y93: 0 | Z93: 0 | AA93: 0 | AB93: 0 | AC93: 0 | AD93: 0 | AE93: 0.08 | AG93: 25 | AH93: 25 | AI93: 1 | AJ93: Operation | AK93: Flat | AY93: none | BU93: 0 | CB93: 0 | CC93: 0 | CF93: =CF65 -> 4 | CG93: =CG65 -> 4 | CH93: =CH65 -> 4 | DK93: [103]
A94: ICH01_41 | B94: Industrie | C94: Conversion | D94: Industry | E94: Chemicals | F94: Propylene intermediate | G94: Propylene from PDH alkenation of Bio LPG - Petrochemicals | H94: [Mton_Py/y] | I94: 1180.5315 | J94: 1180.5315 | K94: 1180.5315 | L94: 1180.5315 | M94: 1180.5315 | N94: 1180.5315 | O94: 1180.5315 | P94: 0 | Q94: 53.123919 | R94: 53.123919 | S94: 53.123919 | T94: 53.123919 | U94: 53.123919 | V94: 53.123919 | W94: 53.123919 | X94: 0 | Y94: 0 | Z94: 0 | AA94: 0 | AB94: 0 | AC94: 0 | AD94: 0 | AE94: 0.08 | AG94: 25 | AH94: 25 | AI94: 1 | AJ94: Operation | AK94: Flat | AY94: none | BN94: 0.12 | BP94: 0.12 | BU94: =IF(BL94=1,BN94,0) -> 0 | CB94: 1 | CC94: 1 | CD94: 1 | CE94: 1 | CF94: 1 | CG94: 1 | CH94: 1 | DK94: [103] | DL94: =VLOOKUP($F94,Activities!$A$9:$I$180,3,FALSE)/$AI94 -> 0 | DM94: =VLOOKUP($F94,Activities!$A$9:$I$180,4,FALSE)/$AI94 -> 0 | DN94: =VLOOKUP($F94,Activities!$A$9:$I$180,5,FALSE)/$AI94 -> 0 | DO94: =VLOOKUP($F94,Activities!$A$9:$I$180,6,FALSE)/$AI94 -> 0 | DP94: =VLOOKUP($F94,Activities!$A$9:$I$180,7,FALSE)/$AI94 -> 0 | DQ94: =VLOOKUP($F94,Activities!$A$9:$I$180,8,FALSE)/$AI94 -> 0 | DR94: =VLOOKUP($F94,Activities!$A$9:$I$180,9,FALSE)/$AI94 -> 0
A95: ICH01_42 | B95: Industrie | C95: Conversion | D95: Industry | E95: Chemicals | F95: Ethylene intermediate | G95: Existing bionaphtha steam cracker - Petrochemical industry | H95: [Mton_Ey/y] | I95: 1939.543 | J95: 1939.543 | K95: 1939.543 | L95: 1939.543 | M95: 1939.543 | N95: 1939.543 | O95: 1939.543 | P95: 0 | Q95: 77.581721 | R95: 77.581721 | S95: 77.581721 | T95: 77.581721 | U95: 77.581721 | V95: 77.581721 | W95: 77.581721 | X95: 0 | Y95: 0 | Z95: 0 | AA95: 0 | AB95: 0 | AC95: 0 | AD95: 0 | AE95: 0.08 | AF95: 0 | AG95: 25 | AH95: 25 | AI95: 1 | AJ95: Operation | AK95: Flat | AY95: none | CC95: 4 | CD95: 4 | CE95: 4 | CF95: 4 | CG95: 4 | CH95: 4
A96: ICB01_01 | B96: Industrie | C96: Conversion | D96: Industry | E96: Chemicals | F96: Bioplastics (PEF, PLA) | G96: Bioplastics from hydrolisis, fermenation and furfularization - Bioplastics | H96: [Mton_BP/y] | I96: =(844+3558)/2 -> 2201 | J96: =I96 -> 2201 | K96: =J96 -> 2201 | L96: =K96 -> 2201 | M96: =L96 -> 2201 | N96: =M96 -> 2201 | O96: =N96 -> 2201 | P96: 0 | Q96: =I96*0.05 -> 110.05 | R96: =J96*0.05 -> 110.05 | S96: =K96*0.05 -> 110.05 | T96: =L96*0.05 -> 110.05 | U96: =M96*0.05 -> 110.05 | V96: =N96*0.05 -> 110.05 | W96: =O96*0.05 -> 110.05 | X96: 0 | Y96: 0 | Z96: 0 | AA96: 0 | AB96: 0 | AC96: 0 | AD96: 0 | AE96: 0.08 | AG96: 30 | AH96: 30 | AI96: 1 | AJ96: Operation | AK96: Flat | AY96: none | BN96: 0 | BU96: =IF(BL96=1,BN96,0) -> 0 | CB96: 5 | CC96: 5 | CD96: 5 | CE96: 5 | CF96: 5 | CG96: 5 | CH96: 5 | DK96: [68] | DL96: =VLOOKUP($F96,Activities!$A$9:$I$180,3,FALSE)/$AI96 -> 0 | DM96: =VLOOKUP($F96,Activities!$A$9:$I$180,4,FALSE)/$AI96 -> 0 | DN96: =VLOOKUP($F96,Activities!$A$9:$I$180,5,FALSE)/$AI96 -> 0 | DO96: =VLOOKUP($F96,Activities!$A$9:$I$180,6,FALSE)/$AI96 -> 0 | DP96: =VLOOKUP($F96,Activities!$A$9:$I$180,7,FALSE)/$AI96 -> 0 | DQ96: =VLOOKUP($F96,Activities!$A$9:$I$180,8,FALSE)/$AI96 -> 0 | DR96: =VLOOKUP($F96,Activities!$A$9:$I$180,9,FALSE)/$AI96 -> 0
A97: ICL01_01 | B97: Industrie | C97: Conversion | D97: Industry | E97: Chemicals | F97: Chlorine intermediate | G97: Chlor - alkali finite gap brine electrolysis - Chlorine production | H97: [Mton_Cl2/y] | I97: =411.1/0.8 -> 513.875 | J97: =411.1/0.8 -> 513.875 | K97: =411.1/0.8 -> 513.875 | L97: =411.1/0.8 -> 513.875 | M97: =411.1/0.8 -> 513.875 | N97: =411.1/0.8 -> 513.875 | O97: =411.1/0.8 -> 513.875 | P97: 0 | Q97: =I97*0.05 -> 25.69375 | R97: =J97*0.05 -> 25.69375 | S97: =K97*0.05 -> 25.69375 | T97: =L97*0.05 -> 25.69375 | U97: =M97*0.05 -> 25.69375 | V97: =N97*0.05 -> 25.69375 | W97: =O97*0.05 -> 25.69375 | AE97: 0.08 | AF97: 0 | AG97: 30 | AH97: 30 | AI97: 1 | AJ97: Shedding | AK97: Flat | AS97: 0.2 | AT97: 0.2 | AU97: 1 hour [h] | AY97: none | BN97: 2 | BP97: 1 | BU97: =IF(BL97=1,BN97,0) -> 0 | CB97: 5 | CC97: 5 | CD97: 5 | CE97: 5 | CF97: 5 | CG97: 5 | CH97: 5 | DK97: [56][106] | DL97: =VLOOKUP($F97,Activities!$A$9:$I$180,3,FALSE)/$AI97 -> 0 | DM97: =VLOOKUP($F97,Activities!$A$9:$I$180,4,FALSE)/$AI97 -> 0 | DN97: =VLOOKUP($F97,Activities!$A$9:$I$180,5,FALSE)/$AI97 -> 0 | DO97: =VLOOKUP($F97,Activities!$A$9:$I$180,6,FALSE)/$AI97 -> 0 | DP97: =VLOOKUP($F97,Activities!$A$9:$I$180,7,FALSE)/$AI97 -> 0 | DQ97: =VLOOKUP($F97,Activities!$A$9:$I$180,8,FALSE)/$AI97 -> 0 | DR97: =VLOOKUP($F97,Activities!$A$9:$I$180,9,FALSE)/$AI97 -> 0
A98: ICL01_02 | B98: Industrie | C98: Final | D98: Industry | E98: Chemicals | F98: Chlorine production - Chemical Industry | G98: Dummy - conversion of chlorine to final product | H98: [Mton_Cl2/y] | I98: 0 | J98: 0 | K98: 0 | L98: 0 | M98: 0 | N98: 0 | O98: 0 | P98: 0 | Q98: 0 | R98: 0 | S98: 0 | T98: 0 | U98: 0 | V98: 0 | W98: 0 | X98: 0 | Y98: 0 | Z98: 0 | AA98: 0 | AB98: 0 | AC98: 0 | AD98: 0 | AE98: 0.08 | AG98: 25 | AH98: 25 | AI98: 1 | AJ98: Operation | AK98: Flat | AY98: none | BN98: =DL98 -> 1 | BP98: 1 | BU98: 0 | CB98: 10 | CC98: =DM98 -> 1 | CD98: =DN98 -> 1 | CE98: =DO98 -> 1 | CF98: =DP98 -> 1 | CG98: =DQ98 -> 1 | CH98: =DR98 -> 1 | DK98: [D] | DL98: =VLOOKUP($F98,Activities!$A$9:$I$180,3,FALSE)/$AI98 -> 1 | DM98: =VLOOKUP($F98,Activities!$A$9:$I$180,4,FALSE)/$AI98 -> 1 | DN98: =VLOOKUP($F98,Activities!$A$9:$I$180,5,FALSE)/$AI98 -> 1 | DO98: =VLOOKUP($F98,Activities!$A$9:$I$180,6,FALSE)/$AI98 -> 1 | DP98: =VLOOKUP($F98,Activities!$A$9:$I$180,7,FALSE)/$AI98 -> 1 | DQ98: =VLOOKUP($F98,Activities!$A$9:$I$180,8,FALSE)/$AI98 -> 1 | DR98: =VLOOKUP($F98,Activities!$A$9:$I$180,9,FALSE)/$AI98 -> 1
A99: ICL01_03 | B99: Industrie | C99: Conversion | D99: Industry | E99: Chemicals | F99: Chlorine intermediate | G99: Chlor - alkali zero-gap brine electrolysis - Chlorine production | H99: [Mton_Cl2/y] | I99: =I97 -> 513.875 | J99: =J97 -> 513.875 | K99: =K97 -> 513.875 | L99: =L97 -> 513.875 | M99: =M97 -> 513.875 | N99: =N97 -> 513.875 | O99: =O97 -> 513.875 | P99: =P97 -> 0 | ... AH99: =AH97 -> 30 | AI99: 1 | AJ99: Shedding | AK99: Flat | AS99: 0.2 | AT99: 0.2 | AU99: 1 hour [h] | AY99: none | BU99: 0 | CC99: 5 | CD99: 5 | CE99: 5 | CF99: 5 | CG99: 5 | CH99: 5 | DK99: [56][106]
A100: IOC01_01 | B100: Industrie | C100: Final | D100: Industry | E100: Chemicals | F100: Other ETS chemicals - Chemical Industry | G100: Reference remaining chemicals - Other ETS chemicals | H100: [Idx_2020/y] | I100: =5360-SUM(I71*Activities!C26,Technologies!I72*Activities!C27,Technologies!I73*Activities!C28,Technologies!I74*Activities!C29,Technologies!I78*Activities!C30,Technologies!I79*Activities!C32,Technologies!I80*Activities!C31) -> 3451.7064 | J100: =5360-SUM(J71*Activities!D26,Technologies!J72*Activities!D27,Technologies!J73*Activities!D28,Technologies!J74*Activities!D29,Technologies!J78*Activities!D30,Technologies!J79*Activities!D32,Technologies!J80*Activities!D31) -> 3451.7064 | K100: =5360-SUM(K71*Activities!E26,Technologies!K72*Activities!E27,Technologies!K73*Activities!E28,Technologies!K74*Activities!E29,Technologies!K78*Activities!E30,Technologies!K79*Activities!E32,Technologies!K80*Activities!E31) -> 3451.7064 | L100: =5360-SUM(L71*Activities!F26,Technologies!L72*Activities!F27,Technologies!L73*Activities!F28,Technologies!L74*Activities!F29,Technologies!L78*Activities!F30,Technologies!L79*Activities!F32,Technologies!L80*Activities!F31) -> 3451.7064 | M100: =5360-SUM(M71*Activities!G26,Technologies!M72*Activities!G27,Technologies!M73*Activities!G28,Technologies!M74*Activities!G29,Technologies!M78*Activities!G30,Technologies!M79*Activities!G32,Technologies!M80*Activities!G31) -> 3451.7064 | N100: =5360-SUM(N71*Activities!H26,Technologies!N72*Activities!H27,Technologies!N73*Activities!H28,Technologies!N74*Activities!H29,Technologies!N78*Activities!H30,Technologies!N79*Activities!H32,Technologies!N80*Activities!H31) -> 3451.7064 | O100: =5360-SUM(O71*Activities!I26,Technologies!O72*Activities!I27,Technologies!O73*Activities!I28,Technologies!O74*Activities!I29,Technologies!O78*Activities!I30,Technologies!O79*Activities!I32,Technologies!O80*Activities!I31) -> 3451.7064 | P100: 0 | Q100: 161 | R100: 161 | S100: 161 | T100: 161 | U100: 161 | V100: 161 | W100: 161 | X100: 0 | Y100: 0 | Z100: 0 | AA100: 0 | AB100: 0 | AC100: 0 | AD100: 0 | AE100: 0.08 | AF100: 0 | AG100: 30 | AH100: 30 | AI100: 1 | AJ100: Operation | AK100: Flat | AY100: none | BN100: =DL100 -> 1 | BO100: 0.25 | BP100: 0.25 | BQ100: 0.25 | BR100: 0.25 | BU100: =IF(BL100=1,BN100,0) -> 0 | CB100: =DL100 -> 1 | CC100: =DM100 -> 1 | CD100: =DN100 -> 1 | CE100: =DO100 -> 1 | CF100: =DP100 -> 1 | CG100: =DQ100 -> 1 | CH100: 1 | DK100: [12],[36] | DL100: =VLOOKUP($F100,Activities!$A$9:$I$180,3,FALSE)/$AI100 -> 1 | DM100: =VLOOKUP($F100,Activities!$A$9:$I$180,4,FALSE)/$AI100 -> 1 | DN100: =VLOOKUP($F100,Activities!$A$9:$I$180,5,FALSE)/$AI100 -> 1 | DO100: =VLOOKUP($F100,Activities!$A$9:$I$180,6,FALSE)/$AI100 -> 1 | DP100: =VLOOKUP($F100,Activities!$A$9:$I$180,7,FALSE)/$AI100 -> 1 | DQ100: =VLOOKUP($F100,Activities!$A$9:$I$180,8,FALSE)/$AI100 -> 1 | DR100: =VLOOKUP($F100,Activities!$A$9:$I$180,9,FALSE)/$AI100 -> 1
A101: IOC01_02 | B101: Industrie | C101: Final | D101: Industry | E101: Chemicals | F101: Other ETS chemicals - Chemical Industry | G101: Improved remaining chemicals (bio feedstock) - Other ETS chemicals | H101: [Idx_2020/y] | I101: =I100/5360*7360 -> 4739.6566 | J101: =J100/5360*7360 -> 4739.6566 | K101: =K100/5360*7360 -> 4739.6566 | L101: =L100/5360*7360 -> 4739.6566 | M101: =M100/5360*7360 -> 4739.6566 | N101: =N100/5360*7360 -> 4739.6566 | O101: =O100/5360*7360 -> 4739.6566 | P101: 0 | Q101: 221 | R101: 221 | S101: 221 | T101: 221 | U101: 221 | V101: 221 | W101: 221 | X101: 0 | Y101: 0 | Z101: 0 | AA101: 0 | AB101: 0 | AC101: 0 | AD101: 0 | AE101: 0.08 | AF101: 0 | AG101: 30 | AH101: 30 | AI101: 1 | AJ101: Operation | AK101: Flat | AY101: none | BN101: 0 | BU101: =IF(BL101=1,BN101,0) -> 0 | CC101: =DM101 -> 1 | CD101: =DN101 -> 1 | CE101: =DO101 -> 1 | CF101: =DP101 -> 1 | CG101: =DQ101 -> 1 | CH101: =DR101 -> 1 | DK101: [12] | DL101: =VLOOKUP($F101,Activities!$A$9:$I$180,3,FALSE)/$AI101 -> 1 | DM101: =VLOOKUP($F101,Activities!$A$9:$I$180,4,FALSE)/$AI101 -> 1 | DN101: =VLOOKUP($F101,Activities!$A$9:$I$180,5,FALSE)/$AI101 -> 1 | DO101: =VLOOKUP($F101,Activities!$A$9:$I$180,6,FALSE)/$AI101 -> 1 | DP101: =VLOOKUP($F101,Activities!$A$9:$I$180,7,FALSE)/$AI101 -> 1 | DQ101: =VLOOKUP($F101,Activities!$A$9:$I$180,8,FALSE)/$AI101 -> 1 | DR101: =VLOOKUP($F101,Activities!$A$9:$I$180,9,FALSE)/$AI101 -> 1
...

Sheet EnergyBalance
A2: Tech. Specifics | P2: Data source | Q2: Activity Balances - Activity Balances - Activity Balances - Activity Balances - Activity Balances - Activity Balances - Activity Balances - Activity Balances - Activity Balances - Activity Balances - Activity Balances - Activity Balances - Activity Balances - Activity Balances - Activity Balances - Activity Balances - Activity Balances - Activity Balances - Activity Balances - Activity Balances - Activity Balances - Activity Balances - Activity Balances - Activity Balances - Activity Balances - Activity Balances - Activity Balances - Activity Balances - Activity Balances - Activity Balances - Activity Balances - Activity Balances - Activity Balances - Activity Balances - Activity Balances - Activity Balances - Activity Balances - Activity Balances - Activity Balances - Activity Balances - Activity Balances - Activity Balances - Activity Balances - Activity Balances - Activity Balances - Activity Balances - Activity Balances - Activity Balances - Activity Balances - Activity Balances - Activity Balances - Activity Balances - Activity Balances - Activity Balances - Activity Balances - Activity Balances - Activity Balances - Activity Balances - Activity Balances - Activity Balances - Activity Balances - Activity Balances - Activity Balances - Activity Balances - Activity Balances - Activity Balances - Activity Balances - Activity Balances - Activity Balances - Activity Balances - Activity Balances - Activity Balances - Activity Balances - Activity Balances - Activity Balances - Activity Balances - Activity Balances - Activity Balances - Activity Balances - Activity Balances - Activity Balances - Activity Balances - Activity Balances - Activity Balances - Activity Balances - Activity Balances - Activity Balances - Activity Balances - Activity Balances - Activity Balances - Activity Balances - Activity Balances - Activity Balances - Activity Balances - Activity Balances - Activity Balances - Activity Balances - Activity Balances - Activity Balances - Activity Balances - Activity Balances - Activity Balances - Activity Balances - Activity Balances - Activity Balances - Activity Balances - Activity Balances - Activity Balances - Activity Balances - Activity Balances - Activity Balances - Activity Balances - Activity Balances - Activity Balances - Activity Balances - Activity Balances - Activity Balances - Activity Balances - Activity Balances - Activity Balances - Activity Balances - Activity Balances - Activity Balances - Activity Balances - Activity Balances - Activity Balances - Activity Balances - Activity Balances - Activity Balances - Activity Balances - Activity Balances - Activity Balances
A3: Tech_ID | B3: Policy Sectors | C3: Category | D3: Sector | E3: Main Activity | F3: Name | G3: CO2 Removal | H3: CO2 used from CCUS network | I3: Accounted Embodied CO2 | J3: Feedstock Carbon | K3: Other ETS emission (process emission) | L3: Other non-ETS emission forms | M3: ETS status | N3: Emission node | O3: International emissions | Q3: Electricity demand - Residential | R3: Houses - Residential Flats | S3: Houses - Residential Terrace | T3: Houses - Residential Dwellings | U3: Electricity demand - Services | V3: Space - Services | W3: Electricity demand - Agricuture | X3: Heat demand - Agriculture | Y3: Machinery - Agriculture | Z3: Steel production - Basic Metals Industry | AA3: Nitric Acid production - Fertilizers Industry | AB3: Urea production - Fertilizers Industry | AC3: Other Ammonia based fertilizers - Fertilizers Industry | AD3: Ethylene production - Chemical Industry | AE3: Propylene production - Chemical Industry | AF3: Butadiene production - Chemical Industry | AG3: BTX aromatics production - Chemical Industry | AH3: LDPE production - Chemical Industry | AI3: LLDPE production - Chemical Industry | AJ3: HDPE production - Chemical Industry | AK3: Polypropylene production - Chemical Industry | AL3: PTA production - Chemical Industry | AM3: PVC production - Chemical Industry | AN3: Polyester production - Chemical Industry | AO3: Ethylene oxide production - Chemical Industry | AP3: Chlorine production - Chemical Industry | AQ3: Other ETS chemicals - Chemical Industry | AR3: Glass production - ETS Industry | AS3: Ceramics production -ETS Industry | AT3: Paper production - ETS Industry | AU3: Board production - ETS Industry | AV3: Food production - non-ETS Industry | AW3: Other ETS - Industry | AX3: Other non-ETS - Industry | AY3: Machinery - Industry | AZ3: Waste Management | BA3: Motorcycles | BB3: Passenger Cars | BC3: Light-Duty Vehicles | BD3: Heavy-Duty Vehicles | BE3: Buses | BF3: Rail | BG3: Domestic Navigation | BH3: Other Transport | BI3: Bunker Navigation | BJ3: Bunker Aviation | BK3: neGHG - Residential - CO2 | BL3: neGHG - Services - CH4 | BM3: neGHG - Agriculture - CO2 | BN3: neGHG - Agriculture - CH4 | BO3: neGHG - Agriculture - N2O | BP3: neGHG - Industry - Chemical - CO2 | BQ3: neGHG - Industry - Other - CO2 | BR3: neGHG - Industry - CH4 | BS3: neGHG - Industry - N2O | BT3: neGHG - Industry - F-gas | BU3: neGHG - Transport - CH4 | BV3: neGHG - Transport - N2O | BW3: neGHG - Transport - F-gas | BX3: neGHG - LULUCF | BY3: Natural Gas Exports | BZ3: Naphtha Exports | CA3: Road Fuel Exports | CB3: Kerosene Exports | CC3: Electricity demand - EU | CD3: Concrete demand | CE3: Salt production | CF3: End-of-life concrete | CG3: Sand | CH3: Gravel/aggregate | CI3: Cement | CJ3: End-of-life ceramic | CK3: Supplementary cementitious material (SCM) | CL3: Extracted salt | CM3: Clay | CN3: Recycled glass | CO3: DRI | CP3: Steel scrap | CQ3: Iron ore | CR3: Limestone | CS3: Ethylene intermediate | CT3: Propylene intermediate | CU3: PTA intermediate | CV3: Chlorine intermediate | CW3: Polyethylene terephthalate (PET) | CX3: Bioplastics (PEF, PLA) | CY3: BHET | CZ3: Ethylene oxide intermediate | DA3: Ethylene glycol | DB3: Sorted polyethylene | DC3: Sorted polypropylene | DD3: Sorted PET | DE3: Sorted PVC | DF3: Electricity EU | DG3: Electricity NL - HVNS | DH3: Electricity NL - HV | DI3: Electricity NL - LV | DJ3: Heat LT Houses C-G | DK3: Heat LT Houses A+,A,B | DL3: Heat LT Services | DM3: Heat LT Network | DN3: Heat LT Agriculture | DO3: Heat HT Industry | DP3: Heat LT Industry | DQ3: Furnace Heat Industry | DR3: Blast Furnace Gas | DS3: LPG | DT3: Naphtha | DU3: Road Fuel | DV3: Kerosene | DW3: Fuel Oil | DX3: Other Oil Products | DY3: Bio Naphtha | DZ3: Bio Ethanol | EA3: Bio Diesel | EB3: Bio Kerosene | EC3: Bio LPG | ED3: Syn Naphtha | EE3: Syn Diesel | EF3: Syn Kerosene | EG3: Syngas | EH3: E-Kerosene | EI3: Methanol | EJ3: Natural Gas HD | EK3: Natural Gas LD | EL3: Natural Gas LNG | EM3: Hydrogen HD | EN3: Hydrogen LD | EO3: Renewable H2 Credit | EP3: Plastic pyrolysis oil | EQ3: Ammonia | ER3: Biomass | ES3: Coal | ET3: Crude Oil | EU3: National Natural Gas | EV3: Uranium | EW3: Municipal Waste | EX3: Mixed Plastic Waste | EY3: Waste for incineration | EZ3: Residual Plastic Waste | FA3: Wood | FB3: Grasscrops | FC3: Dry organic matter | FD3: Wet organic matter | FE3: Manure | FF3: Sugars | FG3: Starch | FH3: Vegetable Oil | FI3: Biomethane | FJ3: Wind Energy | FK3: Solar Energy | FL3: Ambient Energy | FM3: Geothermal Energy | FN3: Solar Heat | FO3: Emitted neGHG - Residential - CO2 | FP3: Emitted neGHG - Services - CH4 | FQ3: Emitted neGHG - Agriculture - CO2 | FR3: Emitted neGHG - Agriculture - CH4 | FS3: Emitted neGHG - Agriculture - N2O | FT3: Emitted neGHG - Industry - CO2 | FU3: Emitted neGHG - Industry - CH4 | FV3: Emitted neGHG - Industry - N2O | FW3: Emitted neGHG - Industry - F-gas | FX3: Emitted neGHG - Transport - CH4 | FY3: Emitted neGHG - Transport - N2O | FZ3: Emitted neGHG - Transport - F-gas | GA3: Emitted neGHG - LULUCF - CO2 | GB3: Renewable CO2 Credit | GC3: CO2 CCUS Network | GD3: CO2 Air ETS | GE3: CO2 Air n-ETS | GF3: CO2 Air Int. Transport | GG3: CO2 Air Feedstock end of lifetime
I4: FORMULA! | J4: FORMULA! | Q4: =IFERROR(VLOOKUP(Q3,Activities!$A$9:$Q$180,16,FALSE)*(1),"") | R4: =IFERROR(VLOOKUP(R3,Activities!$A$9:$Q$180,16,FALSE)*(1),"") | S4: =IFERROR(VLOOKUP(S3,Activities!$A$9:$Q$180,16,FALSE)*(1),"") | T4: =IFERROR(VLOOKUP(T3,Activities!$A$9:$Q$180,16,FALSE)*(1),"") | U4: =IFERROR(VLOOKUP(U3,Activities!$A$9:$Q$180,16,FALSE)*(1),"") | V4: =IFERROR(VLOOKUP(V3,Activities!$A$9:$Q$180,16,FALSE)*(1),"") | W4: =IFERROR(VLOOKUP(W3,Activities!$A$9:$Q$180,16,FALSE)*(1),"") | X4: =IFERROR(VLOOKUP(X3,Activities!$A$9:$Q$180,16,FALSE)*(1),"") | ... AG4: =IFERROR(VLOOKUP(AG3,Activities!$A$9:$Q$180,16,FALSE)*(1),"") | AP4: =IFERROR(VLOOKUP(AP3,Activities!$A$9:$Q$180,16,FALSE)*(1),"") | AQ4: =IFERROR(VLOOKUP(AQ3,Activities!$A$9:$Q$180,16,FALSE)*(1),"") | AR4: =IFERROR(VLOOKUP(AR3,Activities!$A$9:$Q$180,16,FALSE)*(1),"") | AS4: =IFERROR(VLOOKUP(AS3,Activities!$A$9:$Q$180,16,FALSE)*(1),"") | AT4: =IFERROR(VLOOKUP(AT3,Activities!$A$9:$Q$180,16,FALSE)*(1),"") | AU4: =IFERROR(VLOOKUP(AU3,Activities!$A$9:$Q$180,16,FALSE)*(1),"") | AV4: =IFERROR(VLOOKUP(AV3,Activities!$A$9:$Q$180,16,FALSE)*(1),"") | AW4: =IFERROR(VLOOKUP(AW3,Activities!$A$9:$Q$180,16,FALSE)*(1),"") | ... CP4: =IFERROR(VLOOKUP(CP3,Activities!$A$9:$Q$180,16,FALSE)*(1),"") | DF4: =IFERROR(VLOOKUP(DF3,Activities!$A$9:$Q$180,16,FALSE)*(1),"") | DG4: =IFERROR(VLOOKUP(DG3,Activities!$A$9:$Q$180,16,FALSE)*(1),"") | DH4: =IFERROR(VLOOKUP(DH3,Activities!$A$9:$Q$180,16,FALSE)*(1),"") | DI4: =IFERROR(VLOOKUP(DI3,Activities!$A$9:$Q$180,16,FALSE)*(1),"") | DJ4: =IFERROR(VLOOKUP(DJ3,Activities!$A$9:$Q$180,16,FALSE)*(1),"") | DK4: =IFERROR(VLOOKUP(DK3,Activities!$A$9:$Q$180,16,FALSE)*(1),"") | DL4: =IFERROR(VLOOKUP(DL3,Activities!$A$9:$Q$180,16,FALSE)*(1),"") | DM4: =IFERROR(VLOOKUP(DM3,Activities!$A$9:$Q$180,16,FALSE)*(1),"") | ... GB4: =IFERROR(VLOOKUP(GB3,Activities!$A$9:$Q$180,16,FALSE)*(1),"") | GC4: NL | GD4: NL | GE4: NL | GF4: NL | GG4: NL
G5: no AIMMS | H5: no AIMMS | I5: no AIMMS | J5: no AIMMS | K5: no AIMMS | L5: no AIMMS | M5: no AIMMS | N5: no AIMMS | O5: no AIMMS | Q5: =IFERROR(VLOOKUP(Q3,Activities!$A$9:$Q$180,16,FALSE)*(1-VLOOKUP(Q3,Activities!$A$9:$Q$180,17,FALSE)),"") | R5: =IFERROR(VLOOKUP(R3,Activities!$A$9:$Q$180,16,FALSE)*(1-VLOOKUP(R3,Activities!$A$9:$Q$180,17,FALSE)),"") | S5: =IFERROR(VLOOKUP(S3,Activities!$A$9:$Q$180,16,FALSE)*(1-VLOOKUP(S3,Activities!$A$9:$Q$180,17,FALSE)),"") | T5: =IFERROR(VLOOKUP(T3,Activities!$A$9:$Q$180,16,FALSE)*(1-VLOOKUP(T3,Activities!$A$9:$Q$180,17,FALSE)),"") | U5: =IFERROR(VLOOKUP(U3,Activities!$A$9:$Q$180,16,FALSE)*(1-VLOOKUP(U3,Activities!$A$9:$Q$180,17,FALSE)),"") | V5: =IFERROR(VLOOKUP(V3,Activities!$A$9:$Q$180,16,FALSE)*(1-VLOOKUP(V3,Activities!$A$9:$Q$180,17,FALSE)),"") | W5: =IFERROR(VLOOKUP(W3,Activities!$A$9:$Q$180,16,FALSE)*(1-VLOOKUP(W3,Activities!$A$9:$Q$180,17,FALSE)),"") | X5: =IFERROR(VLOOKUP(X3,Activities!$A$9:$Q$180,16,FALSE)*(1-VLOOKUP(X3,Activities!$A$9:$Q$180,17,FALSE)),"") | ... GB5: =IFERROR(VLOOKUP(GB3,Activities!$A$9:$Q$180,16,FALSE)*(1-VLOOKUP(GB3,Activities!$A$9:$Q$180,17,FALSE)),"")
G6: [%] | H6: [Mton_CO2/UoA] | I6: [Mton_CO2/UoA] | J6: [Mton_CO2/UoA] | K6: [Mton_CO2/UoA] | L6: [Mton_CO2/UoA] | M6: [t/f] | N6: [node] | O6: [%] | P6: [ref No.] | Q6: =VLOOKUP(Q3,Activities!$A$9:$Q$227,2,FALSE) -> [PJ] | R6: =VLOOKUP(R3,Activities!$A$9:$Q$227,2,FALSE) -> [khouses] | S6: =VLOOKUP(S3,Activities!$A$9:$Q$227,2,FALSE) -> [khouses] | T6: =VLOOKUP(T3,Activities!$A$9:$Q$227,2,FALSE) -> [khouses] | U6: =VLOOKUP(U3,Activities!$A$9:$Q$227,2,FALSE) -> [PJ] | V6: =VLOOKUP(V3,Activities!$A$9:$Q$227,2,FALSE) -> [Mm2] | W6: =VLOOKUP(W3,Activities!$A$9:$Q$227,2,FALSE) -> [PJ] | X6: =VLOOKUP(X3,Activities!$A$9:$Q$227,2,FALSE) -> [PJ] | ... GG6: =VLOOKUP(GG3,Activities!$A$9:$Q$227,2,FALSE) -> [Mton_CO2]
A7: Res01_01 | B7: =IF(Technologies!B7<>0,Technologies!B7,"") -> Gebouwde omgeving | C7: =VLOOKUP($A7,Technologies!$A$7:$H$576,3,FALSE) -> Final | D7: =VLOOKUP($A7,Technologies!$A$7:$H$576,4,FALSE) -> Residential | E7: =VLOOKUP($A7,Technologies!$A$7:$H$576,6,FALSE) -> Electricity demand - Residential | F7: =VLOOKUP($A7,Technologies!$A$7:$H$576,7,FALSE) -> Dummy standard electricity consumption - Residential | I7: {=-SUMPRODUCT((Feedstocks!$C$4:$C$141=A7)*Feedstocks!$E$4:$E$141,Feedstocks!$F$4:$F$141,Feedstocks!$H$4:$H$141,Feedstocks!$I$4:$I$141)} -> 0 | J7: {=-SUMPRODUCT((Feedstocks!$C$4:$C$141=A7)*Feedstocks!$E$4:$E$141,Feedstocks!$H$4:$H$141,Feedstocks!$I$4:$I$141)} -> 0 | N7: =VLOOKUP(E7,Activities!$A$9:$M$227,13,FALSE) -> NL | P7: [1] | Q7: 1 | DI7: -1 | GC7: =ROUND(IF($C7="Primary",0,-$G7*(SUMPRODUCT($Q$4:$GA$4,$Q7:$GA7)+$J7)-$H7)*IF($N7=GC$4,1,0),4) -> 0 | GD7: =ROUND(IF($C7="Primary",0,$M7*(1-$O7)*($G7*(SUMPRODUCT($Q$4:$GA$4,$Q7:$GA7)+$J7)+$H7-SUMPRODUCT($Q$5:$GA$5,$Q7:$GA7)-$I7+$K7))*IF($N7=GD$4,1,0),4) -> 0 | GE7: =ROUND(IF($C7="Primary",0,(1-$M7)*(1-$O7)*($G7*(SUMPRODUCT($Q$4:$GA$4,$Q7:$GA7)+$J7)+$H7-SUMPRODUCT($Q$5:$GA$5,$Q7:$GA7)-$I7+$L7))*IF($N7=GD$4,1,0),4) -> 0 | GF7: =ROUND(IF($C7="Primary",0,$O7*($G7*(SUMPRODUCT($Q$4:$GA$4,$Q7:$GA7)+$J7)-SUMPRODUCT($Q$5:$GA$5,$Q7:$GA7)-$I7))*IF($N7=GD$4,1,0),4) -> 0 | GG7: =$I7 -> 0
A8: Res01_02 | B8: =IF(Technologies!B8<>0,Technologies!B8,"") -> Gebouwde omgeving | C8: =VLOOKUP($A8,Technologies!$A$7:$H$576,3,FALSE) -> Final | D8: =VLOOKUP($A8,Technologies!$A$7:$H$576,4,FALSE) -> Residential | E8: =VLOOKUP($A8,Technologies!$A$7:$H$576,6,FALSE) -> Electricity demand - Residential | F8: =VLOOKUP($A8,Technologies!$A$7:$H$576,7,FALSE) -> Flexible standard electricity consumption - Residential | I8: {=-SUMPRODUCT((Feedstocks!$C$4:$C$141=A8)*Feedstocks!$E$4:$E$141,Feedstocks!$F$4:$F$141,Feedstocks!$H$4:$H$141,Feedstocks!$I$4:$I$141)} -> 0 | J8: {=-SUMPRODUCT((Feedstocks!$C$4:$C$141=A8)*Feedstocks!$E$4:$E$141,Feedstocks!$H$4:$H$141,Feedstocks!$I$4:$I$141)} -> 0 | N8: =VLOOKUP(E8,Activities!$A$9:$M$227,13,FALSE) -> NL | P8: [1] | Q8: 1 | DI8: -1 | GC8: =ROUND(IF($C8="Primary",0,-$G8*(SUMPRODUCT($Q$4:$GA$4,$Q8:$GA8)+$J8)-$H8)*IF($N8=GC$4,1,0),4) -> 0 | GD8: =ROUND(IF($C8="Primary",0,$M8*(1-$O8)*($G8*(SUMPRODUCT($Q$4:$GA$4,$Q8:$GA8)+$J8)+$H8-SUMPRODUCT($Q$5:$GA$5,$Q8:$GA8)-$I8+$K8))*IF($N8=GD$4,1,0),4) -> 0 | GE8: =ROUND(IF($C8="Primary",0,(1-$M8)*(1-$O8)*($G8*(SUMPRODUCT($Q$4:$GA$4,$Q8:$GA8)+$J8)+$H8-SUMPRODUCT($Q$5:$GA$5,$Q8:$GA8)-$I8+$L8))*IF($N8=GD$4,1,0),4) -> 0 | GF8: =ROUND(IF($C8="Primary",0,$O8*($G8*(SUMPRODUCT($Q$4:$GA$4,$Q8:$GA8)+$J8)-SUMPRODUCT($Q$5:$GA$5,$Q8:$GA8)-$I8))*IF($N8=GD$4,1,0),4) -> 0 | GG8: =$I8 -> 0
A9: Res02_01 | B9: =IF(Technologies!B9<>0,Technologies!B9,"") -> Gebouwde omgeving | C9: =VLOOKUP($A9,Technologies!$A$7:$H$576,3,FALSE) -> Final | D9: =VLOOKUP($A9,Technologies!$A$7:$H$576,4,FALSE) -> Residential | E9: =VLOOKUP($A9,Technologies!$A$7:$H$576,6,FALSE) -> Houses - Residential Flats | F9: =VLOOKUP($A9,Technologies!$A$7:$H$576,7,FALSE) -> House with insulation GFE - Residential Flats | I9: {=-SUMPRODUCT((Feedstocks!$C$4:$C$141=A9)*Feedstocks!$E$4:$E$141,Feedstocks!$F$4:$F$141,Feedstocks!$H$4:$H$141,Feedstocks!$I$4:$I$141)} -> 0 | J9: {=-SUMPRODUCT((Feedstocks!$C$4:$C$141=A9)*Feedstocks!$E$4:$E$141,Feedstocks!$H$4:$H$141,Feedstocks!$I$4:$I$141)} -> 0 | N9: =VLOOKUP(E9,Activities!$A$9:$M$227,13,FALSE) -> NL | P9: [1] | R9: 1 | DJ9: -0.0305084 | GC9: =ROUND(IF($C9="Primary",0,-$G9*(SUMPRODUCT($Q$4:$GA$4,$Q9:$GA9)+$J9)-$H9)*IF($N9=GC$4,1,0),4) -> 0 | GD9: =ROUND(IF($C9="Primary",0,$M9*(1-$O9)*($G9*(SUMPRODUCT($Q$4:$GA$4,$Q9:$GA9)+$J9)+$H9-SUMPRODUCT($Q$5:$GA$5,$Q9:$GA9)-$I9+$K9))*IF($N9=GD$4,1,0),4) -> 0 | GE9: =ROUND(IF($C9="Primary",0,(1-$M9)*(1-$O9)*($G9*(SUMPRODUCT($Q$4:$GA$4,$Q9:$GA9)+$J9)+$H9-SUMPRODUCT($Q$5:$GA$5,$Q9:$GA9)-$I9+$L9))*IF($N9=GD$4,1,0),4) -> 0 | GF9: =ROUND(IF($C9="Primary",0,$O9*($G9*(SUMPRODUCT($Q$4:$GA$4,$Q9:$GA9)+$J9)-SUMPRODUCT($Q$5:$GA$5,$Q9:$GA9)-$I9))*IF($N9=GD$4,1,0),4) -> 0 | GG9: =$I9 -> 0
A10: Res02_02 | B10: =IF(Technologies!B10<>0,Technologies!B10,"") -> Gebouwde omgeving | C10: =VLOOKUP($A10,Technologies!$A$7:$H$576,3,FALSE) -> Final | D10: =VLOOKUP($A10,Technologies!$A$7:$H$576,4,FALSE) -> Residential | E10: =VLOOKUP($A10,Technologies!$A$7:$H$576,6,FALSE) -> Houses - Residential Flats | F10: =VLOOKUP($A10,Technologies!$A$7:$H$576,7,FALSE) -> House with insulation DC - Residential Flats | I10: {=-SUMPRODUCT((Feedstocks!$C$4:$C$141=A10)*Feedstocks!$E$4:$E$141,Feedstocks!$F$4:$F$141,Feedstocks!$H$4:$H$141,Feedstocks!$I$4:$I$141)} -> 0 | J10: {=-SUMPRODUCT((Feedstocks!$C$4:$C$141=A10)*Feedstocks!$E$4:$E$141,Feedstocks!$H$4:$H$141,Feedstocks!$I$4:$I$141)} -> 0 | N10: =VLOOKUP(E10,Activities!$A$9:$M$227,13,FALSE) -> NL | P10: [1] | R10: 1 | DJ10: -0.0293484 | GC10: =ROUND(IF($C10="Primary",0,-$G10*(SUMPRODUCT($Q$4:$GA$4,$Q10:$GA10)+$J10)-$H10)*IF($N10=GC$4,1,0),4) -> 0 | GD10: =ROUND(IF($C10="Primary",0,$M10*(1-$O10)*($G10*(SUMPRODUCT($Q$4:$GA$4,$Q10:$GA10)+$J10)+$H10-SUMPRODUCT($Q$5:$GA$5,$Q10:$GA10)-$I10+$K10))*IF($N10=GD$4,1,0),4) -> 0 | GE10: =ROUND(IF($C10="Primary",0,(1-$M10)*(1-$O10)*($G10*(SUMPRODUCT($Q$4:$GA$4,$Q10:$GA10)+$J10)+$H10-SUMPRODUCT($Q$5:$GA$5,$Q10:$GA10)-$I10+$L10))*IF($N10=GD$4,1,0),4) -> 0 | GF10: =ROUND(IF($C10="Primary",0,$O10*($G10*(SUMPRODUCT($Q$4:$GA$4,$Q10:$GA10)+$J10)-SUMPRODUCT($Q$5:$GA$5,$Q10:$GA10)-$I10))*IF($N10=GD$4,1,0),4) -> 0 | GG10: =$I10 -> 0
A11: Res02_03 | B11: =IF(Technologies!B11<>0,Technologies!B11,"") -> Gebouwde omgeving | C11: =VLOOKUP($A11,Technologies!$A$7:$H$576,3,FALSE) -> Final | D11: =VLOOKUP($A11,Technologies!$A$7:$H$576,4,FALSE) -> Residential | E11: =VLOOKUP($A11,Technologies!$A$7:$H$576,6,FALSE) -> Houses - Residential Flats | F11: =VLOOKUP($A11,Technologies!$A$7:$H$576,7,FALSE) -> House with insulation B - Residential Flats | I11: {=-SUMPRODUCT((Feedstocks!$C$4:$C$141=A11)*Feedstocks!$E$4:$E$141,Feedstocks!$F$4:$F$141,Feedstocks!$H$4:$H$141,Feedstocks!$I$4:$I$141)} -> 0 | J11: {=-SUMPRODUCT((Feedstocks!$C$4:$C$141=A11)*Feedstocks!$E$4:$E$141,Feedstocks!$H$4:$H$141,Feedstocks!$I$4:$I$141)} -> 0 | N11: =VLOOKUP(E11,Activities!$A$9:$M$227,13,FALSE) -> NL | P11: [1] | R11: 1 | DK11: -0.0267384 | GC11: =ROUND(IF($C11="Primary",0,-$G11*(SUMPRODUCT($Q$4:$GA$4,$Q11:$GA11)+$J11)-$H11)*IF($N11=GC$4,1,0),4) -> 0 | GD11: =ROUND(IF($C11="Primary",0,$M11*(1-$O11)*($G11*(SUMPRODUCT($Q$4:$GA$4,$Q11:$GA11)+$J11)+$H11-SUMPRODUCT($Q$5:$GA$5,$Q11:$GA11)-$I11+$K11))*IF($N11=GD$4,1,0),4) -> 0 | GE11: =ROUND(IF($C11="Primary",0,(1-$M11)*(1-$O11)*($G11*(SUMPRODUCT($Q$4:$GA$4,$Q11:$GA11)+$J11)+$H11-SUMPRODUCT($Q$5:$GA$5,$Q11:$GA11)-$I11+$L11))*IF($N11=GD$4,1,0),4) -> 0 | GF11: =ROUND(IF($C11="Primary",0,$O11*($G11*(SUMPRODUCT($Q$4:$GA$4,$Q11:$GA11)+$J11)-SUMPRODUCT($Q$5:$GA$5,$Q11:$GA11)-$I11))*IF($N11=GD$4,1,0),4) -> 0 | GG11: =$I11 -> 0
A12: Res02_04 | B12: =IF(Technologies!B12<>0,Technologies!B12,"") -> Gebouwde omgeving | C12: =VLOOKUP($A12,Technologies!$A$7:$H$576,3,FALSE) -> Final | D12: =VLOOKUP($A12,Technologies!$A$7:$H$576,4,FALSE) -> Residential | E12: =VLOOKUP($A12,Technologies!$A$7:$H$576,6,FALSE) -> Houses - Residential Flats | F12: =VLOOKUP($A12,Technologies!$A$7:$H$576,7,FALSE) -> House with insulation A - Residential Flats | I12: {=-SUMPRODUCT((Feedstocks!$C$4:$C$141=A12)*Feedstocks!$E$4:$E$141,Feedstocks!$F$4:$F$141,Feedstocks!$H$4:$H$141,Feedstocks!$I$4:$I$141)} -> 0 | J12: {=-SUMPRODUCT((Feedstocks!$C$4:$C$141=A12)*Feedstocks!$E$4:$E$141,Feedstocks!$H$4:$H$141,Feedstocks!$I$4:$I$141)} -> 0 | N12: =VLOOKUP(E12,Activities!$A$9:$M$227,13,FALSE) -> NL | P12: [1] | R12: 1 | DK12: -0.0206484 | GC12: =ROUND(IF($C12="Primary",0,-$G12*(SUMPRODUCT($Q$4:$GA$4,$Q12:$GA12)+$J12)-$H12)*IF($N12=GC$4,1,0),4) -> 0 | GD12: =ROUND(IF($C12="Primary",0,$M12*(1-$O12)*($G12*(SUMPRODUCT($Q$4:$GA$4,$Q12:$GA12)+$J12)+$H12-SUMPRODUCT($Q$5:$GA$5,$Q12:$GA12)-$I12+$K12))*IF($N12=GD$4,1,0),4) -> 0 | GE12: =ROUND(IF($C12="Primary",0,(1-$M12)*(1-$O12)*($G12*(SUMPRODUCT($Q$4:$GA$4,$Q12:$GA12)+$J12)+$H12-SUMPRODUCT($Q$5:$GA$5,$Q12:$GA12)-$I12+$L12))*IF($N12=GD$4,1,0),4) -> 0 | GF12: =ROUND(IF($C12="Primary",0,$O12*($G12*(SUMPRODUCT($Q$4:$GA$4,$Q12:$GA12)+$J12)-SUMPRODUCT($Q$5:$GA$5,$Q12:$GA12)-$I12))*IF($N12=GD$4,1,0),4) -> 0 | GG12: =$I12 -> 0
